Workbook

Sheet Anleitung
B2: Titel | C2: MatchZeit
B3: Urheber | C3: Claudia Bäuerlein
B4: Kontakt | C4: matchzeit@gmail.com
B5: Idee | C5: Das Tool ermöglicht die passende Software zur Arbeitszeiterfassung für Ihren Landwirtschaftlichen Betrieb zu finden.
C6: Die hinterlegte Datengrundlage kann mithilfe des Tabellenblatts "Programme_Grunddaten" jederzeit ergänzt und aktualisiert werden.
C7: Auf der Tool-Website werden dem Nutzer Fragen zu seinen individuellen Voraussetzungen und Bedürfnissen im Betrieb gestellt.
C8: Dem Matching von Nutzerantwort und Programm-Kriterium liegt ein Bewertungsscore zugrunde, der die
C9: maximal erreichbaren Punkte mit den erreichten Punkten in prozentualen Zusammenhang bringt.
C10: Nach einer Auswahl von max. 3 KO-Kriterien, werden als Ergebnis die drei passendsten Arbeitszeiterfassungssoftware angezeigt.
C11: Hier erhält der Nutzer Informationen und einen Link, der direkt auf die Unternehmenswebsite führt.
B12: Zielgruppe | C12: landwirtschaftliche Betriebe in Deutschland, die Arbeitszeiterfassung digitalisieren wollen
B13: Anleitung | C13: Datenpfleger | D13: Das Tabellenblatt "Programme_Grunddaten" aufrufen. Anweisungen dort folgen.
D14: Die anderen Tabellenblätter sind schreibgeschützt und werden für die Tool-Logik benötigt.
C15: Nutzer | D15: Link zum Tool anklicken, Erklärungen folgen
B16: Link zum Tool | C16: www.match-zeit.de

Sheet Programme_Grunddaten
A1: Titel | B1: Stammdaten und Bewertungsbasis
A2: Verantwortliche Person: | B2: Claudia Bäuerlein
A3: letzte Aktualisierung: | B3: 46178
A4: kurze Anleitung: | B4: Erfassen Sie hier neue Programme oder aktualisieren Sie bestehende Einträge.
B5: Bitte tragen Sie alle verfügbaren Informationen ein und bewerten Sie die Kriterien ausschließlich anhand der vorgegebenen Auswahlmöglichkeiten.
B6: Nutzen Sie die Kommentare in den Spaltenüberschriften als Orientierung für eine einheitliche Bewertung.
B7: Aktualisieren Sie den Bearbeitungsstatus nach Abschluss der Bearbeitung.
H8: Kriterium_ID | I8: K01 | J8: K02 | K8: K02.1 | L8: K02.1.1 | M8: K03 | N8: K04 | O8: K04.1 | P8: K04.2 | Q8: K05 | R8: K05.1 | S8: K06 | T8: K06.1 | U8: K06.2 | V8: K06.3 | W8: K07 | X8: K08 | Y8: K08.1 | Z8: K08.2 | AA8: K09 | AB8: K10 | AC8: K10.1 | AD8: K10.2 | AE8: K10.3 | AF8: K10.4 | AG8: K10.5 | AH8: K10.6 | AI8: K10.7 | AJ8: K11 | AK8: K12 | AL8: K13 | AM8: K14 | AN8: K15 | AO8: K16 | AP8: K17 | AQ8: K18 | AR8: K19 | AS8: K20 | AT8: K21 | AU8: K22 | AV8: K23 | AW8: K24 | AX8: K25
A9: Bearbeitungsstatus | B9: Programm_ID | C9: Programm_Name | D9: Anbieter | E9: Website | F9: Zielgruppe | G9: Kurzbeschreibung | H9: Kriterien | I9: open Source | J9: kommerziell (proprietär) | K9: kostenlose Version verfügbar | L9: Kostenmodell | M9: lokale Lösung (on-premise) | N9: cloud-/webbasiert | O9: Serverstandort, Hosting | P9: offline fähig (nachträgliche Synchronisation) | Q9: Erweiterbarkeit | R9: Schnittstelle zu DATEV | S9: Erfassungsmedium | T9: Smartphone (Browser, App) | U9: PC (webbasiert oder lokal installiert) | V9: Terminal | W9: EuGH konform | X9: Stand Alone Zeiterfassungsprogramm | Y9: Teil von HR-Programm | Z9: Teil von FMS | AA9: Zeiterfassung - Softwareaufbau | AB9: Zusatz- Features | AC9: Schichtplanung | AD9: Zutrittskontrolle | AE9: eAU | AF9: Urlaubsplanung | AG9: Personalakte | AH9: Arbeitszeitkonto | AI9: Tätigkeit- / Projekterfassung | AJ9: Anpassbarkeit | AK9: Sprachen | AL9: manuelle Eingabe | AM9: vollautomatisch (georeferenziert) | AN9: Geofencing | AO9: Bedien- und Zugriffsstruktur | AP9: Mandantenfähig | AQ9: Supportstruktur | AR9: Übersicht zur Datenauswertung | AS9: Korrekturen möglich | AT9: gesetzl. Pausen automatisch buchen | AU9: Überprüfung Arbeitszeitregeln / Pausenzeiten | AV9: Datenarchivierung | AW9: Besonderheiten | AX9: Preis | AY9: zuletzt geprüft am | AZ9: geprüft von | BA9: Kommentar
A10: Geprüft | B10: P01 | C10: Atoss | D10: ATOSS Software SE | E10: www.atoss.com | F10: alle Branchen | G10: digitales Workforce Management System | I10: Nein | J10: Ja | K10: Nein | M10: Nein | N10: Ja | Q10: offene Schnittstellen | R10: Ja | S10: App, Telefon, Terminal | T10: Ja | V10: Ja | W10: Ja | Y10: Ja | Z10: Nein | AB10: Ja | AC10: Ja | AF10: Ja | AG10: Ja | AI10: Ja | AK10: Deutsch, Englisch und andere | AL10: Ja | AM10: Nein | AQ10: Ja | AR10: Ja | AX10: keine Angabe | AY10: 46099 | AZ10: Claudia Bäuerlein
A11: Geprüft | B11: P02 | C11: ZEUS | D11: ISGUS GmbH | E11: www.isgus.de | F11: alle Branchen | G11: digitales Workforce Management System, mit Zeiterfassungsmodul | I11: Nein | J11: Ja | K11: Nein | M11: Nein | N11: Ja | O11: Deutschland | P11: Ja | Q11: offene Schnittstellen | R11: Ja | S11: App, Smartphone, Tablet, PC Terminal | T11: Ja | U11: Ja | V11: Ja | W11: Ja | Y11: Ja | Z11: Nein | AA11: modular | AB11: Ja | AC11: Ja | AD11: Ja | AF11: Ja | AG11: Ja | AH11: Ja | AI11: Ja | AK11: Deutsch und Englisch | AL11: Ja | AM11: Nein | AO11: rollenbasiert | AQ11: Ja | AR11: Ja | AS11: Ja | AU11: Ja | AW11: die Schichtbörse bietet den Mitarbeitern die Möglichkeit ihre Schichten digital zu tauschen, Evakuierungsübersicht: verspricht einen klaren Überblick über den Sicherheitsstatus der Mitarbeiter in kritischen Situationen, Open Source Teile des Codes sind verfügbar | AX11: keine Angabe | AY11: 46176 | AZ11: Claudia Bäuerlein
A12: Geprüft | B12: P03 | C12: GRÜN ZICOM | D12: GRÜN Software Group GmbH | E12: www.gruen.net | F12: Medien, Handel, Industrie | G12: Branchensoftware für Mittelstand | I12: Nein | J12: Ja | K12: Nein | L12: Abo / befristete Lizenz | M12: Ja | N12: Ja | P12: Ja | Q12: offene Schnittstellen | R12: Ja | S12: App, PC, Terminal | T12: Ja | U12: Ja | V12: Ja | W12: Ja | Y12: Ja | Z12: Nein | AA12: modular | AB12: Ja | AC12: Ja | AF12: Ja | AH12: Ja | AI12: Ja | AK12: Deutsch | AL12: Ja | AM12: Nein | AQ12: Ja | AR12: Ja | AS12: Ja | AX12: keine Angabe | AY12: 46100 | AZ12: Claudia Bäuerlein
A13: Geprüft | B13: P04 | C13: KRUTEC | D13: Krutec SoftCon GmbH | E13: www.krutec.de | F13: alle Branchen | G13: Fokus auf Zeiterfassung | I13: Nein | J13: Ja | K13: Nein | M13: Ja | N13: Ja | O13: Deutschland | Q13: offene Schnittstellen | R13: Ja | S13: Browser, App, Terminal | T13: Ja | U13: Ja | V13: Ja | W13: Ja | Y13: Ja | Z13: Nein | AA13: modular | AB13: Ja | AC13: Ja | AD13: Ja | AF13: Ja | AH13: Ja | AI13: Ja | AK13: Deutsch | AL13: Ja | AM13: Nein | AO13: rollenbasiert | AP13: Ja | AQ13: Ja | AR13: Ja | AS13: Ja | AU13: Ja | AW13: Standort bei Erfassung kann mit erfasst werden | AX13: keine Angabe | AY13: 46100 | AZ13: Claudia Bäuerlein
A14: Geprüft | B14: P05 | C14: meg, TiMaS | D14: mess-elektronik-groß GmbH | E14: www.megzeit.de | F14: Unternehmen, Behörden, Kleinbetrieb | G14: einfach, Arbeitszeiten erfassen, Zutritt steuern | I14: Nein | J14: Ja | K14: Nein | L14: einmalige Zahlung | M14: Ja | N14: Ja | O14: Deutschland | P14: Ja | Q14: offene Schnittstellen | R14: Ja | S14: App, Terminal, PC | T14: Ja | U14: Ja | V14: Ja | X14: Ja | Z14: Nein | AA14: modular | AB14: Ja | AD14: Ja | AF14: Ja | AH14: Ja | AI14: Ja | AK14: Deutsch und Englisch | AL14: Ja | AM14: Nein | AO14: rollenbasiert | AQ14: Ja | AR14: Ja | AS14: Ja | AW14: Standort bei Erfassung kann mit erfasst werden | AX14: z.B. Zeiterfassungssystem am Computer und per App einmalig 479 €, ab 10 Nutzern | AY14: 46101 | AZ14: Claudia Bäuerlein
A15: Geprüft | B15: P06 | C15: MobilZeit | D15: MobilZeit GmbH | E15: www.mobilzeit.de | F15: Handwerker, Dienstleistungsunternehmen | G15: Zeiterfassung, GPS-Ortung und Zutrittskontrolle | I15: Nein | J15: Ja | K15: Nein | M15: Nein | N15: Ja | Q15: offene Schnittstellen | R15: Ja | S15: App, Terminal, Box im Fahrzeug | T15: Ja | V15: Ja | X15: Ja | Z15: Nein | AA15: modular | AB15: Ja | AD15: Ja | AI15: Ja | AK15: Deutsch | AL15: Ja | AM15: Nein | AO15: rollenbasiert | AQ15: Ja | AR15: Ja | AW15: GPS Fahrzeugortung, zusätzliche Erfassung der Fahrzeugdaten z.B. Zündung An/Aus | AX15: keine Angabe | AY15: 46104 | AZ15: Claudia Bäuerlein
A16: Geprüft | B16: P07 | C16: Atoria, tisoware | D16: Atoria – the people software GmbH | E16: https://atoria-software.com/de, www.tisoware.com | F16: kleiner bis größerer Mittelstand | G16: modulare HR-Lösungen und Security Anwendungen | I16: Nein | J16: Ja | K16: Nein | L16: Abo / befristete Lizenz | M16: Nein | N16: Ja | Q16: offene Schnittstellen | R16: Ja | S16: App, PC, Terminal | T16: Ja | U16: Ja | V16: Ja | W16: Ja | Y16: Ja | Z16: Nein | AA16: modular | AB16: Ja | AC16: Ja | AD16: Ja | AE16: Ja | AF16: Ja | AG16: Ja | AI16: Ja | AL16: Ja | AM16: Nein | AO16: rollenbasiert | AQ16: Ja | AR16: Ja | AS16: Ja | AU16: Ja | AW16: bietet stationäre Terminals in Kooperation mit Praxispartnern an | AX16: Basismodell: 4 € / Nutzer / Monat | AY16: 46108 | AZ16: Claudia Bäuerlein
A17: Geprüft | B17: P08 | C17: venabo | D17: emvion Business Software GmbH | E17: www.venabo.de | F17: kleine und mittlere Unternehmen | G17: Zeiterfassung und IT-Service-Management | I17: Nein | J17: Ja | K17: Nein | L17: Abo / befristete Lizenz | M17: Nein | N17: Ja | P17: Ja | Q17: offene Schnittstellen | R17: Ja | S17: App, PC, Terminal | T17: Ja | U17: Ja | V17: Ja | W17: Ja | X17: Ja | Z17: Nein | AA17: modular | AB17: Ja | AC17: Ja | AD17: Ja | AE17: Ja | AF17: Ja | AG17: Ja | AI17: Ja | AK17: Deutsch, Englisch und andere | AL17: Ja | AM17: Nein | AO17: rollenbasiert | AQ17: Ja | AR17: Ja | AU17: Ja | AV17: revisionssicher mit Historienprotokoll | AW17: mit GPS Option, bietet stationäre Terminals in Kooperation mit Praxispartnern an | AX17: Beispielpaket für Landwirtschaft und Agrarhandel für 4,5 € / Nutzer / Monat | AY17: 46108 | AZ17: Claudia Bäuerlein
A18: Geprüft | B18: P09 | C18: ZMI. | D18: ZMI GmbH | E18: www.zmi.de | F18: kleine und mittlere Unternehmen, Konzern | G18: Zeiterfassung und HR | I18: Nein | J18: Ja | K18: Nein | M18: Ja | N18: Ja | O18: Deutschland | P18: Ja | Q18: offene Schnittstellen | R18: Ja | S18: App, PC, Terminal | T18: Ja | U18: Ja | V18: Ja | W18: Ja | X18: Ja | Z18: Nein | AA18: modular | AB18: Ja | AC18: Ja | AD18: Ja | AF18: Ja | AG18: Ja | AI18: Ja | AK18: Deutsch und Englisch | AL18: Ja | AM18: Nein | AO18: rollenbasiert | AP18: Ja | AQ18: Ja | AR18: Ja | AS18: Ja | AW18: bietet stationäre Terminals in Kooperation mit Praxispartnern an, Standort bei Erfassung kann mit erfasst werden | AX18: keine Angabe | AY18: 46108 | AZ18: Claudia Bäuerlein
A19: Geprüft | B19: P10 | C19: clockin | D19: clockin GmbH | E19: www.clockin.de | F19: Außendienst oder zuhause; Handwerker, Pflegekräfte und Vertriebsmitarbeiter | G19: einfache Zeiterfassung | I19: Nein | J19: Ja | K19: Nein | L19: Abo / befristete Lizenz | M19: Nein | N19: Ja | P19: Ja | Q19: offene Schnittstellen | R19: Ja | S19: App, PC | T19: Ja | U19: Ja | W19: Ja | X19: Ja | Z19: Nein | AA19: modular | AB19: Ja | AC19: Ja | AF19: Ja | AG19: Ja | AI19: Ja | AK19: Deutsch, Englisch und andere | AL19: Ja | AM19: Nein | AO19: rollenbasiert | AQ19: Ja | AR19: Ja | AS19: Ja | AU19: Ja | AW19: Standort bei Erfassung kann mit erfasst werden | AX19: Basismodell: 3,99 € / Nutzer / Monat | AY19: 46108 | AZ19: Claudia Bäuerlein
A20: Geprüft | B20: P11 | C20: clocko:do | D20: Clockodo GmbH | E20: www.clockodo.com | F20: alle Branchen | G20: einfache Zeiterfassung | I20: Nein | J20: Ja | K20: Nein | M20: Nein | N20: Ja | O20: Deutschland | P20: Ja | Q20: offene Schnittstellen | S20: App, PC | T20: Ja | U20: Ja | W20: Ja | Y20: Ja | Z20: Nein | AB20: Ja | AF20: Ja | AI20: Ja | AJ20: individuell programmierbar | AK20: Deutsch, Englisch und andere | AL20: Ja | AM20: Nein | AO20: rollenbasiert | AQ20: Ja | AR20: Ja | AS20: Ja | AU20: Ja | AW20: Über die API-Schnittstelle können Sie bei Bedarf Clockodo noch weiter nach Ihren Wünschen anpassen, mit Budgetüberwachung für Projekte, keine Anbindung an DATEV, aber vielen anderen Lohnbuchhaltungssystemen | AX20: Basismodell: 4 € / Nutzer / Monat | AY20: 46112 | AZ20: Claudia Bäuerlein
A21: Geprüft | B21: P12 | C21: Crewmeister | D21: ATOSS Aloud GmbH | E21: www.crewmeister.com | F21: alle Branchen | G21: Zeiterfassung: digital und zuverlässig | I21: Nein | J21: Ja | K21: Nein | L21: Abo / befristete Lizenz | M21: Ja | N21: Nein | O21: Deutschland | P21: Ja | Q21: offene Schnittstellen | R21: Ja | S21: App, PC | T21: Ja | U21: Ja | W21: Ja | X21: Ja | Z21: Nein | AA21: modular | AB21: Ja | AC21: Ja | AF21: Ja | AI21: Ja | AK21: Deutsch und Englisch | AL21: Ja | AM21: Nein | AO21: rollenbasiert | AQ21: Ja | AR21: Ja | AS21: Ja | AT21: Ja | AU21: Ja | AW21: GPS Erfassung möglich, Terminalmodus: standard PC / Tablet wird zu vollwertigem Zeiterfassungsterminal, umfangreiches Supportangebot | AX21: Basismodell: ab 1,5 € / Monat / Nutzer, bei jährlicher Abrechnung | AY21: 46112 | AZ21: Claudia Bäuerlein
A22: Geprüft | B22: P13 | C22: edtime | D22: eurodata AG | E22: www.ed-portal.de, https://www.edtime.de/ | F22: alle Branchen | G22: Personaleinsatzplanung und Zeiterfassung | I22: Nein | J22: Ja | K22: Nein | L22: Abo / befristete Lizenz | M22: Nein | N22: Ja | O22: Deutschland | Q22: offene Schnittstellen | S22: App, PC | T22: Ja | U22: Ja | W22: Ja | X22: Ja | Z22: Nein | AA22: modular | AB22: Ja | AC22: Ja | AE22: Ja | AF22: Ja | AK22: Deutsch | AL22: Ja | AM22: Nein | AO22: rollenbasiert | AQ22: Ja | AR22: Ja | AS22: Ja | AU22: Ja | AW22: GPS Standort kann bei Stempelung mit erfasst werden | AX22: 2,25 € / Monat / Mitarbeiter, Preis für jeden weiteren Mitarbeiter bei Kauf des Basispakets für 22,50 € / Monat inklusive 10 Mitarbeiter, Preis exklusive MwSt. | AY22: 46113 | AZ22: Claudia Bäuerlein
A23: Geprüft | B23: P14 | C23: HeavenHR 2.0 | D23: HeavenHR GmbH | E23: www.heavenhr.com | F23: kleine und mittlere Unternehmen | G23: Personalverwaltung und Echtzeit-Lohnabrechnung | I23: Nein | J23: Ja | K23: Nein | L23: Abo / befristete Lizenz | M23: Nein | N23: Ja | O23: Deutschland | Q23: offene Schnittstellen | S23: App, PC, Terminal | T23: Ja | U23: Ja | V23: Ja | Y23: Ja | Z23: Nein | AA23: modular | AB23: Ja | AF23: Ja | AG23: Ja | AK23: Deutsch und Englisch | AL23: Ja | AM23: Nein | AO23: rollenbasiert | AQ23: Ja | AR23: Ja | AS23: Ja | AV23: revisionssicher mit Historienprotokoll | AW23: Fokus liegt auf Lohnabrechnung | AX23: Modell mit Arbeitszeiterfassung: 5,5 € / Monat / Nutzer, Mindestpreis von 99 € | AY23: 46113 | AZ23: Claudia Bäuerlein
A24: Geprüft | B24: P15 | C24: prima:Time | D24: primatime.com s.r.o. | E24: www.primaerp.com | F24: Unternehmen oder Projektgruppen | G24: Projektmanagementsystem | I24: Nein | J24: Ja | K24: Nein | L24: Abo / befristete Lizenz | M24: Nein | N24: Ja | Q24: offene Schnittstellen | S24: App, PC | T24: Ja | U24: Ja | X24: Ja | Z24: Nein | AA24: modular | AB24: Ja | AI24: Ja | AK24: Deutsch, Englisch und andere | AL24: Ja | AM24: Nein | AO24: rollenbasiert | AQ24: Ja | AR24: Ja | AS24: Ja | AW24: Fokus auf Projektmanagement, besonders geeignet bei immer gleichen Stundenzahlen oder sich wiederholenden Aufgaben | AX24: Basismodell: 1,99 € / Monat / Nutzer, Preis ohne MwSt. | AY24: 46113 | AZ24: Claudia Bäuerlein
A25: Geprüft | B25: P16 | C25: TimeTell | D25: TimeTell B.V. | E25: www.timetell.de | F25: alle Branchen | G25: Software für Zeiterfassung und Planung | I25: Nein | J25: Ja | K25: Nein | L25: Abo / befristete Lizenz | M25: Nein | N25: Ja | Q25: offene Schnittstellen | R25: Ja | S25: App, PC, Terminal | T25: Ja | U25: Ja | V25: Ja | Y25: Ja | Z25: Nein | AA25: modular | AB25: Ja | AC25: Ja | AD25: Ja | AF25: Ja | AI25: Ja | AK25: Deutsch, Englisch und andere | AL25: Ja | AM25: Nein | AN25: Ja | AO25: rollenbasiert | AQ25: Ja | AR25: Ja | AW25: Geofencing beim An- und Abmelden (Mitarbeiter können sich nur in vorher definierten Bereich für Arbeit an- und abmelden) | AX25: Basismodell: einmalig 75 € + 3 € / Monat / Nutzer, ab 10 Nutzern | AY25: 46085 | AZ25: Claudia Bäuerlein
A26: Geprüft | B26: P17 | C26: REINER SCT timeCard | D26: REINER Kartengeräte GmbH und Co. KG | E26: www.timecard.de (reiner-sct), https://www.reiner-sct.com/timecard/ | F26: alle Branchen | G26: Zeiterfassung | I26: Nein | J26: Ja | K26: Nein | M26: Nein | N26: Ja | Q26: offene Schnittstellen | R26: Ja | S26: App, PC, Terminal | T26: Ja | U26: Ja | V26: Ja | W26: Ja | X26: Ja | Z26: Nein | AA26: modular | AB26: Ja | AD26: Ja | AE26: Ja | AF26: Ja | AI26: Ja | AK26: Deutsch und Englisch | AL26: Ja | AM26: Nein | AO26: rollenbasiert | AQ26: Ja | AX26: keine Angabe | AY26: 46085 | AZ26: Claudia Bäuerlein
A27: Geprüft | B27: P18 | C27: TIME&BILL | D27: Grobmeier Solutions GmbH | E27: www.timeandbill.de | F27: alle Branchen, kleinere Unternehmen und Teams | G27: einfache Zeiterfassung | I27: Ja | J27: Ja | K27: Nein | L27: Abo / befristete Lizenz | M27: Nein | N27: Ja | O27: Deutschland | Q27: offene Schnittstellen | S27: App, PC | T27: Ja | U27: Ja | X27: Ja | Z27: Nein | AA27: modular | AB27: Ja | AI27: Ja | AJ27: individuell programmierbar | AK27: Deutsch und Englisch | AL27: Ja | AM27: Nein | AO27: rollenbasiert | AQ27: Ja | AS27: Ja | AW27: bietet eine Open Source Variante | AX27: 5 € / Monat für 1 Benutzer, 15 € / Monat für bis zu 5 Benutzer, 40 € / Monat für bis zu 20 Benutzer | AY27: 46085 | AZ27: Claudia Bäuerlein
A28: Geprüft | B28: P19 | C28: timetac | D28: TimeTac GmbH | E28: www.timetac.com | F28: alle Branchen | G28: Zeiterfassung modular nach Unternehmensgröße | I28: Nein | J28: Ja | K28: Nein | L28: Abo / befristete Lizenz | M28: Nein | N28: Ja | O28: EU | P28: Ja | Q28: offene Schnittstellen | R28: Ja | S28: App, PC, Terminal | T28: Ja | U28: Ja | V28: Ja | W28: Ja | X28: Ja | Z28: Nein | AA28: modular | AB28: Ja | AF28: Ja | AI28: Ja | AK28: Deutsch, Englisch und andere | AL28: Ja | AM28: Nein | AO28: rollenbasiert | AQ28: Ja | AW28: Standort bei Erfassung kann mit erfasst werden, Verwaltung verschiedener Unternehmensstandorte möglich | AX28: Basismodell: 6,2 € / Monat / Nutzer + Basisgebühr + Nutzungsgebühr Module | AY28: 46120 | AZ28: Claudia Bäuerlein
A29: Geprüft | B29: P20 | C29: timr | D29: troii Software GmbH | E29: www.timr.com | F29: alle Branchen | G29: digitale Zeiterfassung | I29: Nein | J29: Ja | K29: Ja | L29: Abo / befristete Lizenz | M29: Nein | N29: Ja | O29: Deutschland | S29: App, PC, Terminal | T29: Ja | U29: Ja | V29: Ja | W29: Ja | X29: Ja | Z29: Nein | AA29: modular | AB29: Ja | AF29: Ja | AH29: Ja | AI29: Ja | AK29: Deutsch, Englisch und andere | AL29: Ja | AM29: Nein | AN29: Ja | AO29: rollenbasiert | AQ29: Ja | AR29: Ja | AT29: Ja | AU29: Ja | AW29: Standort bei Erfassung kann mit erfasst werden, Geofencing, freie Version für nur einen Benutzer | AX29: 1 Nutzer ist gratis | AY29: 46120 | AZ29: Claudia Bäuerlein
A30: Geprüft | B30: P21 | C30: Simple WebApps | D30: Harald Hornung | E30: www.simple-webapps.de | F30: kleine und mittelständige Organisationen | G30: basic Zeiterfassung | I30: Nein | J30: Ja | K30: Nein | L30: Abo / befristete Lizenz | M30: Ja | N30: Nein | Q30: offene Schnittstellen | R30: Ja | S30: Browser, Terminal | U30: Ja | V30: Ja | X30: Ja | Z30: Nein | AA30: modular | AB30: Ja | AC30: Ja | AF30: Ja | AI30: Ja | AL30: Ja | AM30: Nein | AQ30: Ja | AW30: Design der Software kann an die des Unternehmens angepasst werden (Corporate Design) | AX30: keine Angabe | AY30: 46120 | AZ30: Claudia Bäuerlein
A31: Geprüft | B31: P22 | C31: Personizer | D31: Personizer GmbH & Co. KG | E31: https://www.personizer.com/de | F31: Unternehmen und Organisationen | G31: einfache Zeiterfassung | I31: Nein | J31: Ja | K31: Nein | L31: Abo / befristete Lizenz | M31: Ja | N31: Nein | O31: EU | Q31: offene Schnittstellen | R31: Ja | S31: App, (PWA), Browser | T31: Ja | U31: Ja | W31: Ja | X31: Ja | Z31: Nein | AA31: modular | AB31: Ja | AE31: Ja | AF31: Ja | AG31: Ja | AH31: Ja | AI31: Ja | AK31: Deutsch und Englisch | AL31: Ja | AM31: Nein | AO31: rollenbasiert | AQ31: Ja | AR31: Ja | AS31: Ja | AV31: revisionssicher mit Historienprotokoll | AW31: Design der Software kann an die des Unternehmens angepasst werden (Corporate Design) | AX31: Basismodell Zeiterfassung: 3,7 € / Monat / Nutzer | AY31: 46120 | AZ31: Claudia Bäuerlein
A32: Geprüft | B32: P23 | C32: AGRARMONITOR | D32: betriko GmbH | E32: www.betriko.de | F32: Agrarmonitor, Lohnunternehmen, Ackerbau | G32: Dokumentation der Ackerarbeiten | I32: Nein | J32: Ja | K32: Nein | L32: Abo / befristete Lizenz | M32: Nein | N32: Ja | O32: Deutschland | Q32: offene Schnittstellen | R32: Ja | S32: App, Smartphone, Tablet | T32: Ja | U32: Ja | Z32: Ja | AA32: monolithisch | AB32: Ja | AF32: Ja | AI32: Ja | AK32: Deutsch | AL32: Ja | AM32: Nein | AO32: rollenbasiert | AQ32: Ja | AW32: umfassende Agrarmanagementsoftware | AX32: 2.900 € jährlich oder 29 € / Monat / aktivem Gerät | AY32: 46204 | AZ32: Claudia Bäuerlein
A33: Geprüft | B33: P24 | C33: askDANTE | D33: askDANTE systems GmbH | E33: https://www.askdante.com/ | F33: kleine und mittlere Unternehmen | G33: einfache Zeiterfassung | I33: Nein | J33: Ja | K33: Ja | L33: Abo / befristete Lizenz | M33: Nein | N33: Ja | Q33: offene Schnittstellen | R33: Ja | S33: App, PC, Terminal | T33: Ja | U33: Ja | V33: Ja | W33: Ja | X33: Ja | Z33: Nein | AA33: modular | AB33: Ja | AC33: Ja | AE33: Ja | AF33: Ja | AG33: Ja | AI33: Ja | AL33: Ja | AM33: Nein | AQ33: Ja | AU33: Ja | AW33: große Auswahl an Alarmregeln: von Arbeitszeitüberschreitung bis Dienstjubiläum | AX33: bis zu 5 Nutzer kostenfrei, dann 4,5 € / Monat / Nutzer | AY33: 46120 | AZ33: Claudia Bäuerlein
A34: Geprüft | B34: P25 | C34: agroprojekt | D34: agroproject Technologie- und Informationssysteme GmbH & Co.KG | E34: www.agroproject.de | F34: Landwirte, Betriebe mit Saisonarbeitskräften | G34: FMS mit integrierter Zeiterfassung insbesondere für Saisonarbeitskräfte | I34: Nein | J34: Ja | M34: Ja | N34: Nein | Q34: offene Schnittstellen | R34: Ja | S34: Mobilgeräte, Terminal | T34: Ja | V34: Ja | Z34: Ja | AA34: modular | AB34: Ja | AG34: Ja | AK34: Deutsch | AL34: Ja | AM34: Nein | AO34: rollenbasiert | AQ34: Ja | AR34: Ja | AW34: Standort bei Erfassung kann mit erfasst werden, Erntehelferverwaltung, Ackerschlagkartei mit Spracheingabe | AY34: 46204 | AZ34: Claudia Bäuerlein
A35: Geprüft | B35: P26 | C35: WorkingHours | D35: Timo Partl | E35: https://workinghoursapp.com/de | F35: alle Branchen | G35: einfache Zeiterfassungsapp | I35: Nein | J35: Ja | K35: Ja | M35: Nein | N35: Ja | Q35: offene Schnittstellen | S35: App | T35: Ja | X35: Ja | Z35: Nein | AA35: monolithisch | AB35: Ja | AI35: Ja | AL35: Ja | AM35: Ja | AN35: Ja | AO35: Einzelzugang | AR35: Ja | AW35: Daten werden im persönlichen Cloudspeicher gespeichert, GPS-Arbeitsplatzerkennung: Timer startet, wenn man zur Arbeit kommt, Geofencing | AX35: keine Angabe | AY35: 46121 | AZ35: Claudia Bäuerlein
A36: Geprüft | B36: P27 | C36: Kelio | D36: KELIO GmbH | E36: https://www.kelio.de/ | F36: alle Branchen | G36: Workforce management software | I36: Nein | J36: Ja | K36: Nein | M36: Ja | N36: Nein | Q36: offene Schnittstellen | S36: webbasiert, Browser, Terminal | U36: Ja | V36: Ja | Y36: Ja | Z36: Nein | AA36: modular | AB36: Ja | AC36: Ja | AD36: Ja | AF36: Ja | AH36: Ja | AI36: Ja | AK36: Deutsch, Englisch und andere | AL36: Ja | AM36: Nein | AQ36: Ja | AR36: Ja | AS36: Ja | AU36: Ja | AW36: Verwaltung mehrerer Unternehmen und Standorte | AX36: keine Angabe | AY36: 46121 | AZ36: Claudia Bäuerlein
A37: Geprüft | B37: P28 | C37: Personio | D37: Personio SE & Co. KG | E37: https://www.personio.de/ | F37: alle Branchen | G37: HR und Lohnbuchhaltung | I37: Nein | J37: Ja | L37: Abo / befristete Lizenz | M37: Nein | Q37: offene Schnittstellen | R37: Ja | S37: App, Terminal | T37: Ja | V37: Ja | Y37: Ja | Z37: Nein | AA37: modular | AB37: Ja | AG37: Ja | AK37: Deutsch, Englisch und andere | AL37: Ja | AM37: Nein | AQ37: Ja | AR37: Ja | AS37: Ja | AU37: Ja | AW37: umfassende HR-Management Software, mit KI Assistent | AX37: keine Angabe | AY37: 46121 | AZ37: Claudia Bäuerlein
A38: Geprüft | B38: P29 | C38: AIDA ORGA | D38: AIDA ORGA | E38: https://aida-orga.de/de/ | F38: alle Branchen | G38: HR- und Workforce Management | I38: Nein | J38: Ja | M38: Nein | N38: Ja | O38: Deutschland | Q38: offene Schnittstellen | R38: Ja | S38: App, Browser, Terminal, Terminalmodus | T38: Ja | U38: Ja | V38: Ja | W38: Ja | Y38: Ja | Z38: Nein | AA38: modular | AB38: Ja | AC38: Ja | AD38: Ja | AF38: Ja | AG38: Ja | AI38: Ja | AL38: Ja | AM38: Nein | AO38: rollenbasiert | AQ38: Ja | AR38: Ja | AS38: Ja | AV38: revisionssicher mit Historienprotokoll | AX38: keine Angabe | AY38: 46121 | AZ38: Claudia Bäuerlein
A39: Geprüft | B39: P30 | C39: Time 3010, Access 3010, PEP 3010, Peris 3010 | D39: AZS System AG | E39: https://azs.de/ | F39: alle Branchen | G39: Lösungen für Zeiterfassung, Zutrittskontrolle und Personaleinsatzplanung | I39: Nein | J39: Ja | K39: Nein | M39: Ja | N39: Ja | Q39: offene Schnittstellen | R39: Ja | S39: App, Browser, Terminal | T39: Ja | U39: Ja | V39: Ja | X39: Ja | Z39: Nein | AA39: modular | AB39: Ja | AC39: Ja | AD39: Ja | AE39: Ja | AF39: Ja | AG39: Ja | AK39: Deutsch und Englisch | AL39: Ja | AM39: Nein | AO39: rollenbasiert | AQ39: Ja | AR39: Ja | AS39: Ja | AX39: keine Angabe | AY39: 46121 | AZ39: Claudia Bäuerlein
A40: Geprüft | B40: P31 | C40: poool | D40: Poool Software & Consulting GmbH | E40: https://www.poool.cc/ | F40: alle Branchen, Schwerpunkt Dienstleistungsunternehmen | G40: ERP-Software | I40: Nein | J40: Ja | K40: Nein | L40: Abo / befristete Lizenz | M40: Nein | N40: Ja | O40: EU | Q40: offene Schnittstellen | R40: Ja | S40: App, PC | T40: Ja | U40: Ja | Y40: Ja | Z40: Nein | AA40: modular | AB40: Ja | AF40: Ja | AG40: Ja | AI40: Ja | AK40: Deutsch und Englisch | AL40: Ja | AM40: Nein | AO40: rollenbasiert | AQ40: Ja | AR40: Ja | AU40: Ja | AW40: ERP-Software mit Fokus auf Dienstleistungsunternehmen | AX40: Basislizenz: 99 € / Monat | AY40: 46121 | AZ40: Claudia Bäuerlein
A41: Geprüft | B41: P32 | C41: FrachtPilot | D41: FlexFleet Solutions GmbH | E41: www.frachtpilot.de | F41: Direktvermarktung, Lieferungen | I41: Nein | J41: Ja | K41: Nein | L41: Abo / befristete Lizenz | M41: Nein | N41: Ja | P41: Ja | Q41: offene Schnittstellen | R41: Ja | S41: App | T41: Ja | Z41: Ja | AA41: modular | AB41: Ja | AI41: Ja | AK41: Deutsch, Englisch und andere | AL41: Ja | AO41: rollenbasiert | AQ41: Ja | AR41: Ja | AW41: umfassende ERP-Software, Verwaltung von Erntehelfer möglich, Kernfunktionen App: Erntemengen- und Arbeitszeiterfassung | AX41: Basic: 106 € / Monat + zubuchbare Dienstleistungen | AY41: 46204 | AZ41: Claudia Bäuerlein
A42: Geprüft | B42: P33 | C42: gastromatic | D42: vertical cloud solution GmbH | E42: www.gastromatic.de | F42: Gastronomie, Einzelhandel, Logistik | I42: Nein | J42: Ja | K42: Nein | L42: Abo / befristete Lizenz | M42: Nein | N42: Ja | Q42: offene Schnittstellen | R42: Ja | S42: Smartphone, Tablet, PC | T42: Ja | U42: Ja | Z42: Nein | AB42: Ja | AC42: Ja | AE42: Ja | AG42: Ja | AK42: Deutsch, Englisch und andere | AL42: Ja | AM42: Nein | AO42: rollenbasiert | AQ42: Ja | AR42: Ja | AS42: Ja | AT42: Ja | AU42: Ja | AV42: revisionssicher mit Historienprotokoll | AW42: GPS Erfassung möglich | AX42: Basismodell: 6,95 € / Monat / Nutzer | AY42: 46204 | AZ42: Claudia Bäuerlein
A43: Geprüft | B43: P34 | C43: wiberry | D43: wiberry GmbH | E43: www.wiberry.de | F43: Witime, Gartenbau | G43: Prozessoptimierte Lösungen für Landwirte & Gärtner | I43: Nein | J43: Ja | M43: Nein | N43: Ja | Q43: offene Schnittstellen | R43: Ja | S43: Smartphone, Tablet, Terminal | T43: Ja | U43: Ja | V43: Ja | Z43: Ja | AB43: Ja | AG43: Ja | AI43: Ja | AK43: Deutsch, Englisch und andere | AO43: rollenbasiert | AQ43: Ja | AR43: Ja | AS43: Ja | AU43: Ja | AW43: spezielles Modul zur Erntehelferverwaltung | AY43: 46204 | AZ43: Claudia Bäuerlein
A44: Geprüft | B44: P35 | C44: galawork | D44: galabau workgroup GmbH | E44: www.galawork.de | F44: Garten- und Landschaftsbau | I44: Nein | J44: Ja | K44: Nein | L44: Abo / befristete Lizenz | M44: Nein | N44: Ja | O44: Deutschland | P44: Ja | Q44: offene Schnittstellen | S44: Smartphone, Tablet, PC | T44: Ja | U44: Ja | Z44: Nein | AA44: modular | AB44: Ja | AF44: Ja | AI44: Ja | AM44: Nein | AO44: rollenbasiert | AQ44: Ja | AR44: Ja | AW44: bildet kompletten Arbeitsprozess im Garten- und Landschaftsbau digital ab | AX44: 36 Monate Mindestvertragslaufzeit, Preis abhängig vom ausgewählten Modul und Nutzerzahl, einmalige Gebühr für Einrichtung und Schulung | AY44: 46204 | AZ44: Claudia Bäuerlein
A45: Geprüft | B45: P36 | C45: NEXT Farming | D45: AGCO GmbH | E45: https://www.nextfarming.de/software/next-farming-apps/ | F45: Zeiterfassung nur Schlagbezogen | G45: Dokumentation der Ackerarbeiten | I45: Nein | J45: Ja | K45: Nein | L45: Abo / befristete Lizenz | M45: Nein | N45: Ja | P45: Ja | Q45: offene Schnittstellen | S45: Smartphone, Tablet | T45: Ja | W45: Nein | Z45: Ja | AB45: Nein | AK45: Deutsch | AL45: Ja | AO45: rollenbasiert | AQ45: Ja | AR45: Ja | AW45: Zeiterfassung erfolgt Schlagbezogen, keine klassische Arbeitszeiterfassung, Integration der Daten in die NextFarming Schlagkartei möglich | AY45: 46204 | AZ45: Claudia Bäuerlein
A46: Geprüft | B46: P37 | C46: hr works | D46: Hrworks GmbH | E46: https://www.hrworks.de/ | F46: Mittelstand, kleine und mittlere Unternehmen | G46: HR-Software | I46: Nein | J46: Ja | K46: Nein | L46: Abo / befristete Lizenz | M46: Nein | N46: Ja | O46: EU | Q46: offene Schnittstellen | R46: Ja | S46: Smartphone, PC, Terminal | U46: Ja | V46: Ja | W46: Ja | Y46: Ja | Z46: Nein | AA46: monolithisch | AB46: Ja | AF46: Ja | AG46: Ja | AI46: Ja | AL46: Ja | AM46: Nein | AO46: rollenbasiert | AQ46: Ja | AR46: Ja | AT46: Ja | AV46: revisionssicher mit Historienprotokoll | AW46: Schnittstelle zu Papershift ermöglicht noch mehr Funktionen | AX46: mindestens 20 Nutzer | AY46: 46177 | AZ46: Claudia Bäuerlein
A47: Geprüft | B47: P38 | C47: SAP SuccessFactors Time Tracking | D47: SAP SE | E47: https://www.sap.com/germany/products/hcm/employee-time-tracking-software.html | F47: alle Branchen | G47: Teil eines umfassenden Management-Tools | I47: Nein | J47: Ja | K47: Nein | L47: Abo / befristete Lizenz | M47: Ja | N47: Ja | Q47: offene Schnittstellen | S47: Smartphone, PC, Terminal | U47: Ja | V47: Ja | W47: Ja | Y47: Ja | Z47: Nein | AA47: modular | AB47: Ja | AC47: Ja | AF47: Ja | AK47: Deutsch, Englisch und andere | AL47: Ja | AM47: Nein | AN47: Ja | AO47: rollenbasiert | AQ47: Ja | AR47: Ja | AU47: Ja | AW47: Geofencing beim An- und Abmelden (Mitarbeiter können sich nur in vorher definierten Bereich für Arbeit an- und abmelden) | AX47: 2,18 € / Nutzer / Monat | AY47: 46177 | AZ47: Claudia Bäuerlein
A48: Geprüft | B48: P39 | C48: factro | D48: Schuchert Managementberatung GmbH & Co. KG | E48: https://www.factro.de/ | F48: alle Branchen | G48: umfangreiches Projektmanagement mit integrierter Zeiterfassung | I48: Nein | J48: Ja | K48: Ja | L48: Abo / befristete Lizenz | M48: Nein | N48: Ja | Q48: offene Schnittstellen | S48: App, Browser, Terminal | T48: Ja | U48: Ja | V48: Ja | Y48: Ja | Z48: Nein | AA48: modular | AB48: Ja | AI48: Ja | AK48: Deutsch | AL48: Ja | AM48: Nein | AQ48: Ja | AR48: Ja | AW48: integrierter Projektplaner | AX48: Basic Projektplaner kostenlos bis zu 3 Nutzer, Modul mit Zeiterfassung: 29,99 € / Nutzer / Monat, ab 3 Nutzern | AY48: 46177 | AZ48: Claudia Bäuerlein
A49: Geprüft | B49: P40 | C49: TimO | D49: Time Management Office GmbH | E49: https://www.timo24.de/ | F49: alle Branchen | G49: modulare Softwarelösung für Unternehmen | I49: Nein | J49: Ja | K49: Nein | L49: Abo / befristete Lizenz | M49: Nein | N49: Ja | O49: Deutschland | P49: Ja | Q49: offene Schnittstellen | S49: App, PC, Terminal | T49: Ja | U49: Ja | V49: Ja | W49: Ja | Z49: Nein | AA49: modular | AB49: Ja | AC49: Ja | AF49: Ja | AI49: Ja | AK49: Deutsch und Englisch | AL49: Ja | AM49: Nein | AN49: Ja | AO49: rollenbasiert | AQ49: Ja | AR49: Ja | AS49: Ja | AT49: Ja | AV49: revisionssicher mit Historienprotokoll | AW49: Geofencing möglich | AX49: 4,99 € / Nutzer / Monat, mindestens 5 Nutzer | AY49: 46177 | AZ49: Claudia Bäuerlein
A50: Geprüft | B50: P41 | C50: ZEP | D50: ZEP GmbH | E50: https://www.zep.de/ | F50: Unternehmen | G50: Arbeitszeiterfassung bis Projekt-ERP | I50: Nein | J50: Ja | K50: Nein | L50: Abo / befristete Lizenz | M50: Nein | N50: Ja | O50: Deutschland | Q50: offene Schnittstellen | R50: Ja | S50: App, Browser, Terminal | T50: Ja | U50: Ja | V50: Ja | W50: Ja | Z50: Nein | AA50: modular | AB50: Ja | AF50: Ja | AI50: Ja | AK50: Deutsch und Englisch | AL50: Ja | AM50: Nein | AO50: rollenbasiert | AQ50: Ja | AR50: Ja | AS50: Ja | AW50: Integration von Kunden- oder Projektdaten aus anderen Systemen möglich | AX50: Basismodell: 2 € / Nutzer / Monat | AY50: 46177 | AZ50: Claudia Bäuerlein
A51: Geprüft | B51: P42 | C51: edtime | D51: eurodata AG | E51: https://www.edtime.de/ | F51: alle Branchen | G51: digitale Zeiterfassung und Personaleinsatzplanung | I51: Nein | J51: Ja | K51: Nein | L51: Abo / befristete Lizenz | M51: Nein | N51: Ja | O51: Deutschland | Q51: offene Schnittstellen | S51: App, Tablet, PC | T51: Ja | U51: Ja | Z51: Nein | AA51: modular | AB51: Ja | AC51: Ja | AE51: Ja | AF51: Ja | AG51: Ja | AH51: Ja | AK51: Deutsch | AL51: Ja | AM51: Nein | AO51: rollenbasiert | AQ51: Ja | AR51: Ja | AS51: Ja | AT51: Ja | AW51: die Schichtbörse bietet den Mitarbeitern die Möglichkeit ihre Schichten digital zu tauschen | AX51: Basismodul u.a. mit Zeiterfassung: 2,25 € / Nutzer / Monat, ab 10 Nutzern | AY51: 46178 | AZ51: Claudia Bäuerlein
A52: Geprüft | B52: P43 | C52: Papershift | D52: Papershift GmbH | E52: https://www.papershift.com/ | F52: alle Branchen | G52: digitale Personalverwaltung | I52: Nein | J52: Ja | K52: Nein | L52: Abo / befristete Lizenz | M52: Nein | N52: Ja | O52: Deutschland | Q52: offene Schnittstellen | R52: Ja | S52: App, Browser, Terminal | T52: Ja | U52: Ja | V52: Ja | Z52: Nein | AA52: modular | AB52: Ja | AC52: Ja | AF52: Ja | AG52: Ja | AH52: Ja | AK52: Deutsch und Englisch | AL52: Ja | AM52: Nein | AN52: Ja | AO52: rollenbasiert | AQ52: Ja | AT52: Ja | AV52: revisionssicher mit Historienprotokoll | AW52: Geofencing möglich | AX52: Basismodul: 4 € / Nutzer / Monat, ab 16 Nutzern | AY52: 46178 | AZ52: Claudia Bäuerlein
A53: Geprüft | B53: P44 | C53: ZEITGURU | D53: Aplano GmbH | E53: https://www.zeitguru.de/ | F53: alle Branchen | G53: digitale Zeiterfassung | I53: Nein | J53: Ja | K53: Nein | L53: Abo / befristete Lizenz | M53: Nein | N53: Ja | Q53: offene Schnittstellen | S53: Smartphone, Tablet, PC | T53: Ja | U53: Ja | X53: Ja | Z53: Nein | AA53: monolithisch | AB53: Ja | AC53: Ja | AF53: Ja | AK53: Deutsch | AL53: Ja | AM53: Nein | AN53: Ja | AO53: rollenbasiert | AQ53: Ja | AR53: Ja | AT53: Ja | AW53: Geofencing | AX53: 3,5 € / Nutzer / Monat, exkl. MwSt. | AY53: 46178 | AZ53: Claudia Bäuerlein
A54: Geprüft | B54: P45 | C54: Aplano | D54: Aplano GmbH | E54: https://www.aplano.de/ | F54: alle Branchen | G54: Personalplanung und Zeiterfassung | I54: Nein | J54: Ja | K54: Nein | L54: Abo / befristete Lizenz | M54: Nein | N54: Ja | Q54: offene Schnittstellen | S54: App, Browser, Terminal | T54: Ja | U54: Ja | V54: Ja | W54: Ja | Z54: Nein | AA54: modular | AB54: Ja | AC54: Ja | AF54: Ja | AG54: Ja | AK54: Deutsch und Englisch | AL54: Ja | AM54: Nein | AN54: Ja | AO54: rollenbasiert | AQ54: Ja | AR54: Ja | AU54: Ja | AW54: Geofencing, Hilfe durch KI Assistenten, digitale Schichtbörse | AX54: 4,5 € / Nutzer / Monat | AY54: 46178 | AZ54: Claudia Bäuerlein
A55: Geprüft | B55: P46 | C55: GDI | D55: GDI Software GMbH | E55: https://www.gdi.de/zeiterfassungssoftware/ | F55: kleine und mittlere Unternehmen | G55: Zeiterfassungssoftware | I55: Nein | J55: Ja | K55: Nein | L55: Abo / befristete Lizenz | M55: Nein | N55: Ja | Q55: offene Schnittstellen | R55: Ja | S55: App, Browser, Terminal | T55: Ja | U55: Ja | V55: Ja | W55: Ja | Y55: Ja | Z55: Nein | AB55: Ja | AC55: Ja | AF55: Ja | AI55: Ja | AL55: Ja | AM55: Nein | AN55: Ja | AO55: rollenbasiert | AQ55: Ja | AR55: Ja | AW55: Geofencing, Erfassung von Gerätezeiten | AX55: 4 € / Nutzer / Monat | AY55: 46178 | AZ55: Claudia Bäuerlein
A56: Geprüft | B56: P47 | C56: Shiftbase | D56: Shiftbase B.V. | E56: https://www.shiftbase.com/de/ | F56: Schichtbetriebe | G56: Dienstplanung und Zeiterfassung | I56: Nein | J56: Ja | K56: Ja | L56: Abo / befristete Lizenz | M56: Nein | N56: Ja | Q56: offene Schnittstellen | R56: Ja | S56: App, Desktop, Terminal | T56: Ja | V56: Ja | Z56: Nein | AB56: Ja | AC56: Ja | AF56: Ja | AG56: Ja | AK56: Deutsch, Englisch und andere | AL56: Ja | AM56: Nein | AN56: Ja | AO56: rollenbasiert | AQ56: Ja | AR56: Ja | AS56: Ja | AT56: Ja | AU56: Ja | AV56: revisionssicher mit Historienprotokoll | AW56: Geofencing, optimiert für Schichtarbeitbetriebe, Multi-Faktor-Authentifizierung (MFA) beim Login möglich | AX56: einfache Zeiterfassung bis 15 Nutzer kostenlos, Basic-Modul (mit weitere Funktionen) 30 € / Monat für 6 Nutzer | AY56: 46178 | AZ56: Claudia Bäuerlein
A57: Geprüft | B57: P48 | C57: TimeTrack | D57: TimeTrack GmbH | E57: https://www.timetrackapp.com/ | F57: mittelständige und große Unternehmen | G57: Zeiterfassung und Personaleinsatzplanung | I57: Nein | J57: Ja | K57: Ja | L57: Abo / befristete Lizenz | M57: Ja | N57: Ja | P57: Ja | Q57: offene Schnittstellen | R57: Ja | S57: Smartphone, Tablet, PC, Terminal | T57: Ja | U57: Ja | V57: Ja | Y57: Nein | Z57: Nein | AA57: modular | AB57: Ja | AC57: Ja | AD57: Ja | AE57: Ja | AF57: Ja | AI57: Ja | AK57: Deutsch und Englisch | AL57: Ja | AM57: Nein | AN57: Ja | AO57: rollenbasiert | AQ57: Ja | AR57: Ja | AW57: rechtskonforme Reisekostenabrechnung möglich, über Web oder als Lokale Lösung verfügbar, Standorterfassung bei Buchung möglich | AX57: Basismodell: 5 € / Nutzer / Monat, kostenlose Version für einen Einzelzugang | AY57: 46199 | AZ57: Claudia Bäuerlein
A58: Geprüft | B58: P49 | C58: 123erfasst | D58: 123erfasst.de GmbH, Unternehmen der NEVARIS Bausoftware GmbH | E58: https://123erfasst.de/personal/ | F58: Handwerker, Bauunternehmen | G58: digitale Zeiterfassung und Personalmanagement | I58: Nein | J58: Ja | K58: Ja | L58: Abo / befristete Lizenz | M58: Nein | N58: Ja | P58: Ja | Q58: offene Schnittstellen | S58: Smartphone, Tablet | T58: Ja | Z58: Nein | AA58: modular | AB58: Ja | AI58: Ja | AK58: Deutsch, Englisch und andere | AL58: Ja | AM58: Nein | AO58: rollenbasiert | AQ58: Ja | AR58: Ja | AW58: Standort kann bei Bedarf bei Stempelung mit erfasst werden, Führung eines Bautagebuchs möglich mit Dokumentation von Leistungen, Zeiten, Kommentaren und Fotos | AX58: bis zu 10 Nutzer kostenlos, Standard: 8,40 € / Nutzer / Monat | AY58: 46202 | AZ58: Claudia Bäuerlein
A59: Geprüft | B59: P50 | C59: clockify | D59: CAKE.com Inc. | E59: https://clockify.me/de/ | F59: alle Branchen | G59: Zeiterfassungs - und Arbeitstabellenapp | I59: Nein | J59: Ja | K59: Ja | M59: Nein | N59: Ja | Q59: offene Schnittstellen | S59: App für Smartphone und Desktop | T59: Ja | U59: Ja | Z59: Nein | AA59: modular | AB59: Ja | AF59: Ja | AI59: Ja | AK59: Deutsch, Englisch und andere | AL59: Ja | AM59: Nein | AO59: rollenbasiert | AQ59: Ja | AR59: Ja | AW59: Auto-Tracker: besuchte Apps und Webseiten können während der Arbeitszeit dokumentiert werden, GPS Verfolgung während der Arbeitszeit möglich | AX59: bis 5 Nutzer kostenlos, | AY59: 46202 | AZ59: Claudia Bäuerlein
A60: Geprüft | B60: P51 | C60: harvest | D60: Bending Spoons US Inc. | E60: https://www.getharvest.com/ | F60: Landwirtschaft | G60: Zeiterfassung und Verwaltung von Arbeitskräften | I60: Nein | J60: Ja | K60: Ja | L60: Abo / befristete Lizenz | M60: Nein | N60: Ja | Q60: offene Schnittstellen | R60: Nein | S60: Mobilgerät, Desktop, Browser | T60: Ja | U60: Ja | Z60: Nein | AB60: Ja | AI60: Ja | AK60: Deutsch, Englisch und andere | AM60: Nein | AQ60: Ja | AR60: Ja | AW60: GPS-Tracking möglich | AX60: kostenlose Version für einen Einzelzugang | AY60: 46203 | AZ60: Claudia Bäuerlein
A61: Neu | B61: P52 | C61: Everhour | D61: Everhour | E61: https://everhour.com/de
A62: Neu | B62: P53 | C62: factorial | D62: Factorial GmbH | E62: https://factorialhr.de/
A63: Neu | B63: P54 | C63: Hours TimeLord | E63: https://hourstimelord.com/
A64: Neu | B64: P55 | C64: Hubstaff | D64: Netsoft Holdings, LLC d/b/a Hubstaff | E64: https://hubstaff.com/
A65: Neu | B65: P56 | C65: Jibble | D65: Jibble Group | E65: https://www.jibble.io/de
A66: Neu | B66: P57 | C66: tellent | D66: Recruitee B.V. | E66: https://tellent.com/de/hr-manage/zeiterfassung
A67: Neu | B67: P58 | C67: MomoZeit | D67: ProntoWeb GmbH | E67: https://momozeit.de/
A68: Neu | B68: P59 | C68: Monday | E68: https://support.monday.com/hc/de
A69: Neu | B69: P60 | C69: myhours | E69: https://myhours.com/
A70: Neu | B70: P61 | C70: TimeCamp | D70: TimeCamp. Inc. | E70: https://www.timecamp.com/de/
A71: Neu | B71: P62 | C71: Time Doctor | E71: https://www.timedoctor.com/
A72: Neu | B72: P63 | C72: timeghost | D72: timeghost GmbH | E72: https://www.timetracking.timeghost.io/
A73: Neu | B73: P64 | C73: TimeLine ERP | D73: Gebauer GmbH | E73: https://www.timeline-erp.com/de/
A74: Neu | B74: P65 | C74: Timely | D74: Timely AS | E74: https://www.timely.com/cro/variantd
A75: Neu | B75: P66 | C75: TimePunch | D75: TimePunch KG | E75: https://timepunch.de/
A76: Neu | B76: P67 | C76: ordio | D76: Ordio GmbH | E76: https://www.ordio.com/
A77: Neu | B77: P68 | C77: Staffmatic | D77: EASYPEP | E77: https://staffomatic.com/de/
A78: Neu | B78: P69 | C78: SpikeTime | D78: SpikeTime Zeiterfassung - Andreas Seiler und Axel Schulze GbR | E78: https://www.spiketime.de/
A79: Neu | B79: P70 | C79: Kimai | D79: Kevin Papst | E79: https://www.kimai.org/de/
A80: Neu | B80: P71 | C80: memtime (Add-on für Kantata OX) | D80: memtime GmbH | E80: https://www.memtime.com/de
A81: Neu | B81: P72 | C81: timeBuzzer | D81: timeBuzzer GmbH | E81: https://timebuzzer.com/de/
A82: Neu | B82: P73 | C82: awork | D82: awork GmbH | E82: https://www.awork.com/de
A83: Neu | B83: P74 | C83: factro | D83: Schuchert Managementberatung GmbH & Co. KG | E83: https://www.factro.de/
... A95: Neu | B95: P86 | C95: Timicx | D95: Timicx GmbH | E95: https://www.timicx.de/
A96: Neu | B96: P87 | C96: todo.vu | E96: https://todo.vu/
A97: Neu | B97: P88 | C97: absence | D97: absence.io GmbH | E97: https://www.absence.io/de/
A98: Neu | B98: P89 | C98: teamspace | D98: 5 POINT AG | E98: https://www.teamspace.de/
A99: Neu | B99: P90 | C99: beebole | E99: https://beebole.com/
A100: Neu | B100: P91 | C100: connecteam | E100: https://connecteam.com/
A101: Neu | B101: P92 | C101: Monitask | E101: https://www.monitask.com/de/
A102: Neu | B102: P93 | C102: Paymo | D102: Paymo LLC | E102: https://www.paymoapp.com/de/
A103: Neu | B103: P94 | C103: EARLY (früher Timeular) | D103: TimeTac GmbH | E103: https://early.app/de/
A104: Neu | B104: P95 | C104: Sage | D104: Sage GmbH | E104: https://www.sage.com/de-de/hr-software/zeiterfassung/
A105: Neu | B105: P96 | C105: Interflex | D105: Interflex Datensysteme GmbH | E105: https://interflex.com/loesungen/zeiterfassung/
A106: Neu | B106: P97 | C106: SaaS | D106: EGOTEC AG | E106: https://www.saas.de/
A107: Neu | B107: P98 | C107: TimeMoto | D107: TimeMoto B.V. | E107: https://www.timemoto.com/de-de
A108: Neu | B108: P99 | C108: Miditec | D108: MIDITEC Datensysteme GmbH | E108: https://www.miditec.de/
A109: Neu | B109: P100 | C109: Datafox | D109: Datafox GmbH | E109: https://www.datafox.de/
A110: Neu | B110: P101 | C110: AENOS | D110: visionera GmbH | E110: https://www.aeonos.de/
A111: Neu | B111: P102 | C111: ringer | D111: ringer Zeiterfassung GmbH & Co. KG | E111: https://www.ringer.de/
...

Sheet programme_info
A1: programm_id | B1: programm_name | C1: anbieter | D1: website | E1: kurzbeschreibung | F1: zielgruppe | G1: erfassungsmedium | H1: besonderheiten | I1: preis
A2: =IF(AND(Programme_Grunddaten!$A10="Geprüft",Programme_Grunddaten!B10<>""),Programme_Grunddaten!B10,"") -> P01 | B2: =IF(AND(Programme_Grunddaten!$A10="Geprüft",Programme_Grunddaten!C10<>""),Programme_Grunddaten!C10,"") -> Atoss | C2: =IF(AND(Programme_Grunddaten!$A10="Geprüft",Programme_Grunddaten!D10<>""),Programme_Grunddaten!D10,"") -> ATOSS Software SE | D2: =IF(AND(Programme_Grunddaten!$A10="Geprüft",Programme_Grunddaten!E10<>""),Programme_Grunddaten!E10,"") -> www.atoss.com | E2: =IF(AND(Programme_Grunddaten!$A10="Geprüft",Programme_Grunddaten!G10<>""),Programme_Grunddaten!G10,"") -> digitales Workforce Management System | F2: =IF(AND(Programme_Grunddaten!$A10="Geprüft",Programme_Grunddaten!F10<>""),Programme_Grunddaten!F10,"") -> alle Branchen | G2: =IF(AND(Programme_Grunddaten!$A10="Geprüft",Programme_Grunddaten!S10<>""),Programme_Grunddaten!S10,"") -> App, Telefon, Terminal | H2: =IF(AND(Programme_Grunddaten!$A10="Geprüft",Programme_Grunddaten!AW10<>""),Programme_Grunddaten!AW10,"") | I2: =IF(AND(Programme_Grunddaten!$A10="Geprüft",Programme_Grunddaten!AX10<>""),Programme_Grunddaten!AX10,"") -> keine Angabe | K2: =IF(AND(programme_info!A11="Geprüft",Programme_Grunddaten!AW10<>""),Programme_Grunddaten!AW10,"")
A3: =IF(AND(Programme_Grunddaten!$A11="Geprüft",Programme_Grunddaten!B11<>""),Programme_Grunddaten!B11,"") -> P02 | B3: =IF(AND(Programme_Grunddaten!$A11="Geprüft",Programme_Grunddaten!C11<>""),Programme_Grunddaten!C11,"") -> ZEUS | C3: =IF(AND(Programme_Grunddaten!$A11="Geprüft",Programme_Grunddaten!D11<>""),Programme_Grunddaten!D11,"") -> ISGUS GmbH | D3: =IF(AND(Programme_Grunddaten!$A11="Geprüft",Programme_Grunddaten!E11<>""),Programme_Grunddaten!E11,"") -> www.isgus.de | E3: =IF(AND(Programme_Grunddaten!$A11="Geprüft",Programme_Grunddaten!G11<>""),Programme_Grunddaten!G11,"") -> digitales Workforce Management System, mit Zeiterfassungsmodul | F3: =IF(AND(Programme_Grunddaten!$A11="Geprüft",Programme_Grunddaten!F11<>""),Programme_Grunddaten!F11,"") -> alle Branchen | G3: =IF(AND(Programme_Grunddaten!$A11="Geprüft",Programme_Grunddaten!S11<>""),Programme_Grunddaten!S11,"") -> App, Smartphone, Tablet, PC Terminal | H3: =IF(AND(Programme_Grunddaten!$A11="Geprüft",Programme_Grunddaten!AW11<>""),Programme_Grunddaten!AW11,"") -> die Schichtbörse bietet den Mitarbeitern die Möglichkeit ihre Schichten digital zu tauschen, Evakuierungsübersicht: verspricht einen klaren Überblick über den Sicherheitsstatus der Mitarbeiter in kritischen Situationen, Open Source Teile des Codes sind verfügbar | I3: =IF(AND(Programme_Grunddaten!$A11="Geprüft",Programme_Grunddaten!AX11<>""),Programme_Grunddaten!AX11,"") -> keine Angabe
A4: =IF(AND(Programme_Grunddaten!$A12="Geprüft",Programme_Grunddaten!B12<>""),Programme_Grunddaten!B12,"") -> P03 | B4: =IF(AND(Programme_Grunddaten!$A12="Geprüft",Programme_Grunddaten!C12<>""),Programme_Grunddaten!C12,"") -> GRÜN ZICOM | C4: =IF(AND(Programme_Grunddaten!$A12="Geprüft",Programme_Grunddaten!D12<>""),Programme_Grunddaten!D12,"") -> GRÜN Software Group GmbH | D4: =IF(AND(Programme_Grunddaten!$A12="Geprüft",Programme_Grunddaten!E12<>""),Programme_Grunddaten!E12,"") -> www.gruen.net | E4: =IF(AND(Programme_Grunddaten!$A12="Geprüft",Programme_Grunddaten!G12<>""),Programme_Grunddaten!G12,"") -> Branchensoftware für Mittelstand | F4: =IF(AND(Programme_Grunddaten!$A12="Geprüft",Programme_Grunddaten!F12<>""),Programme_Grunddaten!F12,"") -> Medien, Handel, Industrie | G4: =IF(AND(Programme_Grunddaten!$A12="Geprüft",Programme_Grunddaten!S12<>""),Programme_Grunddaten!S12,"") -> App, PC, Terminal | H4: =IF(AND(Programme_Grunddaten!$A12="Geprüft",Programme_Grunddaten!AW12<>""),Programme_Grunddaten!AW12,"") | I4: =IF(AND(Programme_Grunddaten!$A12="Geprüft",Programme_Grunddaten!AX12<>""),Programme_Grunddaten!AX12,"") -> keine Angabe | K4: =IF(AND(programme_info!A13="Geprüft",Programme_Grunddaten!AW12<>""),Programme_Grunddaten!AW12,"")
A5: =IF(AND(Programme_Grunddaten!$A13="Geprüft",Programme_Grunddaten!B13<>""),Programme_Grunddaten!B13,"") -> P04 | B5: =IF(AND(Programme_Grunddaten!$A13="Geprüft",Programme_Grunddaten!C13<>""),Programme_Grunddaten!C13,"") -> KRUTEC | C5: =IF(AND(Programme_Grunddaten!$A13="Geprüft",Programme_Grunddaten!D13<>""),Programme_Grunddaten!D13,"") -> Krutec SoftCon GmbH | D5: =IF(AND(Programme_Grunddaten!$A13="Geprüft",Programme_Grunddaten!E13<>""),Programme_Grunddaten!E13,"") -> www.krutec.de | E5: =IF(AND(Programme_Grunddaten!$A13="Geprüft",Programme_Grunddaten!G13<>""),Programme_Grunddaten!G13,"") -> Fokus auf Zeiterfassung | F5: =IF(AND(Programme_Grunddaten!$A13="Geprüft",Programme_Grunddaten!F13<>""),Programme_Grunddaten!F13,"") -> alle Branchen | G5: =IF(AND(Programme_Grunddaten!$A13="Geprüft",Programme_Grunddaten!S13<>""),Programme_Grunddaten!S13,"") -> Browser, App, Terminal | H5: =IF(AND(Programme_Grunddaten!$A13="Geprüft",Programme_Grunddaten!AW13<>""),Programme_Grunddaten!AW13,"") -> Standort bei Erfassung kann mit erfasst werden | I5: =IF(AND(Programme_Grunddaten!$A13="Geprüft",Programme_Grunddaten!AX13<>""),Programme_Grunddaten!AX13,"") -> keine Angabe
A6: =IF(AND(Programme_Grunddaten!$A14="Geprüft",Programme_Grunddaten!B14<>""),Programme_Grunddaten!B14,"") -> P05 | B6: =IF(AND(Programme_Grunddaten!$A14="Geprüft",Programme_Grunddaten!C14<>""),Programme_Grunddaten!C14,"") -> meg, TiMaS | C6: =IF(AND(Programme_Grunddaten!$A14="Geprüft",Programme_Grunddaten!D14<>""),Programme_Grunddaten!D14,"") -> mess-elektronik-groß GmbH | D6: =IF(AND(Programme_Grunddaten!$A14="Geprüft",Programme_Grunddaten!E14<>""),Programme_Grunddaten!E14,"") -> www.megzeit.de | E6: =IF(AND(Programme_Grunddaten!$A14="Geprüft",Programme_Grunddaten!G14<>""),Programme_Grunddaten!G14,"") -> einfach, Arbeitszeiten erfassen, Zutritt steuern | F6: =IF(AND(Programme_Grunddaten!$A14="Geprüft",Programme_Grunddaten!F14<>""),Programme_Grunddaten!F14,"") -> Unternehmen, Behörden, Kleinbetrieb | G6: =IF(AND(Programme_Grunddaten!$A14="Geprüft",Programme_Grunddaten!S14<>""),Programme_Grunddaten!S14,"") -> App, Terminal, PC | H6: =IF(AND(Programme_Grunddaten!$A14="Geprüft",Programme_Grunddaten!AW14<>""),Programme_Grunddaten!AW14,"") -> Standort bei Erfassung kann mit erfasst werden | I6: =IF(AND(Programme_Grunddaten!$A14="Geprüft",Programme_Grunddaten!AX14<>""),Programme_Grunddaten!AX14,"") -> z.B. Zeiterfassungssystem am Computer und per App einmalig 479 €, ab 10 Nutzern
A7: =IF(AND(Programme_Grunddaten!$A15="Geprüft",Programme_Grunddaten!B15<>""),Programme_Grunddaten!B15,"") -> P06 | B7: =IF(AND(Programme_Grunddaten!$A15="Geprüft",Programme_Grunddaten!C15<>""),Programme_Grunddaten!C15,"") -> MobilZeit | C7: =IF(AND(Programme_Grunddaten!$A15="Geprüft",Programme_Grunddaten!D15<>""),Programme_Grunddaten!D15,"") -> MobilZeit GmbH | D7: =IF(AND(Programme_Grunddaten!$A15="Geprüft",Programme_Grunddaten!E15<>""),Programme_Grunddaten!E15,"") -> www.mobilzeit.de | E7: =IF(AND(Programme_Grunddaten!$A15="Geprüft",Programme_Grunddaten!G15<>""),Programme_Grunddaten!G15,"") -> Zeiterfassung, GPS-Ortung und Zutrittskontrolle | F7: =IF(AND(Programme_Grunddaten!$A15="Geprüft",Programme_Grunddaten!F15<>""),Programme_Grunddaten!F15,"") -> Handwerker, Dienstleistungsunternehmen | G7: =IF(AND(Programme_Grunddaten!$A15="Geprüft",Programme_Grunddaten!S15<>""),Programme_Grunddaten!S15,"") -> App, Terminal, Box im Fahrzeug | H7: =IF(AND(Programme_Grunddaten!$A15="Geprüft",Programme_Grunddaten!AW15<>""),Programme_Grunddaten!AW15,"") -> GPS Fahrzeugortung, zusätzliche Erfassung der Fahrzeugdaten z.B. Zündung An/Aus | I7: =IF(AND(Programme_Grunddaten!$A15="Geprüft",Programme_Grunddaten!AX15<>""),Programme_Grunddaten!AX15,"") -> keine Angabe
A8: =IF(AND(Programme_Grunddaten!$A16="Geprüft",Programme_Grunddaten!B16<>""),Programme_Grunddaten!B16,"") -> P07 | B8: =IF(AND(Programme_Grunddaten!$A16="Geprüft",Programme_Grunddaten!C16<>""),Programme_Grunddaten!C16,"") -> Atoria, tisoware | C8: =IF(AND(Programme_Grunddaten!$A16="Geprüft",Programme_Grunddaten!D16<>""),Programme_Grunddaten!D16,"") -> Atoria – the people software GmbH | D8: =IF(AND(Programme_Grunddaten!$A16="Geprüft",Programme_Grunddaten!E16<>""),Programme_Grunddaten!E16,"") -> https://atoria-software.com/de, www.tisoware.com | E8: =IF(AND(Programme_Grunddaten!$A16="Geprüft",Programme_Grunddaten!G16<>""),Programme_Grunddaten!G16,"") -> modulare HR-Lösungen und Security Anwendungen | F8: =IF(AND(Programme_Grunddaten!$A16="Geprüft",Programme_Grunddaten!F16<>""),Programme_Grunddaten!F16,"") -> kleiner bis größerer Mittelstand | G8: =IF(AND(Programme_Grunddaten!$A16="Geprüft",Programme_Grunddaten!S16<>""),Programme_Grunddaten!S16,"") -> App, PC, Terminal | H8: =IF(AND(Programme_Grunddaten!$A16="Geprüft",Programme_Grunddaten!AW16<>""),Programme_Grunddaten!AW16,"") -> bietet stationäre Terminals in Kooperation mit Praxispartnern an | I8: =IF(AND(Programme_Grunddaten!$A16="Geprüft",Programme_Grunddaten!AX16<>""),Programme_Grunddaten!AX16,"") -> Basismodell: 4 € / Nutzer / Monat
A9: =IF(AND(Programme_Grunddaten!$A17="Geprüft",Programme_Grunddaten!B17<>""),Programme_Grunddaten!B17,"") -> P08 | B9: =IF(AND(Programme_Grunddaten!$A17="Geprüft",Programme_Grunddaten!C17<>""),Programme_Grunddaten!C17,"") -> venabo | C9: =IF(AND(Programme_Grunddaten!$A17="Geprüft",Programme_Grunddaten!D17<>""),Programme_Grunddaten!D17,"") -> emvion Business Software GmbH | D9: =IF(AND(Programme_Grunddaten!$A17="Geprüft",Programme_Grunddaten!E17<>""),Programme_Grunddaten!E17,"") -> www.venabo.de | E9: =IF(AND(Programme_Grunddaten!$A17="Geprüft",Programme_Grunddaten!G17<>""),Programme_Grunddaten!G17,"") -> Zeiterfassung und IT-Service-Management | F9: =IF(AND(Programme_Grunddaten!$A17="Geprüft",Programme_Grunddaten!F17<>""),Programme_Grunddaten!F17,"") -> kleine und mittlere Unternehmen | G9: =IF(AND(Programme_Grunddaten!$A17="Geprüft",Programme_Grunddaten!S17<>""),Programme_Grunddaten!S17,"") -> App, PC, Terminal | H9: =IF(AND(Programme_Grunddaten!$A17="Geprüft",Programme_Grunddaten!AW17<>""),Programme_Grunddaten!AW17,"") -> mit GPS Option, bietet stationäre Terminals in Kooperation mit Praxispartnern an | I9: =IF(AND(Programme_Grunddaten!$A17="Geprüft",Programme_Grunddaten!AX17<>""),Programme_Grunddaten!AX17,"") -> Beispielpaket für Landwirtschaft und Agrarhandel für 4,5 € / Nutzer / Monat
A10: =IF(AND(Programme_Grunddaten!$A18="Geprüft",Programme_Grunddaten!B18<>""),Programme_Grunddaten!B18,"") -> P09 | B10: =IF(AND(Programme_Grunddaten!$A18="Geprüft",Programme_Grunddaten!C18<>""),Programme_Grunddaten!C18,"") -> ZMI. | C10: =IF(AND(Programme_Grunddaten!$A18="Geprüft",Programme_Grunddaten!D18<>""),Programme_Grunddaten!D18,"") -> ZMI GmbH | D10: =IF(AND(Programme_Grunddaten!$A18="Geprüft",Programme_Grunddaten!E18<>""),Programme_Grunddaten!E18,"") -> www.zmi.de | E10: =IF(AND(Programme_Grunddaten!$A18="Geprüft",Programme_Grunddaten!G18<>""),Programme_Grunddaten!G18,"") -> Zeiterfassung und HR | F10: =IF(AND(Programme_Grunddaten!$A18="Geprüft",Programme_Grunddaten!F18<>""),Programme_Grunddaten!F18,"") -> kleine und mittlere Unternehmen, Konzern | G10: =IF(AND(Programme_Grunddaten!$A18="Geprüft",Programme_Grunddaten!S18<>""),Programme_Grunddaten!S18,"") -> App, PC, Terminal | H10: =IF(AND(Programme_Grunddaten!$A18="Geprüft",Programme_Grunddaten!AW18<>""),Programme_Grunddaten!AW18,"") -> bietet stationäre Terminals in Kooperation mit Praxispartnern an, Standort bei Erfassung kann mit erfasst werden | I10: =IF(AND(Programme_Grunddaten!$A18="Geprüft",Programme_Grunddaten!AX18<>""),Programme_Grunddaten!AX18,"") -> keine Angabe
A11: =IF(AND(Programme_Grunddaten!$A19="Geprüft",Programme_Grunddaten!B19<>""),Programme_Grunddaten!B19,"") -> P10 | B11: =IF(AND(Programme_Grunddaten!$A19="Geprüft",Programme_Grunddaten!C19<>""),Programme_Grunddaten!C19,"") -> clockin | C11: =IF(AND(Programme_Grunddaten!$A19="Geprüft",Programme_Grunddaten!D19<>""),Programme_Grunddaten!D19,"") -> clockin GmbH | D11: =IF(AND(Programme_Grunddaten!$A19="Geprüft",Programme_Grunddaten!E19<>""),Programme_Grunddaten!E19,"") -> www.clockin.de | E11: =IF(AND(Programme_Grunddaten!$A19="Geprüft",Programme_Grunddaten!G19<>""),Programme_Grunddaten!G19,"") -> einfache Zeiterfassung | F11: =IF(AND(Programme_Grunddaten!$A19="Geprüft",Programme_Grunddaten!F19<>""),Programme_Grunddaten!F19,"") -> Außendienst oder zuhause; Handwerker, Pflegekräfte und Vertriebsmitarbeiter | G11: =IF(AND(Programme_Grunddaten!$A19="Geprüft",Programme_Grunddaten!S19<>""),Programme_Grunddaten!S19,"") -> App, PC | H11: =IF(AND(Programme_Grunddaten!$A19="Geprüft",Programme_Grunddaten!AW19<>""),Programme_Grunddaten!AW19,"") -> Standort bei Erfassung kann mit erfasst werden | I11: =IF(AND(Programme_Grunddaten!$A19="Geprüft",Programme_Grunddaten!AX19<>""),Programme_Grunddaten!AX19,"") -> Basismodell: 3,99 € / Nutzer / Monat
A12: =IF(AND(Programme_Grunddaten!$A20="Geprüft",Programme_Grunddaten!B20<>""),Programme_Grunddaten!B20,"") -> P11 | B12: =IF(AND(Programme_Grunddaten!$A20="Geprüft",Programme_Grunddaten!C20<>""),Programme_Grunddaten!C20,"") -> clocko:do | C12: =IF(AND(Programme_Grunddaten!$A20="Geprüft",Programme_Grunddaten!D20<>""),Programme_Grunddaten!D20,"") -> Clockodo GmbH | D12: =IF(AND(Programme_Grunddaten!$A20="Geprüft",Programme_Grunddaten!E20<>""),Programme_Grunddaten!E20,"") -> www.clockodo.com | E12: =IF(AND(Programme_Grunddaten!$A20="Geprüft",Programme_Grunddaten!G20<>""),Programme_Grunddaten!G20,"") -> einfache Zeiterfassung | F12: =IF(AND(Programme_Grunddaten!$A20="Geprüft",Programme_Grunddaten!F20<>""),Programme_Grunddaten!F20,"") -> alle Branchen | G12: =IF(AND(Programme_Grunddaten!$A20="Geprüft",Programme_Grunddaten!S20<>""),Programme_Grunddaten!S20,"") -> App, PC | H12: =IF(AND(Programme_Grunddaten!$A20="Geprüft",Programme_Grunddaten!AW20<>""),Programme_Grunddaten!AW20,"") -> Über die API-Schnittstelle können Sie bei Bedarf Clockodo noch weiter nach Ihren Wünschen anpassen, mit Budgetüberwachung für Projekte, keine Anbindung an DATEV, aber vielen anderen Lohnbuchhaltungssystemen | I12: =IF(AND(Programme_Grunddaten!$A20="Geprüft",Programme_Grunddaten!AX20<>""),Programme_Grunddaten!AX20,"") -> Basismodell: 4 € / Nutzer / Monat
A13: =IF(AND(Programme_Grunddaten!$A21="Geprüft",Programme_Grunddaten!B21<>""),Programme_Grunddaten!B21,"") -> P12 | B13: =IF(AND(Programme_Grunddaten!$A21="Geprüft",Programme_Grunddaten!C21<>""),Programme_Grunddaten!C21,"") -> Crewmeister | C13: =IF(AND(Programme_Grunddaten!$A21="Geprüft",Programme_Grunddaten!D21<>""),Programme_Grunddaten!D21,"") -> ATOSS Aloud GmbH | D13: =IF(AND(Programme_Grunddaten!$A21="Geprüft",Programme_Grunddaten!E21<>""),Programme_Grunddaten!E21,"") -> www.crewmeister.com | E13: =IF(AND(Programme_Grunddaten!$A21="Geprüft",Programme_Grunddaten!G21<>""),Programme_Grunddaten!G21,"") -> Zeiterfassung: digital und zuverlässig | F13: =IF(AND(Programme_Grunddaten!$A21="Geprüft",Programme_Grunddaten!F21<>""),Programme_Grunddaten!F21,"") -> alle Branchen | G13: =IF(AND(Programme_Grunddaten!$A21="Geprüft",Programme_Grunddaten!S21<>""),Programme_Grunddaten!S21,"") -> App, PC | H13: =IF(AND(Programme_Grunddaten!$A21="Geprüft",Programme_Grunddaten!AW21<>""),Programme_Grunddaten!AW21,"") -> GPS Erfassung möglich, Terminalmodus: standard PC / Tablet wird zu vollwertigem Zeiterfassungsterminal, umfangreiches Supportangebot | I13: =IF(AND(Programme_Grunddaten!$A21="Geprüft",Programme_Grunddaten!AX21<>""),Programme_Grunddaten!AX21,"") -> Basismodell: ab 1,5 € / Monat / Nutzer, bei jährlicher Abrechnung
A14: =IF(AND(Programme_Grunddaten!$A22="Geprüft",Programme_Grunddaten!B22<>""),Programme_Grunddaten!B22,"") -> P13 | B14: =IF(AND(Programme_Grunddaten!$A22="Geprüft",Programme_Grunddaten!C22<>""),Programme_Grunddaten!C22,"") -> edtime | C14: =IF(AND(Programme_Grunddaten!$A22="Geprüft",Programme_Grunddaten!D22<>""),Programme_Grunddaten!D22,"") -> eurodata AG | D14: =IF(AND(Programme_Grunddaten!$A22="Geprüft",Programme_Grunddaten!E22<>""),Programme_Grunddaten!E22,"") -> www.ed-portal.de, https://www.edtime.de/ | E14: =IF(AND(Programme_Grunddaten!$A22="Geprüft",Programme_Grunddaten!G22<>""),Programme_Grunddaten!G22,"") -> Personaleinsatzplanung und Zeiterfassung | F14: =IF(AND(Programme_Grunddaten!$A22="Geprüft",Programme_Grunddaten!F22<>""),Programme_Grunddaten!F22,"") -> alle Branchen | G14: =IF(AND(Programme_Grunddaten!$A22="Geprüft",Programme_Grunddaten!S22<>""),Programme_Grunddaten!S22,"") -> App, PC | H14: =IF(AND(Programme_Grunddaten!$A22="Geprüft",Programme_Grunddaten!AW22<>""),Programme_Grunddaten!AW22,"") -> GPS Standort kann bei Stempelung mit erfasst werden | I14: =IF(AND(Programme_Grunddaten!$A22="Geprüft",Programme_Grunddaten!AX22<>""),Programme_Grunddaten!AX22,"") -> 2,25 € / Monat / Mitarbeiter, Preis für jeden weiteren Mitarbeiter bei Kauf des Basispakets für 22,50 € / Monat inklusive 10 Mitarbeiter, Preis exklusive MwSt.
A15: =IF(AND(Programme_Grunddaten!$A23="Geprüft",Programme_Grunddaten!B23<>""),Programme_Grunddaten!B23,"") -> P14 | B15: =IF(AND(Programme_Grunddaten!$A23="Geprüft",Programme_Grunddaten!C23<>""),Programme_Grunddaten!C23,"") -> HeavenHR 2.0 | C15: =IF(AND(Programme_Grunddaten!$A23="Geprüft",Programme_Grunddaten!D23<>""),Programme_Grunddaten!D23,"") -> HeavenHR GmbH | D15: =IF(AND(Programme_Grunddaten!$A23="Geprüft",Programme_Grunddaten!E23<>""),Programme_Grunddaten!E23,"") -> www.heavenhr.com | E15: =IF(AND(Programme_Grunddaten!$A23="Geprüft",Programme_Grunddaten!G23<>""),Programme_Grunddaten!G23,"") -> Personalverwaltung und Echtzeit-Lohnabrechnung | F15: =IF(AND(Programme_Grunddaten!$A23="Geprüft",Programme_Grunddaten!F23<>""),Programme_Grunddaten!F23,"") -> kleine und mittlere Unternehmen | G15: =IF(AND(Programme_Grunddaten!$A23="Geprüft",Programme_Grunddaten!S23<>""),Programme_Grunddaten!S23,"") -> App, PC, Terminal | H15: =IF(AND(Programme_Grunddaten!$A23="Geprüft",Programme_Grunddaten!AW23<>""),Programme_Grunddaten!AW23,"") -> Fokus liegt auf Lohnabrechnung | I15: =IF(AND(Programme_Grunddaten!$A23="Geprüft",Programme_Grunddaten!AX23<>""),Programme_Grunddaten!AX23,"") -> Modell mit Arbeitszeiterfassung: 5,5 € / Monat / Nutzer, Mindestpreis von 99 €
A16: =IF(AND(Programme_Grunddaten!$A24="Geprüft",Programme_Grunddaten!B24<>""),Programme_Grunddaten!B24,"") -> P15 | B16: =IF(AND(Programme_Grunddaten!$A24="Geprüft",Programme_Grunddaten!C24<>""),Programme_Grunddaten!C24,"") -> prima:Time | C16: =IF(AND(Programme_Grunddaten!$A24="Geprüft",Programme_Grunddaten!D24<>""),Programme_Grunddaten!D24,"") -> primatime.com s.r.o. | D16: =IF(AND(Programme_Grunddaten!$A24="Geprüft",Programme_Grunddaten!E24<>""),Programme_Grunddaten!E24,"") -> www.primaerp.com | E16: =IF(AND(Programme_Grunddaten!$A24="Geprüft",Programme_Grunddaten!G24<>""),Programme_Grunddaten!G24,"") -> Projektmanagementsystem | F16: =IF(AND(Programme_Grunddaten!$A24="Geprüft",Programme_Grunddaten!F24<>""),Programme_Grunddaten!F24,"") -> Unternehmen oder Projektgruppen | G16: =IF(AND(Programme_Grunddaten!$A24="Geprüft",Programme_Grunddaten!S24<>""),Programme_Grunddaten!S24,"") -> App, PC | H16: =IF(AND(Programme_Grunddaten!$A24="Geprüft",Programme_Grunddaten!AW24<>""),Programme_Grunddaten!AW24,"") -> Fokus auf Projektmanagement, besonders geeignet bei immer gleichen Stundenzahlen oder sich wiederholenden Aufgaben | I16: =IF(AND(Programme_Grunddaten!$A24="Geprüft",Programme_Grunddaten!AX24<>""),Programme_Grunddaten!AX24,"") -> Basismodell: 1,99 € / Monat / Nutzer, Preis ohne MwSt.
... A122: =IF(AND(Programme_Grunddaten!$A130="Geprüft",Programme_Grunddaten!B130<>""),Programme_Grunddaten!B130,"") | B122: =IF(AND(Programme_Grunddaten!$A130="Geprüft",Programme_Grunddaten!C130<>""),Programme_Grunddaten!C130,"") | C122: =IF(AND(Programme_Grunddaten!$A130="Geprüft",Programme_Grunddaten!D130<>""),Programme_Grunddaten!D130,"") | D122: =IF(AND(Programme_Grunddaten!$A130="Geprüft",Programme_Grunddaten!E130<>""),Programme_Grunddaten!E130,"") | E122: =IF(AND(Programme_Grunddaten!$A130="Geprüft",Programme_Grunddaten!G130<>""),Programme_Grunddaten!G130,"") | F122: =IF(AND(Programme_Grunddaten!$A130="Geprüft",Programme_Grunddaten!F130<>""),Programme_Grunddaten!F130,"") | G122: =IF(AND(Programme_Grunddaten!$A130="Geprüft",Programme_Grunddaten!S130<>""),Programme_Grunddaten!S130,"") | H122: =IF(AND(Programme_Grunddaten!$A130="Geprüft",Programme_Grunddaten!AW130<>""),Programme_Grunddaten!AW130,"") | I122: =IF(AND(Programme_Grunddaten!$A130="Geprüft",Programme_Grunddaten!AX130<>""),Programme_Grunddaten!AX130,"")
A123: =IF(AND(Programme_Grunddaten!#REF!="Geprüft",Programme_Grunddaten!#REF!<>""),Programme_Grunddaten!#REF!,"") -> #REF! | B123: =IF(AND(Programme_Grunddaten!#REF!="Geprüft",Programme_Grunddaten!#REF!<>""),Programme_Grunddaten!#REF!,"") -> #REF! | C123: =IF(AND(Programme_Grunddaten!#REF!="Geprüft",Programme_Grunddaten!#REF!<>""),Programme_Grunddaten!#REF!,"") -> #REF! | D123: =IF(AND(Programme_Grunddaten!#REF!="Geprüft",Programme_Grunddaten!#REF!<>""),Programme_Grunddaten!#REF!,"") -> #REF! | E123: =IF(AND(Programme_Grunddaten!#REF!="Geprüft",Programme_Grunddaten!#REF!<>""),Programme_Grunddaten!#REF!,"") -> #REF! | F123: =IF(AND(Programme_Grunddaten!#REF!="Geprüft",Programme_Grunddaten!#REF!<>""),Programme_Grunddaten!#REF!,"") -> #REF! | G123: =IF(AND(Programme_Grunddaten!#REF!="Geprüft",Programme_Grunddaten!#REF!<>""),Programme_Grunddaten!#REF!,"") -> #REF! | H123: =IF(AND(Programme_Grunddaten!#REF!="Geprüft",Programme_Grunddaten!#REF!<>""),Programme_Grunddaten!#REF!,"") -> #REF! | I123: =IF(AND(Programme_Grunddaten!#REF!="Geprüft",Programme_Grunddaten!#REF!<>""),Programme_Grunddaten!#REF!,"") -> #REF!
A124: =IF(AND(Programme_Grunddaten!#REF!="Geprüft",Programme_Grunddaten!#REF!<>""),Programme_Grunddaten!#REF!,"") -> #REF! | B124: =IF(AND(Programme_Grunddaten!#REF!="Geprüft",Programme_Grunddaten!#REF!<>""),Programme_Grunddaten!#REF!,"") -> #REF! | C124: =IF(AND(Programme_Grunddaten!#REF!="Geprüft",Programme_Grunddaten!#REF!<>""),Programme_Grunddaten!#REF!,"") -> #REF! | D124: =IF(AND(Programme_Grunddaten!#REF!="Geprüft",Programme_Grunddaten!#REF!<>""),Programme_Grunddaten!#REF!,"") -> #REF! | E124: =IF(AND(Programme_Grunddaten!#REF!="Geprüft",Programme_Grunddaten!#REF!<>""),Programme_Grunddaten!#REF!,"") -> #REF! | F124: =IF(AND(Programme_Grunddaten!#REF!="Geprüft",Programme_Grunddaten!#REF!<>""),Programme_Grunddaten!#REF!,"") -> #REF! | G124: =IF(AND(Programme_Grunddaten!#REF!="Geprüft",Programme_Grunddaten!#REF!<>""),Programme_Grunddaten!#REF!,"") -> #REF! | H124: =IF(AND(Programme_Grunddaten!#REF!="Geprüft",Programme_Grunddaten!#REF!<>""),Programme_Grunddaten!#REF!,"") -> #REF! | I124: =IF(AND(Programme_Grunddaten!#REF!="Geprüft",Programme_Grunddaten!#REF!<>""),Programme_Grunddaten!#REF!,"") -> #REF!
A125: =IF(AND(Programme_Grunddaten!#REF!="Geprüft",Programme_Grunddaten!#REF!<>""),Programme_Grunddaten!#REF!,"") -> #REF! | B125: =IF(AND(Programme_Grunddaten!#REF!="Geprüft",Programme_Grunddaten!#REF!<>""),Programme_Grunddaten!#REF!,"") -> #REF! | C125: =IF(AND(Programme_Grunddaten!#REF!="Geprüft",Programme_Grunddaten!#REF!<>""),Programme_Grunddaten!#REF!,"") -> #REF! | D125: =IF(AND(Programme_Grunddaten!#REF!="Geprüft",Programme_Grunddaten!#REF!<>""),Programme_Grunddaten!#REF!,"") -> #REF! | E125: =IF(AND(Programme_Grunddaten!#REF!="Geprüft",Programme_Grunddaten!#REF!<>""),Programme_Grunddaten!#REF!,"") -> #REF! | F125: =IF(AND(Programme_Grunddaten!#REF!="Geprüft",Programme_Grunddaten!#REF!<>""),Programme_Grunddaten!#REF!,"") -> #REF! | G125: =IF(AND(Programme_Grunddaten!#REF!="Geprüft",Programme_Grunddaten!#REF!<>""),Programme_Grunddaten!#REF!,"") -> #REF! | H125: =IF(AND(Programme_Grunddaten!#REF!="Geprüft",Programme_Grunddaten!#REF!<>""),Programme_Grunddaten!#REF!,"") -> #REF! | I125: =IF(AND(Programme_Grunddaten!#REF!="Geprüft",Programme_Grunddaten!#REF!<>""),Programme_Grunddaten!#REF!,"") -> #REF!
A126: =IF(AND(Programme_Grunddaten!$A131="Geprüft",Programme_Grunddaten!B131<>""),Programme_Grunddaten!B131,"") | B126: =IF(AND(Programme_Grunddaten!$A131="Geprüft",Programme_Grunddaten!C131<>""),Programme_Grunddaten!C131,"") | C126: =IF(AND(Programme_Grunddaten!$A131="Geprüft",Programme_Grunddaten!D131<>""),Programme_Grunddaten!D131,"") | D126: =IF(AND(Programme_Grunddaten!$A131="Geprüft",Programme_Grunddaten!E131<>""),Programme_Grunddaten!E131,"") | E126: =IF(AND(Programme_Grunddaten!$A131="Geprüft",Programme_Grunddaten!G131<>""),Programme_Grunddaten!G131,"") | F126: =IF(AND(Programme_Grunddaten!$A131="Geprüft",Programme_Grunddaten!F131<>""),Programme_Grunddaten!F131,"") | G126: =IF(AND(Programme_Grunddaten!$A131="Geprüft",Programme_Grunddaten!S131<>""),Programme_Grunddaten!S131,"") | H126: =IF(AND(Programme_Grunddaten!$A131="Geprüft",Programme_Grunddaten!AW131<>""),Programme_Grunddaten!AW131,"") | I126: =IF(AND(Programme_Grunddaten!$A131="Geprüft",Programme_Grunddaten!AX131<>""),Programme_Grunddaten!AX131,"")
A127: =IF(AND(Programme_Grunddaten!$A132="Geprüft",Programme_Grunddaten!B132<>""),Programme_Grunddaten!B132,"") | B127: =IF(AND(Programme_Grunddaten!$A132="Geprüft",Programme_Grunddaten!C132<>""),Programme_Grunddaten!C132,"") | C127: =IF(AND(Programme_Grunddaten!$A132="Geprüft",Programme_Grunddaten!D132<>""),Programme_Grunddaten!D132,"") | D127: =IF(AND(Programme_Grunddaten!$A132="Geprüft",Programme_Grunddaten!E132<>""),Programme_Grunddaten!E132,"") | E127: =IF(AND(Programme_Grunddaten!$A132="Geprüft",Programme_Grunddaten!G132<>""),Programme_Grunddaten!G132,"") | F127: =IF(AND(Programme_Grunddaten!$A132="Geprüft",Programme_Grunddaten!F132<>""),Programme_Grunddaten!F132,"") | G127: =IF(AND(Programme_Grunddaten!$A132="Geprüft",Programme_Grunddaten!S132<>""),Programme_Grunddaten!S132,"") | H127: =IF(AND(Programme_Grunddaten!$A132="Geprüft",Programme_Grunddaten!AW132<>""),Programme_Grunddaten!AW132,"") | I127: =IF(AND(Programme_Grunddaten!$A132="Geprüft",Programme_Grunddaten!AX132<>""),Programme_Grunddaten!AX132,"")
A128: =IF(AND(Programme_Grunddaten!$A133="Geprüft",Programme_Grunddaten!B133<>""),Programme_Grunddaten!B133,"") | B128: =IF(AND(Programme_Grunddaten!$A133="Geprüft",Programme_Grunddaten!C133<>""),Programme_Grunddaten!C133,"") | C128: =IF(AND(Programme_Grunddaten!$A133="Geprüft",Programme_Grunddaten!D133<>""),Programme_Grunddaten!D133,"") | D128: =IF(AND(Programme_Grunddaten!$A133="Geprüft",Programme_Grunddaten!E133<>""),Programme_Grunddaten!E133,"") | E128: =IF(AND(Programme_Grunddaten!$A133="Geprüft",Programme_Grunddaten!G133<>""),Programme_Grunddaten!G133,"") | F128: =IF(AND(Programme_Grunddaten!$A133="Geprüft",Programme_Grunddaten!F133<>""),Programme_Grunddaten!F133,"") | G128: =IF(AND(Programme_Grunddaten!$A133="Geprüft",Programme_Grunddaten!S133<>""),Programme_Grunddaten!S133,"") | H128: =IF(AND(Programme_Grunddaten!$A133="Geprüft",Programme_Grunddaten!AW133<>""),Programme_Grunddaten!AW133,"") | I128: =IF(AND(Programme_Grunddaten!$A133="Geprüft",Programme_Grunddaten!AX133<>""),Programme_Grunddaten!AX133,"")
A129: =IF(AND(Programme_Grunddaten!$A134="Geprüft",Programme_Grunddaten!B134<>""),Programme_Grunddaten!B134,"") | B129: =IF(AND(Programme_Grunddaten!$A134="Geprüft",Programme_Grunddaten!C134<>""),Programme_Grunddaten!C134,"") | C129: =IF(AND(Programme_Grunddaten!$A134="Geprüft",Programme_Grunddaten!D134<>""),Programme_Grunddaten!D134,"") | D129: =IF(AND(Programme_Grunddaten!$A134="Geprüft",Programme_Grunddaten!E134<>""),Programme_Grunddaten!E134,"") | E129: =IF(AND(Programme_Grunddaten!$A134="Geprüft",Programme_Grunddaten!G134<>""),Programme_Grunddaten!G134,"") | F129: =IF(AND(Programme_Grunddaten!$A134="Geprüft",Programme_Grunddaten!F134<>""),Programme_Grunddaten!F134,"") | G129: =IF(AND(Programme_Grunddaten!$A134="Geprüft",Programme_Grunddaten!S134<>""),Programme_Grunddaten!S134,"") | H129: =IF(AND(Programme_Grunddaten!$A134="Geprüft",Programme_Grunddaten!AW134<>""),Programme_Grunddaten!AW134,"") | I129: =IF(AND(Programme_Grunddaten!$A134="Geprüft",Programme_Grunddaten!AX134<>""),Programme_Grunddaten!AX134,"")
A130: =IF(AND(Programme_Grunddaten!$A135="Geprüft",Programme_Grunddaten!B135<>""),Programme_Grunddaten!B135,"") | B130: =IF(AND(Programme_Grunddaten!$A135="Geprüft",Programme_Grunddaten!C135<>""),Programme_Grunddaten!C135,"") | C130: =IF(AND(Programme_Grunddaten!$A135="Geprüft",Programme_Grunddaten!D135<>""),Programme_Grunddaten!D135,"") | D130: =IF(AND(Programme_Grunddaten!$A135="Geprüft",Programme_Grunddaten!E135<>""),Programme_Grunddaten!E135,"") | E130: =IF(AND(Programme_Grunddaten!$A135="Geprüft",Programme_Grunddaten!G135<>""),Programme_Grunddaten!G135,"") | F130: =IF(AND(Programme_Grunddaten!$A135="Geprüft",Programme_Grunddaten!F135<>""),Programme_Grunddaten!F135,"") | G130: =IF(AND(Programme_Grunddaten!$A135="Geprüft",Programme_Grunddaten!S135<>""),Programme_Grunddaten!S135,"") | H130: =IF(AND(Programme_Grunddaten!$A135="Geprüft",Programme_Grunddaten!AW135<>""),Programme_Grunddaten!AW135,"") | I130: =IF(AND(Programme_Grunddaten!$A135="Geprüft",Programme_Grunddaten!AX135<>""),Programme_Grunddaten!AX135,"")
A131: =IF(AND(Programme_Grunddaten!$A136="Geprüft",Programme_Grunddaten!B136<>""),Programme_Grunddaten!B136,"") | B131: =IF(AND(Programme_Grunddaten!$A136="Geprüft",Programme_Grunddaten!C136<>""),Programme_Grunddaten!C136,"") | C131: =IF(AND(Programme_Grunddaten!$A136="Geprüft",Programme_Grunddaten!D136<>""),Programme_Grunddaten!D136,"") | D131: =IF(AND(Programme_Grunddaten!$A136="Geprüft",Programme_Grunddaten!E136<>""),Programme_Grunddaten!E136,"") | E131: =IF(AND(Programme_Grunddaten!$A136="Geprüft",Programme_Grunddaten!G136<>""),Programme_Grunddaten!G136,"") | F131: =IF(AND(Programme_Grunddaten!$A136="Geprüft",Programme_Grunddaten!F136<>""),Programme_Grunddaten!F136,"") | G131: =IF(AND(Programme_Grunddaten!$A136="Geprüft",Programme_Grunddaten!S136<>""),Programme_Grunddaten!S136,"") | H131: =IF(AND(Programme_Grunddaten!$A136="Geprüft",Programme_Grunddaten!AW136<>""),Programme_Grunddaten!AW136,"") | I131: =IF(AND(Programme_Grunddaten!$A136="Geprüft",Programme_Grunddaten!AX136<>""),Programme_Grunddaten!AX136,"")
A132: =IF(AND(Programme_Grunddaten!$A137="Geprüft",Programme_Grunddaten!B137<>""),Programme_Grunddaten!B137,"") | B132: =IF(AND(Programme_Grunddaten!$A137="Geprüft",Programme_Grunddaten!C137<>""),Programme_Grunddaten!C137,"") | C132: =IF(AND(Programme_Grunddaten!$A137="Geprüft",Programme_Grunddaten!D137<>""),Programme_Grunddaten!D137,"") | D132: =IF(AND(Programme_Grunddaten!$A137="Geprüft",Programme_Grunddaten!E137<>""),Programme_Grunddaten!E137,"") | E132: =IF(AND(Programme_Grunddaten!$A137="Geprüft",Programme_Grunddaten!G137<>""),Programme_Grunddaten!G137,"") | F132: =IF(AND(Programme_Grunddaten!$A137="Geprüft",Programme_Grunddaten!F137<>""),Programme_Grunddaten!F137,"") | G132: =IF(AND(Programme_Grunddaten!$A137="Geprüft",Programme_Grunddaten!S137<>""),Programme_Grunddaten!S137,"") | H132: =IF(AND(Programme_Grunddaten!$A137="Geprüft",Programme_Grunddaten!AW137<>""),Programme_Grunddaten!AW137,"") | I132: =IF(AND(Programme_Grunddaten!$A137="Geprüft",Programme_Grunddaten!AX137<>""),Programme_Grunddaten!AX137,"")
A133: =IF(AND(Programme_Grunddaten!$A138="Geprüft",Programme_Grunddaten!B138<>""),Programme_Grunddaten!B138,"") | B133: =IF(AND(Programme_Grunddaten!$A138="Geprüft",Programme_Grunddaten!C138<>""),Programme_Grunddaten!C138,"") | C133: =IF(AND(Programme_Grunddaten!$A138="Geprüft",Programme_Grunddaten!D138<>""),Programme_Grunddaten!D138,"") | D133: =IF(AND(Programme_Grunddaten!$A138="Geprüft",Programme_Grunddaten!E138<>""),Programme_Grunddaten!E138,"") | E133: =IF(AND(Programme_Grunddaten!$A138="Geprüft",Programme_Grunddaten!G138<>""),Programme_Grunddaten!G138,"") | F133: =IF(AND(Programme_Grunddaten!$A138="Geprüft",Programme_Grunddaten!F138<>""),Programme_Grunddaten!F138,"") | G133: =IF(AND(Programme_Grunddaten!$A138="Geprüft",Programme_Grunddaten!S138<>""),Programme_Grunddaten!S138,"") | H133: =IF(AND(Programme_Grunddaten!$A138="Geprüft",Programme_Grunddaten!AW138<>""),Programme_Grunddaten!AW138,"") | I133: =IF(AND(Programme_Grunddaten!$A138="Geprüft",Programme_Grunddaten!AX138<>""),Programme_Grunddaten!AX138,"")
A134: =IF(AND(Programme_Grunddaten!$A139="Geprüft",Programme_Grunddaten!B139<>""),Programme_Grunddaten!B139,"") | B134: =IF(AND(Programme_Grunddaten!$A139="Geprüft",Programme_Grunddaten!C139<>""),Programme_Grunddaten!C139,"") | C134: =IF(AND(Programme_Grunddaten!$A139="Geprüft",Programme_Grunddaten!D139<>""),Programme_Grunddaten!D139,"") | D134: =IF(AND(Programme_Grunddaten!$A139="Geprüft",Programme_Grunddaten!E139<>""),Programme_Grunddaten!E139,"") | E134: =IF(AND(Programme_Grunddaten!$A139="Geprüft",Programme_Grunddaten!G139<>""),Programme_Grunddaten!G139,"") | F134: =IF(AND(Programme_Grunddaten!$A139="Geprüft",Programme_Grunddaten!F139<>""),Programme_Grunddaten!F139,"") | G134: =IF(AND(Programme_Grunddaten!$A139="Geprüft",Programme_Grunddaten!S139<>""),Programme_Grunddaten!S139,"") | H134: =IF(AND(Programme_Grunddaten!$A139="Geprüft",Programme_Grunddaten!AW139<>""),Programme_Grunddaten!AW139,"") | I134: =IF(AND(Programme_Grunddaten!$A139="Geprüft",Programme_Grunddaten!AX139<>""),Programme_Grunddaten!AX139,"")
A135: =IF(AND(Programme_Grunddaten!$A140="Geprüft",Programme_Grunddaten!B140<>""),Programme_Grunddaten!B140,"") | B135: =IF(AND(Programme_Grunddaten!$A140="Geprüft",Programme_Grunddaten!C140<>""),Programme_Grunddaten!C140,"") | C135: =IF(AND(Programme_Grunddaten!$A140="Geprüft",Programme_Grunddaten!D140<>""),Programme_Grunddaten!D140,"") | D135: =IF(AND(Programme_Grunddaten!$A140="Geprüft",Programme_Grunddaten!E140<>""),Programme_Grunddaten!E140,"") | E135: =IF(AND(Programme_Grunddaten!$A140="Geprüft",Programme_Grunddaten!G140<>""),Programme_Grunddaten!G140,"") | F135: =IF(AND(Programme_Grunddaten!$A140="Geprüft",Programme_Grunddaten!F140<>""),Programme_Grunddaten!F140,"") | G135: =IF(AND(Programme_Grunddaten!$A140="Geprüft",Programme_Grunddaten!S140<>""),Programme_Grunddaten!S140,"") | H135: =IF(AND(Programme_Grunddaten!$A140="Geprüft",Programme_Grunddaten!AW140<>""),Programme_Grunddaten!AW140,"") | I135: =IF(AND(Programme_Grunddaten!$A140="Geprüft",Programme_Grunddaten!AX140<>""),Programme_Grunddaten!AX140,"")
A136: =IF(AND(Programme_Grunddaten!$A141="Geprüft",Programme_Grunddaten!B141<>""),Programme_Grunddaten!B141,"") | B136: =IF(AND(Programme_Grunddaten!$A141="Geprüft",Programme_Grunddaten!C141<>""),Programme_Grunddaten!C141,"") | C136: =IF(AND(Programme_Grunddaten!$A141="Geprüft",Programme_Grunddaten!D141<>""),Programme_Grunddaten!D141,"") | D136: =IF(AND(Programme_Grunddaten!$A141="Geprüft",Programme_Grunddaten!E141<>""),Programme_Grunddaten!E141,"") | E136: =IF(AND(Programme_Grunddaten!$A141="Geprüft",Programme_Grunddaten!G141<>""),Programme_Grunddaten!G141,"") | F136: =IF(AND(Programme_Grunddaten!$A141="Geprüft",Programme_Grunddaten!F141<>""),Programme_Grunddaten!F141,"") | G136: =IF(AND(Programme_Grunddaten!$A141="Geprüft",Programme_Grunddaten!S141<>""),Programme_Grunddaten!S141,"") | H136: =IF(AND(Programme_Grunddaten!$A141="Geprüft",Programme_Grunddaten!AW141<>""),Programme_Grunddaten!AW141,"") | I136: =IF(AND(Programme_Grunddaten!$A141="Geprüft",Programme_Grunddaten!AX141<>""),Programme_Grunddaten!AX141,"")
A137: =IF(AND(Programme_Grunddaten!$A142="Geprüft",Programme_Grunddaten!B142<>""),Programme_Grunddaten!B142,"") | B137: =IF(AND(Programme_Grunddaten!$A142="Geprüft",Programme_Grunddaten!C142<>""),Programme_Grunddaten!C142,"") | C137: =IF(AND(Programme_Grunddaten!$A142="Geprüft",Programme_Grunddaten!D142<>""),Programme_Grunddaten!D142,"") | D137: =IF(AND(Programme_Grunddaten!$A142="Geprüft",Programme_Grunddaten!E142<>""),Programme_Grunddaten!E142,"") | E137: =IF(AND(Programme_Grunddaten!$A142="Geprüft",Programme_Grunddaten!G142<>""),Programme_Grunddaten!G142,"") | F137: =IF(AND(Programme_Grunddaten!$A142="Geprüft",Programme_Grunddaten!F142<>""),Programme_Grunddaten!F142,"") | G137: =IF(AND(Programme_Grunddaten!$A142="Geprüft",Programme_Grunddaten!S142<>""),Programme_Grunddaten!S142,"") | H137: =IF(AND(Programme_Grunddaten!$A142="Geprüft",Programme_Grunddaten!AW142<>""),Programme_Grunddaten!AW142,"") | I137: =IF(AND(Programme_Grunddaten!$A142="Geprüft",Programme_Grunddaten!AX142<>""),Programme_Grunddaten!AX142,"")
... A999: =IF(AND(Programme_Grunddaten!$A1004="Geprüft",Programme_Grunddaten!B1004<>""),Programme_Grunddaten!B1004,"") | B999: =IF(AND(Programme_Grunddaten!$A1004="Geprüft",Programme_Grunddaten!C1004<>""),Programme_Grunddaten!C1004,"") | C999: =IF(AND(Programme_Grunddaten!$A1004="Geprüft",Programme_Grunddaten!D1004<>""),Programme_Grunddaten!D1004,"") | D999: =IF(AND(Programme_Grunddaten!$A1004="Geprüft",Programme_Grunddaten!E1004<>""),Programme_Grunddaten!E1004,"") | E999: =IF(AND(Programme_Grunddaten!$A1004="Geprüft",Programme_Grunddaten!G1004<>""),Programme_Grunddaten!G1004,"") | F999: =IF(AND(Programme_Grunddaten!$A1004="Geprüft",Programme_Grunddaten!F1004<>""),Programme_Grunddaten!F1004,"") | G999: =IF(AND(Programme_Grunddaten!$A1004="Geprüft",Programme_Grunddaten!S1004<>""),Programme_Grunddaten!S1004,"") | H999: =IF(AND(Programme_Grunddaten!$A1004="Geprüft",Programme_Grunddaten!AW1004<>""),Programme_Grunddaten!AW1004,"") | I999: =IF(AND(Programme_Grunddaten!$A1004="Geprüft",Programme_Grunddaten!AX1004<>""),Programme_Grunddaten!AX1004,"")
A1000: =IF(AND(Programme_Grunddaten!$A1001="Geprüft",Programme_Grunddaten!B1001<>""),Programme_Grunddaten!B1001,"") | B1000: =IF(AND(Programme_Grunddaten!$A1001="Geprüft",Programme_Grunddaten!C1001<>""),Programme_Grunddaten!C1001,"") | C1000: =IF(AND(Programme_Grunddaten!$A1001="Geprüft",Programme_Grunddaten!D1001<>""),Programme_Grunddaten!D1001,"") | D1000: =IF(AND(Programme_Grunddaten!$A1001="Geprüft",Programme_Grunddaten!E1001<>""),Programme_Grunddaten!E1001,"") | E1000: =IF(AND(Programme_Grunddaten!$A1001="Geprüft",Programme_Grunddaten!G1001<>""),Programme_Grunddaten!G1001,"") | F1000: =IF(AND(Programme_Grunddaten!$A1001="Geprüft",Programme_Grunddaten!F1001<>""),Programme_Grunddaten!F1001,"") | G1000: =IF(AND(Programme_Grunddaten!$A1001="Geprüft",Programme_Grunddaten!S1001<>""),Programme_Grunddaten!S1001,"") | H1000: =IF(AND(Programme_Grunddaten!$A1001="Geprüft",Programme_Grunddaten!AW1001<>""),Programme_Grunddaten!AW1001,"")

Sheet bewertungen
A1: programm_id | B1: K01 | C1: K02 | D1: K02.1 | E1: K02.1.1 | F1: K03 | G1: K04 | H1: K04.1 | I1: K04.2 | J1: K05 | K1: K05.1 | L1: K06.1 | M1: K06.2 | N1: K06.3 | O1: K07 | P1: K08 | Q1: K08.1 | R1: K08.2 | S1: K09 | T1: K10 | U1: K10.1 | V1: K10.2 | W1: K10.3 | X1: K10.4 | Y1: K10.5 | Z1: K10.6 | AA1: K10.7 | AB1: K11 | AC1: K12 | AD1: K13 | AE1: K14 | AF1: K15 | AG1: K16 | AH1: K17 | AI1: K18 | AJ1: K19 | AK1: K20 | AL1: K21 | AM1: K22 | AN1: K23
A2: =IF(AND(Programme_Grunddaten!A10="Geprüft",Programme_Grunddaten!B10<>""),Programme_Grunddaten!B10,"") -> P01 | B2: =IF(AND(Programme_Grunddaten!$A10="Geprüft",Programme_Grunddaten!I10<>""),IF(Programme_Grunddaten!I10="Ja",1,0),"") -> 0 | C2: =IF(AND(Programme_Grunddaten!$A10="Geprüft",Programme_Grunddaten!J10<>""),IF(Programme_Grunddaten!J10="Ja",1,0),"") -> 1 | D2: =IF(AND(Programme_Grunddaten!$A10="Geprüft",Programme_Grunddaten!K10<>""),IF(Programme_Grunddaten!K10="Ja",1,0),"") -> 0 | E2: =IF(AND(Programme_Grunddaten!$A10="Geprüft",Programme_Grunddaten!L10<>""),IF(Programme_Grunddaten!L10="Abo / befristete Lizenz",1,0),"") | F2: =IF(AND(Programme_Grunddaten!$A10="Geprüft",Programme_Grunddaten!M10<>""),IF(Programme_Grunddaten!M10="Ja",1,0),"") -> 0 | G2: =IF(AND(Programme_Grunddaten!$A10="Geprüft",Programme_Grunddaten!N10<>""),IF(Programme_Grunddaten!N10="Ja",1,0),"") -> 1 | H2: =IF(AND(Programme_Grunddaten!$A10="Geprüft",Programme_Grunddaten!O10<>""),IF(Programme_Grunddaten!O10="Deutschland",0,IF(Programme_Grunddaten!O10="EU",1,2)),"") | I2: =IF(AND(Programme_Grunddaten!$A10="Geprüft",Programme_Grunddaten!P10<>""),IF(Programme_Grunddaten!P10="Ja",1,0),"") | J2: =IF(AND(Programme_Grunddaten!$A10="Geprüft",Programme_Grunddaten!Q10<>""),IF(Programme_Grunddaten!Q10="geschlossenes System",1,0),"") -> 0 | K2: =IF(AND(Programme_Grunddaten!$A10="Geprüft",Programme_Grunddaten!R10<>""),IF(Programme_Grunddaten!R10="Ja",1,0),"") -> 1 | L2: =IF(AND(Programme_Grunddaten!$A10="Geprüft",Programme_Grunddaten!T10<>""),IF(Programme_Grunddaten!T10="Ja",1,0),"") -> 1 | M2: =IF(AND(Programme_Grunddaten!$A10="Geprüft",Programme_Grunddaten!U10<>""),IF(Programme_Grunddaten!U10="Ja",1,0),"") | N2: =IF(AND(Programme_Grunddaten!$A10="Geprüft",Programme_Grunddaten!V10<>""),IF(Programme_Grunddaten!V10="Ja",1,0),"") -> 1 | O2: =IF(AND(Programme_Grunddaten!$A10="Geprüft",Programme_Grunddaten!W10<>""),IF(Programme_Grunddaten!W10="Ja",1,0),"") -> 1 | P2: =IF(AND(Programme_Grunddaten!$A10="Geprüft",Programme_Grunddaten!X10<>""),IF(Programme_Grunddaten!X10="Ja",1,0),"") | Q2: =IF(AND(Programme_Grunddaten!$A10="Geprüft",Programme_Grunddaten!Y10<>""),IF(Programme_Grunddaten!Y10="Ja",1,0),"") -> 1 | R2: =IF(AND(Programme_Grunddaten!$A10="Geprüft",Programme_Grunddaten!Z10<>""),IF(Programme_Grunddaten!Z10="Ja",1,0),"") -> 0 | S2: =IF(AND(Programme_Grunddaten!$A10="Geprüft",Programme_Grunddaten!AA10<>""),IF(Programme_Grunddaten!AA10="monolithisch",1,0),"") | T2: =IF(AND(Programme_Grunddaten!$A10="Geprüft",Programme_Grunddaten!AB10<>""),IF(Programme_Grunddaten!AB10="Ja",1,0),"") -> 1 | U2: =IF(AND(Programme_Grunddaten!$A10="Geprüft",Programme_Grunddaten!AC10<>""),IF(Programme_Grunddaten!AC10="Ja",1,0),"") -> 1 | V2: =IF(AND(Programme_Grunddaten!$A10="Geprüft",Programme_Grunddaten!AD10<>""),IF(Programme_Grunddaten!AD10="Ja",1,0),"") | W2: =IF(AND(Programme_Grunddaten!$A10="Geprüft",Programme_Grunddaten!AE10<>""),IF(Programme_Grunddaten!AE10="Ja",1,0),"") | X2: =IF(AND(Programme_Grunddaten!$A10="Geprüft",Programme_Grunddaten!AF10<>""),IF(Programme_Grunddaten!AF10="Ja",1,0),"") -> 1 | Y2: =IF(AND(Programme_Grunddaten!$A10="Geprüft",Programme_Grunddaten!AG10<>""),IF(Programme_Grunddaten!AG10="Ja",1,0),"") -> 1 | Z2: =IF(AND(Programme_Grunddaten!$A10="Geprüft",Programme_Grunddaten!AH10<>""),IF(Programme_Grunddaten!AH10="Ja",1,0),"") | AA2: =IF(AND(Programme_Grunddaten!$A10="Geprüft",Programme_Grunddaten!AI10<>""),IF(Programme_Grunddaten!AI10="Ja",1,0),"") -> 1 | AB2: =IF(AND(Programme_Grunddaten!$A10="Geprüft",Programme_Grunddaten!AJ10<>""),IF(Programme_Grunddaten!AJ10="individuell programmierbar",1,0),"") | AC2: =IF(AND(Programme_Grunddaten!$A10="Geprüft",Programme_Grunddaten!AK10<>""),IF(Programme_Grunddaten!AK10="Deutsch",0,IF(Programme_Grunddaten!AK10="Deutsch und Englisch",1,2)),"") -> 2 | AD2: =IF(AND(Programme_Grunddaten!$A10="Geprüft",Programme_Grunddaten!AL10<>""),IF(Programme_Grunddaten!AL10="Ja",1,0),"") -> 1 | AE2: =IF(AND(Programme_Grunddaten!$A10="Geprüft",Programme_Grunddaten!AM10<>""),IF(Programme_Grunddaten!AM10="Ja",1,0),"") -> 0 | AF2: =IF(AND(Programme_Grunddaten!$A10="Geprüft",Programme_Grunddaten!AN10<>""),IF(Programme_Grunddaten!AN10="Ja",1,0),"") | AG2: =IF(AND(Programme_Grunddaten!$A10="Geprüft",Programme_Grunddaten!AO10<>""),IF(Programme_Grunddaten!AO10="Ja",1,0),"") | AH2: =IF(AND(Programme_Grunddaten!$A10="Geprüft",Programme_Grunddaten!AP10<>""),IF(Programme_Grunddaten!AP10="Ja",1,0),"") | AI2: =IF(AND(Programme_Grunddaten!$A10="Geprüft",Programme_Grunddaten!AQ10<>""),IF(Programme_Grunddaten!AQ10="Ja",1,0),"") -> 1 | AJ2: =IF(AND(Programme_Grunddaten!$A10="Geprüft",Programme_Grunddaten!AR10<>""),IF(Programme_Grunddaten!AR10="Ja",1,0),"") -> 1 | AK2: =IF(AND(Programme_Grunddaten!$A10="Geprüft",Programme_Grunddaten!AS10<>""),IF(Programme_Grunddaten!AS10="Ja",1,0),"") | ... AN2: =IF(AND(Programme_Grunddaten!$A10="Geprüft",Programme_Grunddaten!AV10<>""),IF(Programme_Grunddaten!AV10="Ja",1,0),"")
A3: =IF(AND(Programme_Grunddaten!A11="Geprüft",Programme_Grunddaten!B11<>""),Programme_Grunddaten!B11,"") -> P02 | B3: =IF(AND(Programme_Grunddaten!$A11="Geprüft",Programme_Grunddaten!I11<>""),IF(Programme_Grunddaten!I11="Ja",1,0),"") -> 0 | C3: =IF(AND(Programme_Grunddaten!$A11="Geprüft",Programme_Grunddaten!J11<>""),IF(Programme_Grunddaten!J11="Ja",1,0),"") -> 1 | D3: =IF(AND(Programme_Grunddaten!$A11="Geprüft",Programme_Grunddaten!K11<>""),IF(Programme_Grunddaten!K11="Ja",1,0),"") -> 0 | E3: =IF(AND(Programme_Grunddaten!$A11="Geprüft",Programme_Grunddaten!L11<>""),IF(Programme_Grunddaten!L11="Abo / befristete Lizenz",1,0),"") | F3: =IF(AND(Programme_Grunddaten!$A11="Geprüft",Programme_Grunddaten!M11<>""),IF(Programme_Grunddaten!M11="Ja",1,0),"") -> 0 | G3: =IF(AND(Programme_Grunddaten!$A11="Geprüft",Programme_Grunddaten!N11<>""),IF(Programme_Grunddaten!N11="Ja",1,0),"") -> 1 | H3: =IF(AND(Programme_Grunddaten!$A11="Geprüft",Programme_Grunddaten!O11<>""),IF(Programme_Grunddaten!O11="Deutschland",0,IF(Programme_Grunddaten!O11="EU",1,2)),"") -> 0 | I3: =IF(AND(Programme_Grunddaten!$A11="Geprüft",Programme_Grunddaten!P11<>""),IF(Programme_Grunddaten!P11="Ja",1,0),"") -> 1 | J3: =IF(AND(Programme_Grunddaten!$A11="Geprüft",Programme_Grunddaten!Q11<>""),IF(Programme_Grunddaten!Q11="geschlossenes System",1,0),"") -> 0 | K3: =IF(AND(Programme_Grunddaten!$A11="Geprüft",Programme_Grunddaten!R11<>""),IF(Programme_Grunddaten!R11="Ja",1,0),"") -> 1 | L3: =IF(AND(Programme_Grunddaten!$A11="Geprüft",Programme_Grunddaten!T11<>""),IF(Programme_Grunddaten!T11="Ja",1,0),"") -> 1 | M3: =IF(AND(Programme_Grunddaten!$A11="Geprüft",Programme_Grunddaten!U11<>""),IF(Programme_Grunddaten!U11="Ja",1,0),"") -> 1 | N3: =IF(AND(Programme_Grunddaten!$A11="Geprüft",Programme_Grunddaten!V11<>""),IF(Programme_Grunddaten!V11="Ja",1,0),"") -> 1 | O3: =IF(AND(Programme_Grunddaten!$A11="Geprüft",Programme_Grunddaten!W11<>""),IF(Programme_Grunddaten!W11="Ja",1,0),"") -> 1 | P3: =IF(AND(Programme_Grunddaten!$A11="Geprüft",Programme_Grunddaten!X11<>""),IF(Programme_Grunddaten!X11="Ja",1,0),"") | Q3: =IF(AND(Programme_Grunddaten!$A11="Geprüft",Programme_Grunddaten!Y11<>""),IF(Programme_Grunddaten!Y11="Ja",1,0),"") -> 1 | R3: =IF(AND(Programme_Grunddaten!$A11="Geprüft",Programme_Grunddaten!Z11<>""),IF(Programme_Grunddaten!Z11="Ja",1,0),"") -> 0 | S3: =IF(AND(Programme_Grunddaten!$A11="Geprüft",Programme_Grunddaten!AA11<>""),IF(Programme_Grunddaten!AA11="monolithisch",1,0),"") -> 0 | T3: =IF(AND(Programme_Grunddaten!$A11="Geprüft",Programme_Grunddaten!AB11<>""),IF(Programme_Grunddaten!AB11="Ja",1,0),"") -> 1 | U3: =IF(AND(Programme_Grunddaten!$A11="Geprüft",Programme_Grunddaten!AC11<>""),IF(Programme_Grunddaten!AC11="Ja",1,0),"") -> 1 | V3: =IF(AND(Programme_Grunddaten!$A11="Geprüft",Programme_Grunddaten!AD11<>""),IF(Programme_Grunddaten!AD11="Ja",1,0),"") -> 1 | W3: =IF(AND(Programme_Grunddaten!$A11="Geprüft",Programme_Grunddaten!AE11<>""),IF(Programme_Grunddaten!AE11="Ja",1,0),"") | X3: =IF(AND(Programme_Grunddaten!$A11="Geprüft",Programme_Grunddaten!AF11<>""),IF(Programme_Grunddaten!AF11="Ja",1,0),"") -> 1 | Y3: =IF(AND(Programme_Grunddaten!$A11="Geprüft",Programme_Grunddaten!AG11<>""),IF(Programme_Grunddaten!AG11="Ja",1,0),"") -> 1 | Z3: =IF(AND(Programme_Grunddaten!$A11="Geprüft",Programme_Grunddaten!AH11<>""),IF(Programme_Grunddaten!AH11="Ja",1,0),"") -> 1 | AA3: =IF(AND(Programme_Grunddaten!$A11="Geprüft",Programme_Grunddaten!AI11<>""),IF(Programme_Grunddaten!AI11="Ja",1,0),"") -> 1 | AB3: =IF(AND(Programme_Grunddaten!$A11="Geprüft",Programme_Grunddaten!AJ11<>""),IF(Programme_Grunddaten!AJ11="individuell programmierbar",1,0),"") | AC3: =IF(AND(Programme_Grunddaten!$A11="Geprüft",Programme_Grunddaten!AK11<>""),IF(Programme_Grunddaten!AK11="Deutsch",0,IF(Programme_Grunddaten!AK11="Deutsch und Englisch",1,2)),"") -> 1 | AD3: =IF(AND(Programme_Grunddaten!$A11="Geprüft",Programme_Grunddaten!AL11<>""),IF(Programme_Grunddaten!AL11="Ja",1,0),"") -> 1 | AE3: =IF(AND(Programme_Grunddaten!$A11="Geprüft",Programme_Grunddaten!AM11<>""),IF(Programme_Grunddaten!AM11="Ja",1,0),"") -> 0 | AF3: =IF(AND(Programme_Grunddaten!$A11="Geprüft",Programme_Grunddaten!AN11<>""),IF(Programme_Grunddaten!AN11="Ja",1,0),"") | AG3: =IF(AND(Programme_Grunddaten!$A11="Geprüft",Programme_Grunddaten!AO11<>""),IF(Programme_Grunddaten!AO11="Ja",1,0),"") -> 0 | AH3: =IF(AND(Programme_Grunddaten!$A11="Geprüft",Programme_Grunddaten!AP11<>""),IF(Programme_Grunddaten!AP11="Ja",1,0),"") | AI3: =IF(AND(Programme_Grunddaten!$A11="Geprüft",Programme_Grunddaten!AQ11<>""),IF(Programme_Grunddaten!AQ11="Ja",1,0),"") -> 1 | AJ3: =IF(AND(Programme_Grunddaten!$A11="Geprüft",Programme_Grunddaten!AR11<>""),IF(Programme_Grunddaten!AR11="Ja",1,0),"") -> 1 | AK3: =IF(AND(Programme_Grunddaten!$A11="Geprüft",Programme_Grunddaten!AS11<>""),IF(Programme_Grunddaten!AS11="Ja",1,0),"") -> 1 | ... AN3: =IF(AND(Programme_Grunddaten!$A11="Geprüft",Programme_Grunddaten!AV11<>""),IF(Programme_Grunddaten!AV11="Ja",1,0),"")
A4: =IF(AND(Programme_Grunddaten!A12="Geprüft",Programme_Grunddaten!B12<>""),Programme_Grunddaten!B12,"") -> P03 | B4: =IF(AND(Programme_Grunddaten!$A12="Geprüft",Programme_Grunddaten!I12<>""),IF(Programme_Grunddaten!I12="Ja",1,0),"") -> 0 | C4: =IF(AND(Programme_Grunddaten!$A12="Geprüft",Programme_Grunddaten!J12<>""),IF(Programme_Grunddaten!J12="Ja",1,0),"") -> 1 | D4: =IF(AND(Programme_Grunddaten!$A12="Geprüft",Programme_Grunddaten!K12<>""),IF(Programme_Grunddaten!K12="Ja",1,0),"") -> 0 | E4: =IF(AND(Programme_Grunddaten!$A12="Geprüft",Programme_Grunddaten!L12<>""),IF(Programme_Grunddaten!L12="Abo / befristete Lizenz",1,0),"") -> 1 | F4: =IF(AND(Programme_Grunddaten!$A12="Geprüft",Programme_Grunddaten!M12<>""),IF(Programme_Grunddaten!M12="Ja",1,0),"") -> 1 | G4: =IF(AND(Programme_Grunddaten!$A12="Geprüft",Programme_Grunddaten!N12<>""),IF(Programme_Grunddaten!N12="Ja",1,0),"") -> 1 | H4: =IF(AND(Programme_Grunddaten!$A12="Geprüft",Programme_Grunddaten!O12<>""),IF(Programme_Grunddaten!O12="Deutschland",0,IF(Programme_Grunddaten!O12="EU",1,2)),"") | I4: =IF(AND(Programme_Grunddaten!$A12="Geprüft",Programme_Grunddaten!P12<>""),IF(Programme_Grunddaten!P12="Ja",1,0),"") -> 1 | J4: =IF(AND(Programme_Grunddaten!$A12="Geprüft",Programme_Grunddaten!Q12<>""),IF(Programme_Grunddaten!Q12="geschlossenes System",1,0),"") -> 0 | K4: =IF(AND(Programme_Grunddaten!$A12="Geprüft",Programme_Grunddaten!R12<>""),IF(Programme_Grunddaten!R12="Ja",1,0),"") -> 1 | L4: =IF(AND(Programme_Grunddaten!$A12="Geprüft",Programme_Grunddaten!T12<>""),IF(Programme_Grunddaten!T12="Ja",1,0),"") -> 1 | M4: =IF(AND(Programme_Grunddaten!$A12="Geprüft",Programme_Grunddaten!U12<>""),IF(Programme_Grunddaten!U12="Ja",1,0),"") -> 1 | N4: =IF(AND(Programme_Grunddaten!$A12="Geprüft",Programme_Grunddaten!V12<>""),IF(Programme_Grunddaten!V12="Ja",1,0),"") -> 1 | O4: =IF(AND(Programme_Grunddaten!$A12="Geprüft",Programme_Grunddaten!W12<>""),IF(Programme_Grunddaten!W12="Ja",1,0),"") -> 1 | P4: =IF(AND(Programme_Grunddaten!$A12="Geprüft",Programme_Grunddaten!X12<>""),IF(Programme_Grunddaten!X12="Ja",1,0),"") | Q4: =IF(AND(Programme_Grunddaten!$A12="Geprüft",Programme_Grunddaten!Y12<>""),IF(Programme_Grunddaten!Y12="Ja",1,0),"") -> 1 | R4: =IF(AND(Programme_Grunddaten!$A12="Geprüft",Programme_Grunddaten!Z12<>""),IF(Programme_Grunddaten!Z12="Ja",1,0),"") -> 0 | S4: =IF(AND(Programme_Grunddaten!$A12="Geprüft",Programme_Grunddaten!AA12<>""),IF(Programme_Grunddaten!AA12="monolithisch",1,0),"") -> 0 | T4: =IF(AND(Programme_Grunddaten!$A12="Geprüft",Programme_Grunddaten!AB12<>""),IF(Programme_Grunddaten!AB12="Ja",1,0),"") -> 1 | U4: =IF(AND(Programme_Grunddaten!$A12="Geprüft",Programme_Grunddaten!AC12<>""),IF(Programme_Grunddaten!AC12="Ja",1,0),"") -> 1 | V4: =IF(AND(Programme_Grunddaten!$A12="Geprüft",Programme_Grunddaten!AD12<>""),IF(Programme_Grunddaten!AD12="Ja",1,0),"") | W4: =IF(AND(Programme_Grunddaten!$A12="Geprüft",Programme_Grunddaten!AE12<>""),IF(Programme_Grunddaten!AE12="Ja",1,0),"") | X4: =IF(AND(Programme_Grunddaten!$A12="Geprüft",Programme_Grunddaten!AF12<>""),IF(Programme_Grunddaten!AF12="Ja",1,0),"") -> 1 | Y4: =IF(AND(Programme_Grunddaten!$A12="Geprüft",Programme_Grunddaten!AG12<>""),IF(Programme_Grunddaten!AG12="Ja",1,0),"") | Z4: =IF(AND(Programme_Grunddaten!$A12="Geprüft",Programme_Grunddaten!AH12<>""),IF(Programme_Grunddaten!AH12="Ja",1,0),"") -> 1 | AA4: =IF(AND(Programme_Grunddaten!$A12="Geprüft",Programme_Grunddaten!AI12<>""),IF(Programme_Grunddaten!AI12="Ja",1,0),"") -> 1 | AB4: =IF(AND(Programme_Grunddaten!$A12="Geprüft",Programme_Grunddaten!AJ12<>""),IF(Programme_Grunddaten!AJ12="individuell programmierbar",1,0),"") | AC4: =IF(AND(Programme_Grunddaten!$A12="Geprüft",Programme_Grunddaten!AK12<>""),IF(Programme_Grunddaten!AK12="Deutsch",0,IF(Programme_Grunddaten!AK12="Deutsch und Englisch",1,2)),"") -> 0 | AD4: =IF(AND(Programme_Grunddaten!$A12="Geprüft",Programme_Grunddaten!AL12<>""),IF(Programme_Grunddaten!AL12="Ja",1,0),"") -> 1 | AE4: =IF(AND(Programme_Grunddaten!$A12="Geprüft",Programme_Grunddaten!AM12<>""),IF(Programme_Grunddaten!AM12="Ja",1,0),"") -> 0 | AF4: =IF(AND(Programme_Grunddaten!$A12="Geprüft",Programme_Grunddaten!AN12<>""),IF(Programme_Grunddaten!AN12="Ja",1,0),"") | AG4: =IF(AND(Programme_Grunddaten!$A12="Geprüft",Programme_Grunddaten!AO12<>""),IF(Programme_Grunddaten!AO12="Ja",1,0),"") | AH4: =IF(AND(Programme_Grunddaten!$A12="Geprüft",Programme_Grunddaten!AP12<>""),IF(Programme_Grunddaten!AP12="Ja",1,0),"") | AI4: =IF(AND(Programme_Grunddaten!$A12="Geprüft",Programme_Grunddaten!AQ12<>""),IF(Programme_Grunddaten!AQ12="Ja",1,0),"") -> 1 | AJ4: =IF(AND(Programme_Grunddaten!$A12="Geprüft",Programme_Grunddaten!AR12<>""),IF(Programme_Grunddaten!AR12="Ja",1,0),"") -> 1 | AK4: =IF(AND(Programme_Grunddaten!$A12="Geprüft",Programme_Grunddaten!AS12<>""),IF(Programme_Grunddaten!AS12="Ja",1,0),"") -> 1 | ... AN4: =IF(AND(Programme_Grunddaten!$A12="Geprüft",Programme_Grunddaten!AV12<>""),IF(Programme_Grunddaten!AV12="Ja",1,0),"")
A5: =IF(AND(Programme_Grunddaten!A13="Geprüft",Programme_Grunddaten!B13<>""),Programme_Grunddaten!B13,"") -> P04 | B5: =IF(AND(Programme_Grunddaten!$A13="Geprüft",Programme_Grunddaten!I13<>""),IF(Programme_Grunddaten!I13="Ja",1,0),"") -> 0 | C5: =IF(AND(Programme_Grunddaten!$A13="Geprüft",Programme_Grunddaten!J13<>""),IF(Programme_Grunddaten!J13="Ja",1,0),"") -> 1 | D5: =IF(AND(Programme_Grunddaten!$A13="Geprüft",Programme_Grunddaten!K13<>""),IF(Programme_Grunddaten!K13="Ja",1,0),"") -> 0 | E5: =IF(AND(Programme_Grunddaten!$A13="Geprüft",Programme_Grunddaten!L13<>""),IF(Programme_Grunddaten!L13="Abo / befristete Lizenz",1,0),"") | F5: =IF(AND(Programme_Grunddaten!$A13="Geprüft",Programme_Grunddaten!M13<>""),IF(Programme_Grunddaten!M13="Ja",1,0),"") -> 1 | G5: =IF(AND(Programme_Grunddaten!$A13="Geprüft",Programme_Grunddaten!N13<>""),IF(Programme_Grunddaten!N13="Ja",1,0),"") -> 1 | H5: =IF(AND(Programme_Grunddaten!$A13="Geprüft",Programme_Grunddaten!O13<>""),IF(Programme_Grunddaten!O13="Deutschland",0,IF(Programme_Grunddaten!O13="EU",1,2)),"") -> 0 | I5: =IF(AND(Programme_Grunddaten!$A13="Geprüft",Programme_Grunddaten!P13<>""),IF(Programme_Grunddaten!P13="Ja",1,0),"") | J5: =IF(AND(Programme_Grunddaten!$A13="Geprüft",Programme_Grunddaten!Q13<>""),IF(Programme_Grunddaten!Q13="geschlossenes System",1,0),"") -> 0 | K5: =IF(AND(Programme_Grunddaten!$A13="Geprüft",Programme_Grunddaten!R13<>""),IF(Programme_Grunddaten!R13="Ja",1,0),"") -> 1 | L5: =IF(AND(Programme_Grunddaten!$A13="Geprüft",Programme_Grunddaten!T13<>""),IF(Programme_Grunddaten!T13="Ja",1,0),"") -> 1 | M5: =IF(AND(Programme_Grunddaten!$A13="Geprüft",Programme_Grunddaten!U13<>""),IF(Programme_Grunddaten!U13="Ja",1,0),"") -> 1 | N5: =IF(AND(Programme_Grunddaten!$A13="Geprüft",Programme_Grunddaten!V13<>""),IF(Programme_Grunddaten!V13="Ja",1,0),"") -> 1 | O5: =IF(AND(Programme_Grunddaten!$A13="Geprüft",Programme_Grunddaten!W13<>""),IF(Programme_Grunddaten!W13="Ja",1,0),"") -> 1 | P5: =IF(AND(Programme_Grunddaten!$A13="Geprüft",Programme_Grunddaten!X13<>""),IF(Programme_Grunddaten!X13="Ja",1,0),"") | Q5: =IF(AND(Programme_Grunddaten!$A13="Geprüft",Programme_Grunddaten!Y13<>""),IF(Programme_Grunddaten!Y13="Ja",1,0),"") -> 1 | R5: =IF(AND(Programme_Grunddaten!$A13="Geprüft",Programme_Grunddaten!Z13<>""),IF(Programme_Grunddaten!Z13="Ja",1,0),"") -> 0 | S5: =IF(AND(Programme_Grunddaten!$A13="Geprüft",Programme_Grunddaten!AA13<>""),IF(Programme_Grunddaten!AA13="monolithisch",1,0),"") -> 0 | T5: =IF(AND(Programme_Grunddaten!$A13="Geprüft",Programme_Grunddaten!AB13<>""),IF(Programme_Grunddaten!AB13="Ja",1,0),"") -> 1 | U5: =IF(AND(Programme_Grunddaten!$A13="Geprüft",Programme_Grunddaten!AC13<>""),IF(Programme_Grunddaten!AC13="Ja",1,0),"") -> 1 | V5: =IF(AND(Programme_Grunddaten!$A13="Geprüft",Programme_Grunddaten!AD13<>""),IF(Programme_Grunddaten!AD13="Ja",1,0),"") -> 1 | W5: =IF(AND(Programme_Grunddaten!$A13="Geprüft",Programme_Grunddaten!AE13<>""),IF(Programme_Grunddaten!AE13="Ja",1,0),"") | X5: =IF(AND(Programme_Grunddaten!$A13="Geprüft",Programme_Grunddaten!AF13<>""),IF(Programme_Grunddaten!AF13="Ja",1,0),"") -> 1 | Y5: =IF(AND(Programme_Grunddaten!$A13="Geprüft",Programme_Grunddaten!AG13<>""),IF(Programme_Grunddaten!AG13="Ja",1,0),"") | Z5: =IF(AND(Programme_Grunddaten!$A13="Geprüft",Programme_Grunddaten!AH13<>""),IF(Programme_Grunddaten!AH13="Ja",1,0),"") -> 1 | AA5: =IF(AND(Programme_Grunddaten!$A13="Geprüft",Programme_Grunddaten!AI13<>""),IF(Programme_Grunddaten!AI13="Ja",1,0),"") -> 1 | AB5: =IF(AND(Programme_Grunddaten!$A13="Geprüft",Programme_Grunddaten!AJ13<>""),IF(Programme_Grunddaten!AJ13="individuell programmierbar",1,0),"") | AC5: =IF(AND(Programme_Grunddaten!$A13="Geprüft",Programme_Grunddaten!AK13<>""),IF(Programme_Grunddaten!AK13="Deutsch",0,IF(Programme_Grunddaten!AK13="Deutsch und Englisch",1,2)),"") -> 0 | AD5: =IF(AND(Programme_Grunddaten!$A13="Geprüft",Programme_Grunddaten!AL13<>""),IF(Programme_Grunddaten!AL13="Ja",1,0),"") -> 1 | AE5: =IF(AND(Programme_Grunddaten!$A13="Geprüft",Programme_Grunddaten!AM13<>""),IF(Programme_Grunddaten!AM13="Ja",1,0),"") -> 0 | AF5: =IF(AND(Programme_Grunddaten!$A13="Geprüft",Programme_Grunddaten!AN13<>""),IF(Programme_Grunddaten!AN13="Ja",1,0),"") | AG5: =IF(AND(Programme_Grunddaten!$A13="Geprüft",Programme_Grunddaten!AO13<>""),IF(Programme_Grunddaten!AO13="Ja",1,0),"") -> 0 | AH5: =IF(AND(Programme_Grunddaten!$A13="Geprüft",Programme_Grunddaten!AP13<>""),IF(Programme_Grunddaten!AP13="Ja",1,0),"") -> 1 | AI5: =IF(AND(Programme_Grunddaten!$A13="Geprüft",Programme_Grunddaten!AQ13<>""),IF(Programme_Grunddaten!AQ13="Ja",1,0),"") -> 1 | AJ5: =IF(AND(Programme_Grunddaten!$A13="Geprüft",Programme_Grunddaten!AR13<>""),IF(Programme_Grunddaten!AR13="Ja",1,0),"") -> 1 | AK5: =IF(AND(Programme_Grunddaten!$A13="Geprüft",Programme_Grunddaten!AS13<>""),IF(Programme_Grunddaten!AS13="Ja",1,0),"") -> 1 | ... AN5: =IF(AND(Programme_Grunddaten!$A13="Geprüft",Programme_Grunddaten!AV13<>""),IF(Programme_Grunddaten!AV13="Ja",1,0),"")
A6: =IF(AND(Programme_Grunddaten!A14="Geprüft",Programme_Grunddaten!B14<>""),Programme_Grunddaten!B14,"") -> P05 | B6: =IF(AND(Programme_Grunddaten!$A14="Geprüft",Programme_Grunddaten!I14<>""),IF(Programme_Grunddaten!I14="Ja",1,0),"") -> 0 | C6: =IF(AND(Programme_Grunddaten!$A14="Geprüft",Programme_Grunddaten!J14<>""),IF(Programme_Grunddaten!J14="Ja",1,0),"") -> 1 | D6: =IF(AND(Programme_Grunddaten!$A14="Geprüft",Programme_Grunddaten!K14<>""),IF(Programme_Grunddaten!K14="Ja",1,0),"") -> 0 | E6: =IF(AND(Programme_Grunddaten!$A14="Geprüft",Programme_Grunddaten!L14<>""),IF(Programme_Grunddaten!L14="Abo / befristete Lizenz",1,0),"") -> 0 | F6: =IF(AND(Programme_Grunddaten!$A14="Geprüft",Programme_Grunddaten!M14<>""),IF(Programme_Grunddaten!M14="Ja",1,0),"") -> 1 | G6: =IF(AND(Programme_Grunddaten!$A14="Geprüft",Programme_Grunddaten!N14<>""),IF(Programme_Grunddaten!N14="Ja",1,0),"") -> 1 | H6: =IF(AND(Programme_Grunddaten!$A14="Geprüft",Programme_Grunddaten!O14<>""),IF(Programme_Grunddaten!O14="Deutschland",0,IF(Programme_Grunddaten!O14="EU",1,2)),"") -> 0 | I6: =IF(AND(Programme_Grunddaten!$A14="Geprüft",Programme_Grunddaten!P14<>""),IF(Programme_Grunddaten!P14="Ja",1,0),"") -> 1 | J6: =IF(AND(Programme_Grunddaten!$A14="Geprüft",Programme_Grunddaten!Q14<>""),IF(Programme_Grunddaten!Q14="geschlossenes System",1,0),"") -> 0 | K6: =IF(AND(Programme_Grunddaten!$A14="Geprüft",Programme_Grunddaten!R14<>""),IF(Programme_Grunddaten!R14="Ja",1,0),"") -> 1 | L6: =IF(AND(Programme_Grunddaten!$A14="Geprüft",Programme_Grunddaten!T14<>""),IF(Programme_Grunddaten!T14="Ja",1,0),"") -> 1 | M6: =IF(AND(Programme_Grunddaten!$A14="Geprüft",Programme_Grunddaten!U14<>""),IF(Programme_Grunddaten!U14="Ja",1,0),"") -> 1 | N6: =IF(AND(Programme_Grunddaten!$A14="Geprüft",Programme_Grunddaten!V14<>""),IF(Programme_Grunddaten!V14="Ja",1,0),"") -> 1 | O6: =IF(AND(Programme_Grunddaten!$A14="Geprüft",Programme_Grunddaten!W14<>""),IF(Programme_Grunddaten!W14="Ja",1,0),"") | P6: =IF(AND(Programme_Grunddaten!$A14="Geprüft",Programme_Grunddaten!X14<>""),IF(Programme_Grunddaten!X14="Ja",1,0),"") -> 1 | Q6: =IF(AND(Programme_Grunddaten!$A14="Geprüft",Programme_Grunddaten!Y14<>""),IF(Programme_Grunddaten!Y14="Ja",1,0),"") | R6: =IF(AND(Programme_Grunddaten!$A14="Geprüft",Programme_Grunddaten!Z14<>""),IF(Programme_Grunddaten!Z14="Ja",1,0),"") -> 0 | S6: =IF(AND(Programme_Grunddaten!$A14="Geprüft",Programme_Grunddaten!AA14<>""),IF(Programme_Grunddaten!AA14="monolithisch",1,0),"") -> 0 | T6: =IF(AND(Programme_Grunddaten!$A14="Geprüft",Programme_Grunddaten!AB14<>""),IF(Programme_Grunddaten!AB14="Ja",1,0),"") -> 1 | U6: =IF(AND(Programme_Grunddaten!$A14="Geprüft",Programme_Grunddaten!AC14<>""),IF(Programme_Grunddaten!AC14="Ja",1,0),"") | V6: =IF(AND(Programme_Grunddaten!$A14="Geprüft",Programme_Grunddaten!AD14<>""),IF(Programme_Grunddaten!AD14="Ja",1,0),"") -> 1 | W6: =IF(AND(Programme_Grunddaten!$A14="Geprüft",Programme_Grunddaten!AE14<>""),IF(Programme_Grunddaten!AE14="Ja",1,0),"") | X6: =IF(AND(Programme_Grunddaten!$A14="Geprüft",Programme_Grunddaten!AF14<>""),IF(Programme_Grunddaten!AF14="Ja",1,0),"") -> 1 | Y6: =IF(AND(Programme_Grunddaten!$A14="Geprüft",Programme_Grunddaten!AG14<>""),IF(Programme_Grunddaten!AG14="Ja",1,0),"") | Z6: =IF(AND(Programme_Grunddaten!$A14="Geprüft",Programme_Grunddaten!AH14<>""),IF(Programme_Grunddaten!AH14="Ja",1,0),"") -> 1 | AA6: =IF(AND(Programme_Grunddaten!$A14="Geprüft",Programme_Grunddaten!AI14<>""),IF(Programme_Grunddaten!AI14="Ja",1,0),"") -> 1 | AB6: =IF(AND(Programme_Grunddaten!$A14="Geprüft",Programme_Grunddaten!AJ14<>""),IF(Programme_Grunddaten!AJ14="individuell programmierbar",1,0),"") | AC6: =IF(AND(Programme_Grunddaten!$A14="Geprüft",Programme_Grunddaten!AK14<>""),IF(Programme_Grunddaten!AK14="Deutsch",0,IF(Programme_Grunddaten!AK14="Deutsch und Englisch",1,2)),"") -> 1 | AD6: =IF(AND(Programme_Grunddaten!$A14="Geprüft",Programme_Grunddaten!AL14<>""),IF(Programme_Grunddaten!AL14="Ja",1,0),"") -> 1 | AE6: =IF(AND(Programme_Grunddaten!$A14="Geprüft",Programme_Grunddaten!AM14<>""),IF(Programme_Grunddaten!AM14="Ja",1,0),"") -> 0 | AF6: =IF(AND(Programme_Grunddaten!$A14="Geprüft",Programme_Grunddaten!AN14<>""),IF(Programme_Grunddaten!AN14="Ja",1,0),"") | AG6: =IF(AND(Programme_Grunddaten!$A14="Geprüft",Programme_Grunddaten!AO14<>""),IF(Programme_Grunddaten!AO14="Ja",1,0),"") -> 0 | AH6: =IF(AND(Programme_Grunddaten!$A14="Geprüft",Programme_Grunddaten!AP14<>""),IF(Programme_Grunddaten!AP14="Ja",1,0),"") | AI6: =IF(AND(Programme_Grunddaten!$A14="Geprüft",Programme_Grunddaten!AQ14<>""),IF(Programme_Grunddaten!AQ14="Ja",1,0),"") -> 1 | AJ6: =IF(AND(Programme_Grunddaten!$A14="Geprüft",Programme_Grunddaten!AR14<>""),IF(Programme_Grunddaten!AR14="Ja",1,0),"") -> 1 | AK6: =IF(AND(Programme_Grunddaten!$A14="Geprüft",Programme_Grunddaten!AS14<>""),IF(Programme_Grunddaten!AS14="Ja",1,0),"") -> 1 | ... AN6: =IF(AND(Programme_Grunddaten!$A14="Geprüft",Programme_Grunddaten!AV14<>""),IF(Programme_Grunddaten!AV14="Ja",1,0),"")
A7: =IF(AND(Programme_Grunddaten!A15="Geprüft",Programme_Grunddaten!B15<>""),Programme_Grunddaten!B15,"") -> P06 | B7: =IF(AND(Programme_Grunddaten!$A15="Geprüft",Programme_Grunddaten!I15<>""),IF(Programme_Grunddaten!I15="Ja",1,0),"") -> 0 | C7: =IF(AND(Programme_Grunddaten!$A15="Geprüft",Programme_Grunddaten!J15<>""),IF(Programme_Grunddaten!J15="Ja",1,0),"") -> 1 | D7: =IF(AND(Programme_Grunddaten!$A15="Geprüft",Programme_Grunddaten!K15<>""),IF(Programme_Grunddaten!K15="Ja",1,0),"") -> 0 | E7: =IF(AND(Programme_Grunddaten!$A15="Geprüft",Programme_Grunddaten!L15<>""),IF(Programme_Grunddaten!L15="Abo / befristete Lizenz",1,0),"") | F7: =IF(AND(Programme_Grunddaten!$A15="Geprüft",Programme_Grunddaten!M15<>""),IF(Programme_Grunddaten!M15="Ja",1,0),"") -> 0 | G7: =IF(AND(Programme_Grunddaten!$A15="Geprüft",Programme_Grunddaten!N15<>""),IF(Programme_Grunddaten!N15="Ja",1,0),"") -> 1 | H7: =IF(AND(Programme_Grunddaten!$A15="Geprüft",Programme_Grunddaten!O15<>""),IF(Programme_Grunddaten!O15="Deutschland",0,IF(Programme_Grunddaten!O15="EU",1,2)),"") | I7: =IF(AND(Programme_Grunddaten!$A15="Geprüft",Programme_Grunddaten!P15<>""),IF(Programme_Grunddaten!P15="Ja",1,0),"") | J7: =IF(AND(Programme_Grunddaten!$A15="Geprüft",Programme_Grunddaten!Q15<>""),IF(Programme_Grunddaten!Q15="geschlossenes System",1,0),"") -> 0 | K7: =IF(AND(Programme_Grunddaten!$A15="Geprüft",Programme_Grunddaten!R15<>""),IF(Programme_Grunddaten!R15="Ja",1,0),"") -> 1 | L7: =IF(AND(Programme_Grunddaten!$A15="Geprüft",Programme_Grunddaten!T15<>""),IF(Programme_Grunddaten!T15="Ja",1,0),"") -> 1 | M7: =IF(AND(Programme_Grunddaten!$A15="Geprüft",Programme_Grunddaten!U15<>""),IF(Programme_Grunddaten!U15="Ja",1,0),"") | N7: =IF(AND(Programme_Grunddaten!$A15="Geprüft",Programme_Grunddaten!V15<>""),IF(Programme_Grunddaten!V15="Ja",1,0),"") -> 1 | O7: =IF(AND(Programme_Grunddaten!$A15="Geprüft",Programme_Grunddaten!W15<>""),IF(Programme_Grunddaten!W15="Ja",1,0),"") | P7: =IF(AND(Programme_Grunddaten!$A15="Geprüft",Programme_Grunddaten!X15<>""),IF(Programme_Grunddaten!X15="Ja",1,0),"") -> 1 | Q7: =IF(AND(Programme_Grunddaten!$A15="Geprüft",Programme_Grunddaten!Y15<>""),IF(Programme_Grunddaten!Y15="Ja",1,0),"") | R7: =IF(AND(Programme_Grunddaten!$A15="Geprüft",Programme_Grunddaten!Z15<>""),IF(Programme_Grunddaten!Z15="Ja",1,0),"") -> 0 | S7: =IF(AND(Programme_Grunddaten!$A15="Geprüft",Programme_Grunddaten!AA15<>""),IF(Programme_Grunddaten!AA15="monolithisch",1,0),"") -> 0 | T7: =IF(AND(Programme_Grunddaten!$A15="Geprüft",Programme_Grunddaten!AB15<>""),IF(Programme_Grunddaten!AB15="Ja",1,0),"") -> 1 | U7: =IF(AND(Programme_Grunddaten!$A15="Geprüft",Programme_Grunddaten!AC15<>""),IF(Programme_Grunddaten!AC15="Ja",1,0),"") | V7: =IF(AND(Programme_Grunddaten!$A15="Geprüft",Programme_Grunddaten!AD15<>""),IF(Programme_Grunddaten!AD15="Ja",1,0),"") -> 1 | W7: =IF(AND(Programme_Grunddaten!$A15="Geprüft",Programme_Grunddaten!AE15<>""),IF(Programme_Grunddaten!AE15="Ja",1,0),"") | X7: =IF(AND(Programme_Grunddaten!$A15="Geprüft",Programme_Grunddaten!AF15<>""),IF(Programme_Grunddaten!AF15="Ja",1,0),"") | Y7: =IF(AND(Programme_Grunddaten!$A15="Geprüft",Programme_Grunddaten!AG15<>""),IF(Programme_Grunddaten!AG15="Ja",1,0),"") | Z7: =IF(AND(Programme_Grunddaten!$A15="Geprüft",Programme_Grunddaten!AH15<>""),IF(Programme_Grunddaten!AH15="Ja",1,0),"") | AA7: =IF(AND(Programme_Grunddaten!$A15="Geprüft",Programme_Grunddaten!AI15<>""),IF(Programme_Grunddaten!AI15="Ja",1,0),"") -> 1 | AB7: =IF(AND(Programme_Grunddaten!$A15="Geprüft",Programme_Grunddaten!AJ15<>""),IF(Programme_Grunddaten!AJ15="individuell programmierbar",1,0),"") | AC7: =IF(AND(Programme_Grunddaten!$A15="Geprüft",Programme_Grunddaten!AK15<>""),IF(Programme_Grunddaten!AK15="Deutsch",0,IF(Programme_Grunddaten!AK15="Deutsch und Englisch",1,2)),"") -> 0 | AD7: =IF(AND(Programme_Grunddaten!$A15="Geprüft",Programme_Grunddaten!AL15<>""),IF(Programme_Grunddaten!AL15="Ja",1,0),"") -> 1 | AE7: =IF(AND(Programme_Grunddaten!$A15="Geprüft",Programme_Grunddaten!AM15<>""),IF(Programme_Grunddaten!AM15="Ja",1,0),"") -> 0 | AF7: =IF(AND(Programme_Grunddaten!$A15="Geprüft",Programme_Grunddaten!AN15<>""),IF(Programme_Grunddaten!AN15="Ja",1,0),"") | AG7: =IF(AND(Programme_Grunddaten!$A15="Geprüft",Programme_Grunddaten!AO15<>""),IF(Programme_Grunddaten!AO15="Ja",1,0),"") -> 0 | AH7: =IF(AND(Programme_Grunddaten!$A15="Geprüft",Programme_Grunddaten!AP15<>""),IF(Programme_Grunddaten!AP15="Ja",1,0),"") | AI7: =IF(AND(Programme_Grunddaten!$A15="Geprüft",Programme_Grunddaten!AQ15<>""),IF(Programme_Grunddaten!AQ15="Ja",1,0),"") -> 1 | AJ7: =IF(AND(Programme_Grunddaten!$A15="Geprüft",Programme_Grunddaten!AR15<>""),IF(Programme_Grunddaten!AR15="Ja",1,0),"") -> 1 | AK7: =IF(AND(Programme_Grunddaten!$A15="Geprüft",Programme_Grunddaten!AS15<>""),IF(Programme_Grunddaten!AS15="Ja",1,0),"") | ... AN7: =IF(AND(Programme_Grunddaten!$A15="Geprüft",Programme_Grunddaten!AV15<>""),IF(Programme_Grunddaten!AV15="Ja",1,0),"")
A8: =IF(AND(Programme_Grunddaten!A16="Geprüft",Programme_Grunddaten!B16<>""),Programme_Grunddaten!B16,"") -> P07 | B8: =IF(AND(Programme_Grunddaten!$A16="Geprüft",Programme_Grunddaten!I16<>""),IF(Programme_Grunddaten!I16="Ja",1,0),"") -> 0 | C8: =IF(AND(Programme_Grunddaten!$A16="Geprüft",Programme_Grunddaten!J16<>""),IF(Programme_Grunddaten!J16="Ja",1,0),"") -> 1 | D8: =IF(AND(Programme_Grunddaten!$A16="Geprüft",Programme_Grunddaten!K16<>""),IF(Programme_Grunddaten!K16="Ja",1,0),"") -> 0 | E8: =IF(AND(Programme_Grunddaten!$A16="Geprüft",Programme_Grunddaten!L16<>""),IF(Programme_Grunddaten!L16="Abo / befristete Lizenz",1,0),"") -> 1 | F8: =IF(AND(Programme_Grunddaten!$A16="Geprüft",Programme_Grunddaten!M16<>""),IF(Programme_Grunddaten!M16="Ja",1,0),"") -> 0 | G8: =IF(AND(Programme_Grunddaten!$A16="Geprüft",Programme_Grunddaten!N16<>""),IF(Programme_Grunddaten!N16="Ja",1,0),"") -> 1 | H8: =IF(AND(Programme_Grunddaten!$A16="Geprüft",Programme_Grunddaten!O16<>""),IF(Programme_Grunddaten!O16="Deutschland",0,IF(Programme_Grunddaten!O16="EU",1,2)),"") | I8: =IF(AND(Programme_Grunddaten!$A16="Geprüft",Programme_Grunddaten!P16<>""),IF(Programme_Grunddaten!P16="Ja",1,0),"") | J8: =IF(AND(Programme_Grunddaten!$A16="Geprüft",Programme_Grunddaten!Q16<>""),IF(Programme_Grunddaten!Q16="geschlossenes System",1,0),"") -> 0 | K8: =IF(AND(Programme_Grunddaten!$A16="Geprüft",Programme_Grunddaten!R16<>""),IF(Programme_Grunddaten!R16="Ja",1,0),"") -> 1 | L8: =IF(AND(Programme_Grunddaten!$A16="Geprüft",Programme_Grunddaten!T16<>""),IF(Programme_Grunddaten!T16="Ja",1,0),"") -> 1 | M8: =IF(AND(Programme_Grunddaten!$A16="Geprüft",Programme_Grunddaten!U16<>""),IF(Programme_Grunddaten!U16="Ja",1,0),"") -> 1 | N8: =IF(AND(Programme_Grunddaten!$A16="Geprüft",Programme_Grunddaten!V16<>""),IF(Programme_Grunddaten!V16="Ja",1,0),"") -> 1 | O8: =IF(AND(Programme_Grunddaten!$A16="Geprüft",Programme_Grunddaten!W16<>""),IF(Programme_Grunddaten!W16="Ja",1,0),"") -> 1 | P8: =IF(AND(Programme_Grunddaten!$A16="Geprüft",Programme_Grunddaten!X16<>""),IF(Programme_Grunddaten!X16="Ja",1,0),"") | Q8: =IF(AND(Programme_Grunddaten!$A16="Geprüft",Programme_Grunddaten!Y16<>""),IF(Programme_Grunddaten!Y16="Ja",1,0),"") -> 1 | R8: =IF(AND(Programme_Grunddaten!$A16="Geprüft",Programme_Grunddaten!Z16<>""),IF(Programme_Grunddaten!Z16="Ja",1,0),"") -> 0 | S8: =IF(AND(Programme_Grunddaten!$A16="Geprüft",Programme_Grunddaten!AA16<>""),IF(Programme_Grunddaten!AA16="monolithisch",1,0),"") -> 0 | T8: =IF(AND(Programme_Grunddaten!$A16="Geprüft",Programme_Grunddaten!AB16<>""),IF(Programme_Grunddaten!AB16="Ja",1,0),"") -> 1 | U8: =IF(AND(Programme_Grunddaten!$A16="Geprüft",Programme_Grunddaten!AC16<>""),IF(Programme_Grunddaten!AC16="Ja",1,0),"") -> 1 | V8: =IF(AND(Programme_Grunddaten!$A16="Geprüft",Programme_Grunddaten!AD16<>""),IF(Programme_Grunddaten!AD16="Ja",1,0),"") -> 1 | W8: =IF(AND(Programme_Grunddaten!$A16="Geprüft",Programme_Grunddaten!AE16<>""),IF(Programme_Grunddaten!AE16="Ja",1,0),"") -> 1 | X8: =IF(AND(Programme_Grunddaten!$A16="Geprüft",Programme_Grunddaten!AF16<>""),IF(Programme_Grunddaten!AF16="Ja",1,0),"") -> 1 | Y8: =IF(AND(Programme_Grunddaten!$A16="Geprüft",Programme_Grunddaten!AG16<>""),IF(Programme_Grunddaten!AG16="Ja",1,0),"") -> 1 | Z8: =IF(AND(Programme_Grunddaten!$A16="Geprüft",Programme_Grunddaten!AH16<>""),IF(Programme_Grunddaten!AH16="Ja",1,0),"") | AA8: =IF(AND(Programme_Grunddaten!$A16="Geprüft",Programme_Grunddaten!AI16<>""),IF(Programme_Grunddaten!AI16="Ja",1,0),"") -> 1 | AB8: =IF(AND(Programme_Grunddaten!$A16="Geprüft",Programme_Grunddaten!AJ16<>""),IF(Programme_Grunddaten!AJ16="individuell programmierbar",1,0),"") | AC8: =IF(AND(Programme_Grunddaten!$A16="Geprüft",Programme_Grunddaten!AK16<>""),IF(Programme_Grunddaten!AK16="Deutsch",0,IF(Programme_Grunddaten!AK16="Deutsch und Englisch",1,2)),"") | AD8: =IF(AND(Programme_Grunddaten!$A16="Geprüft",Programme_Grunddaten!AL16<>""),IF(Programme_Grunddaten!AL16="Ja",1,0),"") -> 1 | AE8: =IF(AND(Programme_Grunddaten!$A16="Geprüft",Programme_Grunddaten!AM16<>""),IF(Programme_Grunddaten!AM16="Ja",1,0),"") -> 0 | AF8: =IF(AND(Programme_Grunddaten!$A16="Geprüft",Programme_Grunddaten!AN16<>""),IF(Programme_Grunddaten!AN16="Ja",1,0),"") | AG8: =IF(AND(Programme_Grunddaten!$A16="Geprüft",Programme_Grunddaten!AO16<>""),IF(Programme_Grunddaten!AO16="Ja",1,0),"") -> 0 | AH8: =IF(AND(Programme_Grunddaten!$A16="Geprüft",Programme_Grunddaten!AP16<>""),IF(Programme_Grunddaten!AP16="Ja",1,0),"") | AI8: =IF(AND(Programme_Grunddaten!$A16="Geprüft",Programme_Grunddaten!AQ16<>""),IF(Programme_Grunddaten!AQ16="Ja",1,0),"") -> 1 | AJ8: =IF(AND(Programme_Grunddaten!$A16="Geprüft",Programme_Grunddaten!AR16<>""),IF(Programme_Grunddaten!AR16="Ja",1,0),"") -> 1 | AK8: =IF(AND(Programme_Grunddaten!$A16="Geprüft",Programme_Grunddaten!AS16<>""),IF(Programme_Grunddaten!AS16="Ja",1,0),"") -> 1 | ... AN8: =IF(AND(Programme_Grunddaten!$A16="Geprüft",Programme_Grunddaten!AV16<>""),IF(Programme_Grunddaten!AV16="Ja",1,0),"")
A9: =IF(AND(Programme_Grunddaten!A17="Geprüft",Programme_Grunddaten!B17<>""),Programme_Grunddaten!B17,"") -> P08 | B9: =IF(AND(Programme_Grunddaten!$A17="Geprüft",Programme_Grunddaten!I17<>""),IF(Programme_Grunddaten!I17="Ja",1,0),"") -> 0 | C9: =IF(AND(Programme_Grunddaten!$A17="Geprüft",Programme_Grunddaten!J17<>""),IF(Programme_Grunddaten!J17="Ja",1,0),"") -> 1 | D9: =IF(AND(Programme_Grunddaten!$A17="Geprüft",Programme_Grunddaten!K17<>""),IF(Programme_Grunddaten!K17="Ja",1,0),"") -> 0 | E9: =IF(AND(Programme_Grunddaten!$A17="Geprüft",Programme_Grunddaten!L17<>""),IF(Programme_Grunddaten!L17="Abo / befristete Lizenz",1,0),"") -> 1 | F9: =IF(AND(Programme_Grunddaten!$A17="Geprüft",Programme_Grunddaten!M17<>""),IF(Programme_Grunddaten!M17="Ja",1,0),"") -> 0 | G9: =IF(AND(Programme_Grunddaten!$A17="Geprüft",Programme_Grunddaten!N17<>""),IF(Programme_Grunddaten!N17="Ja",1,0),"") -> 1 | H9: =IF(AND(Programme_Grunddaten!$A17="Geprüft",Programme_Grunddaten!O17<>""),IF(Programme_Grunddaten!O17="Deutschland",0,IF(Programme_Grunddaten!O17="EU",1,2)),"") | I9: =IF(AND(Programme_Grunddaten!$A17="Geprüft",Programme_Grunddaten!P17<>""),IF(Programme_Grunddaten!P17="Ja",1,0),"") -> 1 | J9: =IF(AND(Programme_Grunddaten!$A17="Geprüft",Programme_Grunddaten!Q17<>""),IF(Programme_Grunddaten!Q17="geschlossenes System",1,0),"") -> 0 | K9: =IF(AND(Programme_Grunddaten!$A17="Geprüft",Programme_Grunddaten!R17<>""),IF(Programme_Grunddaten!R17="Ja",1,0),"") -> 1 | L9: =IF(AND(Programme_Grunddaten!$A17="Geprüft",Programme_Grunddaten!T17<>""),IF(Programme_Grunddaten!T17="Ja",1,0),"") -> 1 | M9: =IF(AND(Programme_Grunddaten!$A17="Geprüft",Programme_Grunddaten!U17<>""),IF(Programme_Grunddaten!U17="Ja",1,0),"") -> 1 | N9: =IF(AND(Programme_Grunddaten!$A17="Geprüft",Programme_Grunddaten!V17<>""),IF(Programme_Grunddaten!V17="Ja",1,0),"") -> 1 | O9: =IF(AND(Programme_Grunddaten!$A17="Geprüft",Programme_Grunddaten!W17<>""),IF(Programme_Grunddaten!W17="Ja",1,0),"") -> 1 | P9: =IF(AND(Programme_Grunddaten!$A17="Geprüft",Programme_Grunddaten!X17<>""),IF(Programme_Grunddaten!X17="Ja",1,0),"") -> 1 | Q9: =IF(AND(Programme_Grunddaten!$A17="Geprüft",Programme_Grunddaten!Y17<>""),IF(Programme_Grunddaten!Y17="Ja",1,0),"") | R9: =IF(AND(Programme_Grunddaten!$A17="Geprüft",Programme_Grunddaten!Z17<>""),IF(Programme_Grunddaten!Z17="Ja",1,0),"") -> 0 | S9: =IF(AND(Programme_Grunddaten!$A17="Geprüft",Programme_Grunddaten!AA17<>""),IF(Programme_Grunddaten!AA17="monolithisch",1,0),"") -> 0 | T9: =IF(AND(Programme_Grunddaten!$A17="Geprüft",Programme_Grunddaten!AB17<>""),IF(Programme_Grunddaten!AB17="Ja",1,0),"") -> 1 | U9: =IF(AND(Programme_Grunddaten!$A17="Geprüft",Programme_Grunddaten!AC17<>""),IF(Programme_Grunddaten!AC17="Ja",1,0),"") -> 1 | V9: =IF(AND(Programme_Grunddaten!$A17="Geprüft",Programme_Grunddaten!AD17<>""),IF(Programme_Grunddaten!AD17="Ja",1,0),"") -> 1 | W9: =IF(AND(Programme_Grunddaten!$A17="Geprüft",Programme_Grunddaten!AE17<>""),IF(Programme_Grunddaten!AE17="Ja",1,0),"") -> 1 | X9: =IF(AND(Programme_Grunddaten!$A17="Geprüft",Programme_Grunddaten!AF17<>""),IF(Programme_Grunddaten!AF17="Ja",1,0),"") -> 1 | Y9: =IF(AND(Programme_Grunddaten!$A17="Geprüft",Programme_Grunddaten!AG17<>""),IF(Programme_Grunddaten!AG17="Ja",1,0),"") -> 1 | Z9: =IF(AND(Programme_Grunddaten!$A17="Geprüft",Programme_Grunddaten!AH17<>""),IF(Programme_Grunddaten!AH17="Ja",1,0),"") | AA9: =IF(AND(Programme_Grunddaten!$A17="Geprüft",Programme_Grunddaten!AI17<>""),IF(Programme_Grunddaten!AI17="Ja",1,0),"") -> 1 | AB9: =IF(AND(Programme_Grunddaten!$A17="Geprüft",Programme_Grunddaten!AJ17<>""),IF(Programme_Grunddaten!AJ17="individuell programmierbar",1,0),"") | AC9: =IF(AND(Programme_Grunddaten!$A17="Geprüft",Programme_Grunddaten!AK17<>""),IF(Programme_Grunddaten!AK17="Deutsch",0,IF(Programme_Grunddaten!AK17="Deutsch und Englisch",1,2)),"") -> 2 | AD9: =IF(AND(Programme_Grunddaten!$A17="Geprüft",Programme_Grunddaten!AL17<>""),IF(Programme_Grunddaten!AL17="Ja",1,0),"") -> 1 | AE9: =IF(AND(Programme_Grunddaten!$A17="Geprüft",Programme_Grunddaten!AM17<>""),IF(Programme_Grunddaten!AM17="Ja",1,0),"") -> 0 | AF9: =IF(AND(Programme_Grunddaten!$A17="Geprüft",Programme_Grunddaten!AN17<>""),IF(Programme_Grunddaten!AN17="Ja",1,0),"") | AG9: =IF(AND(Programme_Grunddaten!$A17="Geprüft",Programme_Grunddaten!AO17<>""),IF(Programme_Grunddaten!AO17="Ja",1,0),"") -> 0 | AH9: =IF(AND(Programme_Grunddaten!$A17="Geprüft",Programme_Grunddaten!AP17<>""),IF(Programme_Grunddaten!AP17="Ja",1,0),"") | AI9: =IF(AND(Programme_Grunddaten!$A17="Geprüft",Programme_Grunddaten!AQ17<>""),IF(Programme_Grunddaten!AQ17="Ja",1,0),"") -> 1 | AJ9: =IF(AND(Programme_Grunddaten!$A17="Geprüft",Programme_Grunddaten!AR17<>""),IF(Programme_Grunddaten!AR17="Ja",1,0),"") -> 1 | AK9: =IF(AND(Programme_Grunddaten!$A17="Geprüft",Programme_Grunddaten!AS17<>""),IF(Programme_Grunddaten!AS17="Ja",1,0),"") | ... AN9: =IF(AND(Programme_Grunddaten!$A17="Geprüft",Programme_Grunddaten!AV17<>""),IF(Programme_Grunddaten!AV17="Ja",1,0),"") -> 0
A10: =IF(AND(Programme_Grunddaten!A18="Geprüft",Programme_Grunddaten!B18<>""),Programme_Grunddaten!B18,"") -> P09 | B10: =IF(AND(Programme_Grunddaten!$A18="Geprüft",Programme_Grunddaten!I18<>""),IF(Programme_Grunddaten!I18="Ja",1,0),"") -> 0 | C10: =IF(AND(Programme_Grunddaten!$A18="Geprüft",Programme_Grunddaten!J18<>""),IF(Programme_Grunddaten!J18="Ja",1,0),"") -> 1 | D10: =IF(AND(Programme_Grunddaten!$A18="Geprüft",Programme_Grunddaten!K18<>""),IF(Programme_Grunddaten!K18="Ja",1,0),"") -> 0 | E10: =IF(AND(Programme_Grunddaten!$A18="Geprüft",Programme_Grunddaten!L18<>""),IF(Programme_Grunddaten!L18="Abo / befristete Lizenz",1,0),"") | F10: =IF(AND(Programme_Grunddaten!$A18="Geprüft",Programme_Grunddaten!M18<>""),IF(Programme_Grunddaten!M18="Ja",1,0),"") -> 1 | G10: =IF(AND(Programme_Grunddaten!$A18="Geprüft",Programme_Grunddaten!N18<>""),IF(Programme_Grunddaten!N18="Ja",1,0),"") -> 1 | H10: =IF(AND(Programme_Grunddaten!$A18="Geprüft",Programme_Grunddaten!O18<>""),IF(Programme_Grunddaten!O18="Deutschland",0,IF(Programme_Grunddaten!O18="EU",1,2)),"") -> 0 | I10: =IF(AND(Programme_Grunddaten!$A18="Geprüft",Programme_Grunddaten!P18<>""),IF(Programme_Grunddaten!P18="Ja",1,0),"") -> 1 | J10: =IF(AND(Programme_Grunddaten!$A18="Geprüft",Programme_Grunddaten!Q18<>""),IF(Programme_Grunddaten!Q18="geschlossenes System",1,0),"") -> 0 | K10: =IF(AND(Programme_Grunddaten!$A18="Geprüft",Programme_Grunddaten!R18<>""),IF(Programme_Grunddaten!R18="Ja",1,0),"") -> 1 | L10: =IF(AND(Programme_Grunddaten!$A18="Geprüft",Programme_Grunddaten!T18<>""),IF(Programme_Grunddaten!T18="Ja",1,0),"") -> 1 | M10: =IF(AND(Programme_Grunddaten!$A18="Geprüft",Programme_Grunddaten!U18<>""),IF(Programme_Grunddaten!U18="Ja",1,0),"") -> 1 | N10: =IF(AND(Programme_Grunddaten!$A18="Geprüft",Programme_Grunddaten!V18<>""),IF(Programme_Grunddaten!V18="Ja",1,0),"") -> 1 | O10: =IF(AND(Programme_Grunddaten!$A18="Geprüft",Programme_Grunddaten!W18<>""),IF(Programme_Grunddaten!W18="Ja",1,0),"") -> 1 | P10: =IF(AND(Programme_Grunddaten!$A18="Geprüft",Programme_Grunddaten!X18<>""),IF(Programme_Grunddaten!X18="Ja",1,0),"") -> 1 | Q10: =IF(AND(Programme_Grunddaten!$A18="Geprüft",Programme_Grunddaten!Y18<>""),IF(Programme_Grunddaten!Y18="Ja",1,0),"") | R10: =IF(AND(Programme_Grunddaten!$A18="Geprüft",Programme_Grunddaten!Z18<>""),IF(Programme_Grunddaten!Z18="Ja",1,0),"") -> 0 | S10: =IF(AND(Programme_Grunddaten!$A18="Geprüft",Programme_Grunddaten!AA18<>""),IF(Programme_Grunddaten!AA18="monolithisch",1,0),"") -> 0 | T10: =IF(AND(Programme_Grunddaten!$A18="Geprüft",Programme_Grunddaten!AB18<>""),IF(Programme_Grunddaten!AB18="Ja",1,0),"") -> 1 | U10: =IF(AND(Programme_Grunddaten!$A18="Geprüft",Programme_Grunddaten!AC18<>""),IF(Programme_Grunddaten!AC18="Ja",1,0),"") -> 1 | V10: =IF(AND(Programme_Grunddaten!$A18="Geprüft",Programme_Grunddaten!AD18<>""),IF(Programme_Grunddaten!AD18="Ja",1,0),"") -> 1 | W10: =IF(AND(Programme_Grunddaten!$A18="Geprüft",Programme_Grunddaten!AE18<>""),IF(Programme_Grunddaten!AE18="Ja",1,0),"") | X10: =IF(AND(Programme_Grunddaten!$A18="Geprüft",Programme_Grunddaten!AF18<>""),IF(Programme_Grunddaten!AF18="Ja",1,0),"") -> 1 | Y10: =IF(AND(Programme_Grunddaten!$A18="Geprüft",Programme_Grunddaten!AG18<>""),IF(Programme_Grunddaten!AG18="Ja",1,0),"") -> 1 | Z10: =IF(AND(Programme_Grunddaten!$A18="Geprüft",Programme_Grunddaten!AH18<>""),IF(Programme_Grunddaten!AH18="Ja",1,0),"") | AA10: =IF(AND(Programme_Grunddaten!$A18="Geprüft",Programme_Grunddaten!AI18<>""),IF(Programme_Grunddaten!AI18="Ja",1,0),"") -> 1 | AB10: =IF(AND(Programme_Grunddaten!$A18="Geprüft",Programme_Grunddaten!AJ18<>""),IF(Programme_Grunddaten!AJ18="individuell programmierbar",1,0),"") | AC10: =IF(AND(Programme_Grunddaten!$A18="Geprüft",Programme_Grunddaten!AK18<>""),IF(Programme_Grunddaten!AK18="Deutsch",0,IF(Programme_Grunddaten!AK18="Deutsch und Englisch",1,2)),"") -> 1 | AD10: =IF(AND(Programme_Grunddaten!$A18="Geprüft",Programme_Grunddaten!AL18<>""),IF(Programme_Grunddaten!AL18="Ja",1,0),"") -> 1 | AE10: =IF(AND(Programme_Grunddaten!$A18="Geprüft",Programme_Grunddaten!AM18<>""),IF(Programme_Grunddaten!AM18="Ja",1,0),"") -> 0 | AF10: =IF(AND(Programme_Grunddaten!$A18="Geprüft",Programme_Grunddaten!AN18<>""),IF(Programme_Grunddaten!AN18="Ja",1,0),"") | AG10: =IF(AND(Programme_Grunddaten!$A18="Geprüft",Programme_Grunddaten!AO18<>""),IF(Programme_Grunddaten!AO18="Ja",1,0),"") -> 0 | AH10: =IF(AND(Programme_Grunddaten!$A18="Geprüft",Programme_Grunddaten!AP18<>""),IF(Programme_Grunddaten!AP18="Ja",1,0),"") -> 1 | AI10: =IF(AND(Programme_Grunddaten!$A18="Geprüft",Programme_Grunddaten!AQ18<>""),IF(Programme_Grunddaten!AQ18="Ja",1,0),"") -> 1 | AJ10: =IF(AND(Programme_Grunddaten!$A18="Geprüft",Programme_Grunddaten!AR18<>""),IF(Programme_Grunddaten!AR18="Ja",1,0),"") -> 1 | AK10: =IF(AND(Programme_Grunddaten!$A18="Geprüft",Programme_Grunddaten!AS18<>""),IF(Programme_Grunddaten!AS18="Ja",1,0),"") -> 1 | ... AN10: =IF(AND(Programme_Grunddaten!$A18="Geprüft",Programme_Grunddaten!AV18<>""),IF(Programme_Grunddaten!AV18="Ja",1,0),"")
A11: =IF(AND(Programme_Grunddaten!A19="Geprüft",Programme_Grunddaten!B19<>""),Programme_Grunddaten!B19,"") -> P10 | B11: =IF(AND(Programme_Grunddaten!$A19="Geprüft",Programme_Grunddaten!I19<>""),IF(Programme_Grunddaten!I19="Ja",1,0),"") -> 0 | C11: =IF(AND(Programme_Grunddaten!$A19="Geprüft",Programme_Grunddaten!J19<>""),IF(Programme_Grunddaten!J19="Ja",1,0),"") -> 1 | D11: =IF(AND(Programme_Grunddaten!$A19="Geprüft",Programme_Grunddaten!K19<>""),IF(Programme_Grunddaten!K19="Ja",1,0),"") -> 0 | E11: =IF(AND(Programme_Grunddaten!$A19="Geprüft",Programme_Grunddaten!L19<>""),IF(Programme_Grunddaten!L19="Abo / befristete Lizenz",1,0),"") -> 1 | F11: =IF(AND(Programme_Grunddaten!$A19="Geprüft",Programme_Grunddaten!M19<>""),IF(Programme_Grunddaten!M19="Ja",1,0),"") -> 0 | G11: =IF(AND(Programme_Grunddaten!$A19="Geprüft",Programme_Grunddaten!N19<>""),IF(Programme_Grunddaten!N19="Ja",1,0),"") -> 1 | H11: =IF(AND(Programme_Grunddaten!$A19="Geprüft",Programme_Grunddaten!O19<>""),IF(Programme_Grunddaten!O19="Deutschland",0,IF(Programme_Grunddaten!O19="EU",1,2)),"") | I11: =IF(AND(Programme_Grunddaten!$A19="Geprüft",Programme_Grunddaten!P19<>""),IF(Programme_Grunddaten!P19="Ja",1,0),"") -> 1 | J11: =IF(AND(Programme_Grunddaten!$A19="Geprüft",Programme_Grunddaten!Q19<>""),IF(Programme_Grunddaten!Q19="geschlossenes System",1,0),"") -> 0 | K11: =IF(AND(Programme_Grunddaten!$A19="Geprüft",Programme_Grunddaten!R19<>""),IF(Programme_Grunddaten!R19="Ja",1,0),"") -> 1 | L11: =IF(AND(Programme_Grunddaten!$A19="Geprüft",Programme_Grunddaten!T19<>""),IF(Programme_Grunddaten!T19="Ja",1,0),"") -> 1 | M11: =IF(AND(Programme_Grunddaten!$A19="Geprüft",Programme_Grunddaten!U19<>""),IF(Programme_Grunddaten!U19="Ja",1,0),"") -> 1 | N11: =IF(AND(Programme_Grunddaten!$A19="Geprüft",Programme_Grunddaten!V19<>""),IF(Programme_Grunddaten!V19="Ja",1,0),"") | O11: =IF(AND(Programme_Grunddaten!$A19="Geprüft",Programme_Grunddaten!W19<>""),IF(Programme_Grunddaten!W19="Ja",1,0),"") -> 1 | P11: =IF(AND(Programme_Grunddaten!$A19="Geprüft",Programme_Grunddaten!X19<>""),IF(Programme_Grunddaten!X19="Ja",1,0),"") -> 1 | Q11: =IF(AND(Programme_Grunddaten!$A19="Geprüft",Programme_Grunddaten!Y19<>""),IF(Programme_Grunddaten!Y19="Ja",1,0),"") | R11: =IF(AND(Programme_Grunddaten!$A19="Geprüft",Programme_Grunddaten!Z19<>""),IF(Programme_Grunddaten!Z19="Ja",1,0),"") -> 0 | S11: =IF(AND(Programme_Grunddaten!$A19="Geprüft",Programme_Grunddaten!AA19<>""),IF(Programme_Grunddaten!AA19="monolithisch",1,0),"") -> 0 | T11: =IF(AND(Programme_Grunddaten!$A19="Geprüft",Programme_Grunddaten!AB19<>""),IF(Programme_Grunddaten!AB19="Ja",1,0),"") -> 1 | U11: =IF(AND(Programme_Grunddaten!$A19="Geprüft",Programme_Grunddaten!AC19<>""),IF(Programme_Grunddaten!AC19="Ja",1,0),"") -> 1 | V11: =IF(AND(Programme_Grunddaten!$A19="Geprüft",Programme_Grunddaten!AD19<>""),IF(Programme_Grunddaten!AD19="Ja",1,0),"") | W11: =IF(AND(Programme_Grunddaten!$A19="Geprüft",Programme_Grunddaten!AE19<>""),IF(Programme_Grunddaten!AE19="Ja",1,0),"") | X11: =IF(AND(Programme_Grunddaten!$A19="Geprüft",Programme_Grunddaten!AF19<>""),IF(Programme_Grunddaten!AF19="Ja",1,0),"") -> 1 | Y11: =IF(AND(Programme_Grunddaten!$A19="Geprüft",Programme_Grunddaten!AG19<>""),IF(Programme_Grunddaten!AG19="Ja",1,0),"") -> 1 | Z11: =IF(AND(Programme_Grunddaten!$A19="Geprüft",Programme_Grunddaten!AH19<>""),IF(Programme_Grunddaten!AH19="Ja",1,0),"") | AA11: =IF(AND(Programme_Grunddaten!$A19="Geprüft",Programme_Grunddaten!AI19<>""),IF(Programme_Grunddaten!AI19="Ja",1,0),"") -> 1 | AB11: =IF(AND(Programme_Grunddaten!$A19="Geprüft",Programme_Grunddaten!AJ19<>""),IF(Programme_Grunddaten!AJ19="individuell programmierbar",1,0),"") | AC11: =IF(AND(Programme_Grunddaten!$A19="Geprüft",Programme_Grunddaten!AK19<>""),IF(Programme_Grunddaten!AK19="Deutsch",0,IF(Programme_Grunddaten!AK19="Deutsch und Englisch",1,2)),"") -> 2 | AD11: =IF(AND(Programme_Grunddaten!$A19="Geprüft",Programme_Grunddaten!AL19<>""),IF(Programme_Grunddaten!AL19="Ja",1,0),"") -> 1 | AE11: =IF(AND(Programme_Grunddaten!$A19="Geprüft",Programme_Grunddaten!AM19<>""),IF(Programme_Grunddaten!AM19="Ja",1,0),"") -> 0 | AF11: =IF(AND(Programme_Grunddaten!$A19="Geprüft",Programme_Grunddaten!AN19<>""),IF(Programme_Grunddaten!AN19="Ja",1,0),"") | AG11: =IF(AND(Programme_Grunddaten!$A19="Geprüft",Programme_Grunddaten!AO19<>""),IF(Programme_Grunddaten!AO19="Ja",1,0),"") -> 0 | AH11: =IF(AND(Programme_Grunddaten!$A19="Geprüft",Programme_Grunddaten!AP19<>""),IF(Programme_Grunddaten!AP19="Ja",1,0),"") | AI11: =IF(AND(Programme_Grunddaten!$A19="Geprüft",Programme_Grunddaten!AQ19<>""),IF(Programme_Grunddaten!AQ19="Ja",1,0),"") -> 1 | AJ11: =IF(AND(Programme_Grunddaten!$A19="Geprüft",Programme_Grunddaten!AR19<>""),IF(Programme_Grunddaten!AR19="Ja",1,0),"") -> 1 | AK11: =IF(AND(Programme_Grunddaten!$A19="Geprüft",Programme_Grunddaten!AS19<>""),IF(Programme_Grunddaten!AS19="Ja",1,0),"") -> 1 | ... AN11: =IF(AND(Programme_Grunddaten!$A19="Geprüft",Programme_Grunddaten!AV19<>""),IF(Programme_Grunddaten!AV19="Ja",1,0),"")
A12: =IF(AND(Programme_Grunddaten!A20="Geprüft",Programme_Grunddaten!B20<>""),Programme_Grunddaten!B20,"") -> P11 | B12: =IF(AND(Programme_Grunddaten!$A20="Geprüft",Programme_Grunddaten!I20<>""),IF(Programme_Grunddaten!I20="Ja",1,0),"") -> 0 | C12: =IF(AND(Programme_Grunddaten!$A20="Geprüft",Programme_Grunddaten!J20<>""),IF(Programme_Grunddaten!J20="Ja",1,0),"") -> 1 | D12: =IF(AND(Programme_Grunddaten!$A20="Geprüft",Programme_Grunddaten!K20<>""),IF(Programme_Grunddaten!K20="Ja",1,0),"") -> 0 | E12: =IF(AND(Programme_Grunddaten!$A20="Geprüft",Programme_Grunddaten!L20<>""),IF(Programme_Grunddaten!L20="Abo / befristete Lizenz",1,0),"") | F12: =IF(AND(Programme_Grunddaten!$A20="Geprüft",Programme_Grunddaten!M20<>""),IF(Programme_Grunddaten!M20="Ja",1,0),"") -> 0 | G12: =IF(AND(Programme_Grunddaten!$A20="Geprüft",Programme_Grunddaten!N20<>""),IF(Programme_Grunddaten!N20="Ja",1,0),"") -> 1 | H12: =IF(AND(Programme_Grunddaten!$A20="Geprüft",Programme_Grunddaten!O20<>""),IF(Programme_Grunddaten!O20="Deutschland",0,IF(Programme_Grunddaten!O20="EU",1,2)),"") -> 0 | I12: =IF(AND(Programme_Grunddaten!$A20="Geprüft",Programme_Grunddaten!P20<>""),IF(Programme_Grunddaten!P20="Ja",1,0),"") -> 1 | J12: =IF(AND(Programme_Grunddaten!$A20="Geprüft",Programme_Grunddaten!Q20<>""),IF(Programme_Grunddaten!Q20="geschlossenes System",1,0),"") -> 0 | K12: =IF(AND(Programme_Grunddaten!$A20="Geprüft",Programme_Grunddaten!R20<>""),IF(Programme_Grunddaten!R20="Ja",1,0),"") | L12: =IF(AND(Programme_Grunddaten!$A20="Geprüft",Programme_Grunddaten!T20<>""),IF(Programme_Grunddaten!T20="Ja",1,0),"") -> 1 | M12: =IF(AND(Programme_Grunddaten!$A20="Geprüft",Programme_Grunddaten!U20<>""),IF(Programme_Grunddaten!U20="Ja",1,0),"") -> 1 | N12: =IF(AND(Programme_Grunddaten!$A20="Geprüft",Programme_Grunddaten!V20<>""),IF(Programme_Grunddaten!V20="Ja",1,0),"") | O12: =IF(AND(Programme_Grunddaten!$A20="Geprüft",Programme_Grunddaten!W20<>""),IF(Programme_Grunddaten!W20="Ja",1,0),"") -> 1 | P12: =IF(AND(Programme_Grunddaten!$A20="Geprüft",Programme_Grunddaten!X20<>""),IF(Programme_Grunddaten!X20="Ja",1,0),"") | Q12: =IF(AND(Programme_Grunddaten!$A20="Geprüft",Programme_Grunddaten!Y20<>""),IF(Programme_Grunddaten!Y20="Ja",1,0),"") -> 1 | R12: =IF(AND(Programme_Grunddaten!$A20="Geprüft",Programme_Grunddaten!Z20<>""),IF(Programme_Grunddaten!Z20="Ja",1,0),"") -> 0 | S12: =IF(AND(Programme_Grunddaten!$A20="Geprüft",Programme_Grunddaten!AA20<>""),IF(Programme_Grunddaten!AA20="monolithisch",1,0),"") | T12: =IF(AND(Programme_Grunddaten!$A20="Geprüft",Programme_Grunddaten!AB20<>""),IF(Programme_Grunddaten!AB20="Ja",1,0),"") -> 1 | U12: =IF(AND(Programme_Grunddaten!$A20="Geprüft",Programme_Grunddaten!AC20<>""),IF(Programme_Grunddaten!AC20="Ja",1,0),"") | V12: =IF(AND(Programme_Grunddaten!$A20="Geprüft",Programme_Grunddaten!AD20<>""),IF(Programme_Grunddaten!AD20="Ja",1,0),"") | W12: =IF(AND(Programme_Grunddaten!$A20="Geprüft",Programme_Grunddaten!AE20<>""),IF(Programme_Grunddaten!AE20="Ja",1,0),"") | X12: =IF(AND(Programme_Grunddaten!$A20="Geprüft",Programme_Grunddaten!AF20<>""),IF(Programme_Grunddaten!AF20="Ja",1,0),"") -> 1 | Y12: =IF(AND(Programme_Grunddaten!$A20="Geprüft",Programme_Grunddaten!AG20<>""),IF(Programme_Grunddaten!AG20="Ja",1,0),"") | Z12: =IF(AND(Programme_Grunddaten!$A20="Geprüft",Programme_Grunddaten!AH20<>""),IF(Programme_Grunddaten!AH20="Ja",1,0),"") | AA12: =IF(AND(Programme_Grunddaten!$A20="Geprüft",Programme_Grunddaten!AI20<>""),IF(Programme_Grunddaten!AI20="Ja",1,0),"") -> 1 | AB12: =IF(AND(Programme_Grunddaten!$A20="Geprüft",Programme_Grunddaten!AJ20<>""),IF(Programme_Grunddaten!AJ20="individuell programmierbar",1,0),"") -> 1 | AC12: =IF(AND(Programme_Grunddaten!$A20="Geprüft",Programme_Grunddaten!AK20<>""),IF(Programme_Grunddaten!AK20="Deutsch",0,IF(Programme_Grunddaten!AK20="Deutsch und Englisch",1,2)),"") -> 2 | AD12: =IF(AND(Programme_Grunddaten!$A20="Geprüft",Programme_Grunddaten!AL20<>""),IF(Programme_Grunddaten!AL20="Ja",1,0),"") -> 1 | AE12: =IF(AND(Programme_Grunddaten!$A20="Geprüft",Programme_Grunddaten!AM20<>""),IF(Programme_Grunddaten!AM20="Ja",1,0),"") -> 0 | AF12: =IF(AND(Programme_Grunddaten!$A20="Geprüft",Programme_Grunddaten!AN20<>""),IF(Programme_Grunddaten!AN20="Ja",1,0),"") | AG12: =IF(AND(Programme_Grunddaten!$A20="Geprüft",Programme_Grunddaten!AO20<>""),IF(Programme_Grunddaten!AO20="Ja",1,0),"") -> 0 | AH12: =IF(AND(Programme_Grunddaten!$A20="Geprüft",Programme_Grunddaten!AP20<>""),IF(Programme_Grunddaten!AP20="Ja",1,0),"") | AI12: =IF(AND(Programme_Grunddaten!$A20="Geprüft",Programme_Grunddaten!AQ20<>""),IF(Programme_Grunddaten!AQ20="Ja",1,0),"") -> 1 | AJ12: =IF(AND(Programme_Grunddaten!$A20="Geprüft",Programme_Grunddaten!AR20<>""),IF(Programme_Grunddaten!AR20="Ja",1,0),"") -> 1 | AK12: =IF(AND(Programme_Grunddaten!$A20="Geprüft",Programme_Grunddaten!AS20<>""),IF(Programme_Grunddaten!AS20="Ja",1,0),"") -> 1 | ... AN12: =IF(AND(Programme_Grunddaten!$A20="Geprüft",Programme_Grunddaten!AV20<>""),IF(Programme_Grunddaten!AV20="Ja",1,0),"")
A13: =IF(AND(Programme_Grunddaten!A21="Geprüft",Programme_Grunddaten!B21<>""),Programme_Grunddaten!B21,"") -> P12 | B13: =IF(AND(Programme_Grunddaten!$A21="Geprüft",Programme_Grunddaten!I21<>""),IF(Programme_Grunddaten!I21="Ja",1,0),"") -> 0 | C13: =IF(AND(Programme_Grunddaten!$A21="Geprüft",Programme_Grunddaten!J21<>""),IF(Programme_Grunddaten!J21="Ja",1,0),"") -> 1 | D13: =IF(AND(Programme_Grunddaten!$A21="Geprüft",Programme_Grunddaten!K21<>""),IF(Programme_Grunddaten!K21="Ja",1,0),"") -> 0 | E13: =IF(AND(Programme_Grunddaten!$A21="Geprüft",Programme_Grunddaten!L21<>""),IF(Programme_Grunddaten!L21="Abo / befristete Lizenz",1,0),"") -> 1 | F13: =IF(AND(Programme_Grunddaten!$A21="Geprüft",Programme_Grunddaten!M21<>""),IF(Programme_Grunddaten!M21="Ja",1,0),"") -> 1 | G13: =IF(AND(Programme_Grunddaten!$A21="Geprüft",Programme_Grunddaten!N21<>""),IF(Programme_Grunddaten!N21="Ja",1,0),"") -> 0 | H13: =IF(AND(Programme_Grunddaten!$A21="Geprüft",Programme_Grunddaten!O21<>""),IF(Programme_Grunddaten!O21="Deutschland",0,IF(Programme_Grunddaten!O21="EU",1,2)),"") -> 0 | I13: =IF(AND(Programme_Grunddaten!$A21="Geprüft",Programme_Grunddaten!P21<>""),IF(Programme_Grunddaten!P21="Ja",1,0),"") -> 1 | J13: =IF(AND(Programme_Grunddaten!$A21="Geprüft",Programme_Grunddaten!Q21<>""),IF(Programme_Grunddaten!Q21="geschlossenes System",1,0),"") -> 0 | K13: =IF(AND(Programme_Grunddaten!$A21="Geprüft",Programme_Grunddaten!R21<>""),IF(Programme_Grunddaten!R21="Ja",1,0),"") -> 1 | L13: =IF(AND(Programme_Grunddaten!$A21="Geprüft",Programme_Grunddaten!T21<>""),IF(Programme_Grunddaten!T21="Ja",1,0),"") -> 1 | M13: =IF(AND(Programme_Grunddaten!$A21="Geprüft",Programme_Grunddaten!U21<>""),IF(Programme_Grunddaten!U21="Ja",1,0),"") -> 1 | N13: =IF(AND(Programme_Grunddaten!$A21="Geprüft",Programme_Grunddaten!V21<>""),IF(Programme_Grunddaten!V21="Ja",1,0),"") | O13: =IF(AND(Programme_Grunddaten!$A21="Geprüft",Programme_Grunddaten!W21<>""),IF(Programme_Grunddaten!W21="Ja",1,0),"") -> 1 | P13: =IF(AND(Programme_Grunddaten!$A21="Geprüft",Programme_Grunddaten!X21<>""),IF(Programme_Grunddaten!X21="Ja",1,0),"") -> 1 | Q13: =IF(AND(Programme_Grunddaten!$A21="Geprüft",Programme_Grunddaten!Y21<>""),IF(Programme_Grunddaten!Y21="Ja",1,0),"") | R13: =IF(AND(Programme_Grunddaten!$A21="Geprüft",Programme_Grunddaten!Z21<>""),IF(Programme_Grunddaten!Z21="Ja",1,0),"") -> 0 | S13: =IF(AND(Programme_Grunddaten!$A21="Geprüft",Programme_Grunddaten!AA21<>""),IF(Programme_Grunddaten!AA21="monolithisch",1,0),"") -> 0 | T13: =IF(AND(Programme_Grunddaten!$A21="Geprüft",Programme_Grunddaten!AB21<>""),IF(Programme_Grunddaten!AB21="Ja",1,0),"") -> 1 | U13: =IF(AND(Programme_Grunddaten!$A21="Geprüft",Programme_Grunddaten!AC21<>""),IF(Programme_Grunddaten!AC21="Ja",1,0),"") -> 1 | V13: =IF(AND(Programme_Grunddaten!$A21="Geprüft",Programme_Grunddaten!AD21<>""),IF(Programme_Grunddaten!AD21="Ja",1,0),"") | W13: =IF(AND(Programme_Grunddaten!$A21="Geprüft",Programme_Grunddaten!AE21<>""),IF(Programme_Grunddaten!AE21="Ja",1,0),"") | X13: =IF(AND(Programme_Grunddaten!$A21="Geprüft",Programme_Grunddaten!AF21<>""),IF(Programme_Grunddaten!AF21="Ja",1,0),"") -> 1 | Y13: =IF(AND(Programme_Grunddaten!$A21="Geprüft",Programme_Grunddaten!AG21<>""),IF(Programme_Grunddaten!AG21="Ja",1,0),"") | Z13: =IF(AND(Programme_Grunddaten!$A21="Geprüft",Programme_Grunddaten!AH21<>""),IF(Programme_Grunddaten!AH21="Ja",1,0),"") | AA13: =IF(AND(Programme_Grunddaten!$A21="Geprüft",Programme_Grunddaten!AI21<>""),IF(Programme_Grunddaten!AI21="Ja",1,0),"") -> 1 | AB13: =IF(AND(Programme_Grunddaten!$A21="Geprüft",Programme_Grunddaten!AJ21<>""),IF(Programme_Grunddaten!AJ21="individuell programmierbar",1,0),"") | AC13: =IF(AND(Programme_Grunddaten!$A21="Geprüft",Programme_Grunddaten!AK21<>""),IF(Programme_Grunddaten!AK21="Deutsch",0,IF(Programme_Grunddaten!AK21="Deutsch und Englisch",1,2)),"") -> 1 | AD13: =IF(AND(Programme_Grunddaten!$A21="Geprüft",Programme_Grunddaten!AL21<>""),IF(Programme_Grunddaten!AL21="Ja",1,0),"") -> 1 | AE13: =IF(AND(Programme_Grunddaten!$A21="Geprüft",Programme_Grunddaten!AM21<>""),IF(Programme_Grunddaten!AM21="Ja",1,0),"") -> 0 | AF13: =IF(AND(Programme_Grunddaten!$A21="Geprüft",Programme_Grunddaten!AN21<>""),IF(Programme_Grunddaten!AN21="Ja",1,0),"") | AG13: =IF(AND(Programme_Grunddaten!$A21="Geprüft",Programme_Grunddaten!AO21<>""),IF(Programme_Grunddaten!AO21="Ja",1,0),"") -> 0 | AH13: =IF(AND(Programme_Grunddaten!$A21="Geprüft",Programme_Grunddaten!AP21<>""),IF(Programme_Grunddaten!AP21="Ja",1,0),"") | AI13: =IF(AND(Programme_Grunddaten!$A21="Geprüft",Programme_Grunddaten!AQ21<>""),IF(Programme_Grunddaten!AQ21="Ja",1,0),"") -> 1 | AJ13: =IF(AND(Programme_Grunddaten!$A21="Geprüft",Programme_Grunddaten!AR21<>""),IF(Programme_Grunddaten!AR21="Ja",1,0),"") -> 1 | AK13: =IF(AND(Programme_Grunddaten!$A21="Geprüft",Programme_Grunddaten!AS21<>""),IF(Programme_Grunddaten!AS21="Ja",1,0),"") -> 1 | ... AN13: =IF(AND(Programme_Grunddaten!$A21="Geprüft",Programme_Grunddaten!AV21<>""),IF(Programme_Grunddaten!AV21="Ja",1,0),"")
... A122: =IF(AND(Programme_Grunddaten!A130="Geprüft",Programme_Grunddaten!B130<>""),Programme_Grunddaten!B130,"") | B122: =IF(AND(Programme_Grunddaten!$A130="Geprüft",Programme_Grunddaten!I130<>""),IF(Programme_Grunddaten!I130="Ja",1,0),"") | C122: =IF(AND(Programme_Grunddaten!$A130="Geprüft",Programme_Grunddaten!J130<>""),IF(Programme_Grunddaten!J130="Ja",1,0),"") | D122: =IF(AND(Programme_Grunddaten!$A130="Geprüft",Programme_Grunddaten!K130<>""),IF(Programme_Grunddaten!K130="Ja",1,0),"") | E122: =IF(AND(Programme_Grunddaten!$A130="Geprüft",Programme_Grunddaten!L130<>""),IF(Programme_Grunddaten!L130="Abo / befristete Lizenz",1,0),"") | F122: =IF(AND(Programme_Grunddaten!$A130="Geprüft",Programme_Grunddaten!M130<>""),IF(Programme_Grunddaten!M130="Ja",1,0),"") | G122: =IF(AND(Programme_Grunddaten!$A130="Geprüft",Programme_Grunddaten!N130<>""),IF(Programme_Grunddaten!N130="Ja",1,0),"") | H122: =IF(AND(Programme_Grunddaten!$A130="Geprüft",Programme_Grunddaten!O130<>""),IF(Programme_Grunddaten!O130="Deutschland",0,IF(Programme_Grunddaten!O130="EU",1,2)),"") | I122: =IF(AND(Programme_Grunddaten!$A130="Geprüft",Programme_Grunddaten!P130<>""),IF(Programme_Grunddaten!P130="Ja",1,0),"") | J122: =IF(AND(Programme_Grunddaten!$A130="Geprüft",Programme_Grunddaten!Q130<>""),IF(Programme_Grunddaten!Q130="geschlossenes System",1,0),"") | K122: =IF(AND(Programme_Grunddaten!$A130="Geprüft",Programme_Grunddaten!R130<>""),IF(Programme_Grunddaten!R130="Ja",1,0),"") | L122: =IF(AND(Programme_Grunddaten!$A130="Geprüft",Programme_Grunddaten!T130<>""),IF(Programme_Grunddaten!T130="Ja",1,0),"") | M122: =IF(AND(Programme_Grunddaten!$A130="Geprüft",Programme_Grunddaten!U130<>""),IF(Programme_Grunddaten!U130="Ja",1,0),"") | N122: =IF(AND(Programme_Grunddaten!$A130="Geprüft",Programme_Grunddaten!V130<>""),IF(Programme_Grunddaten!V130="Ja",1,0),"") | O122: =IF(AND(Programme_Grunddaten!$A130="Geprüft",Programme_Grunddaten!W130<>""),IF(Programme_Grunddaten!W130="Ja",1,0),"") | P122: =IF(AND(Programme_Grunddaten!$A130="Geprüft",Programme_Grunddaten!X130<>""),IF(Programme_Grunddaten!X130="Ja",1,0),"") | Q122: =IF(AND(Programme_Grunddaten!$A130="Geprüft",Programme_Grunddaten!Y130<>""),IF(Programme_Grunddaten!Y130="Ja",1,0),"") | R122: =IF(AND(Programme_Grunddaten!$A130="Geprüft",Programme_Grunddaten!Z130<>""),IF(Programme_Grunddaten!Z130="Ja",1,0),"") | S122: =IF(AND(Programme_Grunddaten!$A130="Geprüft",Programme_Grunddaten!AA130<>""),IF(Programme_Grunddaten!AA130="monolithisch",1,0),"") | T122: =IF(AND(Programme_Grunddaten!$A130="Geprüft",Programme_Grunddaten!AB130<>""),IF(Programme_Grunddaten!AB130="Ja",1,0),"") | U122: =IF(AND(Programme_Grunddaten!$A130="Geprüft",Programme_Grunddaten!AC130<>""),IF(Programme_Grunddaten!AC130="Ja",1,0),"") | V122: =IF(AND(Programme_Grunddaten!$A130="Geprüft",Programme_Grunddaten!AD130<>""),IF(Programme_Grunddaten!AD130="Ja",1,0),"") | W122: =IF(AND(Programme_Grunddaten!$A130="Geprüft",Programme_Grunddaten!AE130<>""),IF(Programme_Grunddaten!AE130="Ja",1,0),"") | X122: =IF(AND(Programme_Grunddaten!$A130="Geprüft",Programme_Grunddaten!AF130<>""),IF(Programme_Grunddaten!AF130="Ja",1,0),"") | Y122: =IF(AND(Programme_Grunddaten!$A130="Geprüft",Programme_Grunddaten!AG130<>""),IF(Programme_Grunddaten!AG130="Ja",1,0),"") | Z122: =IF(AND(Programme_Grunddaten!$A130="Geprüft",Programme_Grunddaten!AH130<>""),IF(Programme_Grunddaten!AH130="Ja",1,0),"") | AA122: =IF(AND(Programme_Grunddaten!$A130="Geprüft",Programme_Grunddaten!AI130<>""),IF(Programme_Grunddaten!AI130="Ja",1,0),"") | AB122: =IF(AND(Programme_Grunddaten!$A130="Geprüft",Programme_Grunddaten!AJ130<>""),IF(Programme_Grunddaten!AJ130="individuell programmierbar",1,0),"") | AC122: =IF(AND(Programme_Grunddaten!$A130="Geprüft",Programme_Grunddaten!AK130<>""),IF(Programme_Grunddaten!AK130="Deutsch",0,IF(Programme_Grunddaten!AK130="Deutsch und Englisch",1,2)),"") | AD122: =IF(AND(Programme_Grunddaten!$A130="Geprüft",Programme_Grunddaten!AL130<>""),IF(Programme_Grunddaten!AL130="Ja",1,0),"") | AE122: =IF(AND(Programme_Grunddaten!$A130="Geprüft",Programme_Grunddaten!AM130<>""),IF(Programme_Grunddaten!AM130="Ja",1,0),"") | AF122: =IF(AND(Programme_Grunddaten!$A130="Geprüft",Programme_Grunddaten!AN130<>""),IF(Programme_Grunddaten!AN130="Ja",1,0),"") | AG122: =IF(AND(Programme_Grunddaten!$A130="Geprüft",Programme_Grunddaten!AO130<>""),IF(Programme_Grunddaten!AO130="Ja",1,0),"") | AH122: =IF(AND(Programme_Grunddaten!$A130="Geprüft",Programme_Grunddaten!AP130<>""),IF(Programme_Grunddaten!AP130="Ja",1,0),"") | AI122: =IF(AND(Programme_Grunddaten!$A130="Geprüft",Programme_Grunddaten!AQ130<>""),IF(Programme_Grunddaten!AQ130="Ja",1,0),"") | AJ122: =IF(AND(Programme_Grunddaten!$A130="Geprüft",Programme_Grunddaten!AR130<>""),IF(Programme_Grunddaten!AR130="Ja",1,0),"") | AK122: =IF(AND(Programme_Grunddaten!$A130="Geprüft",Programme_Grunddaten!AS130<>""),IF(Programme_Grunddaten!AS130="Ja",1,0),"") | ... AN122: =IF(AND(Programme_Grunddaten!$A130="Geprüft",Programme_Grunddaten!AV130<>""),IF(Programme_Grunddaten!AV130="Ja",1,0),"")
A123: =IF(AND(Programme_Grunddaten!#REF!="Geprüft",Programme_Grunddaten!#REF!<>""),Programme_Grunddaten!#REF!,"") -> #REF! | B123: =IF(AND(Programme_Grunddaten!#REF!="Geprüft",Programme_Grunddaten!#REF!<>""),IF(Programme_Grunddaten!#REF!="Ja",1,0),"") -> #REF! | C123: =IF(AND(Programme_Grunddaten!#REF!="Geprüft",Programme_Grunddaten!#REF!<>""),IF(Programme_Grunddaten!#REF!="Ja",1,0),"") -> #REF! | D123: =IF(AND(Programme_Grunddaten!#REF!="Geprüft",Programme_Grunddaten!#REF!<>""),IF(Programme_Grunddaten!#REF!="Ja",1,0),"") -> #REF! | E123: =IF(AND(Programme_Grunddaten!#REF!="Geprüft",Programme_Grunddaten!#REF!<>""),IF(Programme_Grunddaten!#REF!="Abo / befristete Lizenz",1,0),"") -> #REF! | F123: =IF(AND(Programme_Grunddaten!#REF!="Geprüft",Programme_Grunddaten!#REF!<>""),IF(Programme_Grunddaten!#REF!="Ja",1,0),"") -> #REF! | G123: =IF(AND(Programme_Grunddaten!#REF!="Geprüft",Programme_Grunddaten!#REF!<>""),IF(Programme_Grunddaten!#REF!="Ja",1,0),"") -> #REF! | H123: =IF(AND(Programme_Grunddaten!#REF!="Geprüft",Programme_Grunddaten!#REF!<>""),IF(Programme_Grunddaten!#REF!="Deutschland",0,IF(Programme_Grunddaten!#REF!="EU",1,2)),"") -> #REF! | I123: =IF(AND(Programme_Grunddaten!#REF!="Geprüft",Programme_Grunddaten!#REF!<>""),IF(Programme_Grunddaten!#REF!="Ja",1,0),"") -> #REF! | J123: =IF(AND(Programme_Grunddaten!#REF!="Geprüft",Programme_Grunddaten!#REF!<>""),IF(Programme_Grunddaten!#REF!="geschlossenes System",1,0),"") -> #REF! | K123: =IF(AND(Programme_Grunddaten!#REF!="Geprüft",Programme_Grunddaten!#REF!<>""),IF(Programme_Grunddaten!#REF!="Ja",1,0),"") -> #REF! | L123: =IF(AND(Programme_Grunddaten!#REF!="Geprüft",Programme_Grunddaten!#REF!<>""),IF(Programme_Grunddaten!#REF!="Ja",1,0),"") -> #REF! | M123: =IF(AND(Programme_Grunddaten!#REF!="Geprüft",Programme_Grunddaten!#REF!<>""),IF(Programme_Grunddaten!#REF!="Ja",1,0),"") -> #REF! | N123: =IF(AND(Programme_Grunddaten!#REF!="Geprüft",Programme_Grunddaten!#REF!<>""),IF(Programme_Grunddaten!#REF!="Ja",1,0),"") -> #REF! | O123: =IF(AND(Programme_Grunddaten!#REF!="Geprüft",Programme_Grunddaten!#REF!<>""),IF(Programme_Grunddaten!#REF!="Ja",1,0),"") -> #REF! | P123: =IF(AND(Programme_Grunddaten!#REF!="Geprüft",Programme_Grunddaten!#REF!<>""),IF(Programme_Grunddaten!#REF!="Ja",1,0),"") -> #REF! | Q123: =IF(AND(Programme_Grunddaten!#REF!="Geprüft",Programme_Grunddaten!#REF!<>""),IF(Programme_Grunddaten!#REF!="Ja",1,0),"") -> #REF! | R123: =IF(AND(Programme_Grunddaten!#REF!="Geprüft",Programme_Grunddaten!#REF!<>""),IF(Programme_Grunddaten!#REF!="Ja",1,0),"") -> #REF! | S123: =IF(AND(Programme_Grunddaten!#REF!="Geprüft",Programme_Grunddaten!#REF!<>""),IF(Programme_Grunddaten!#REF!="monolithisch",1,0),"") -> #REF! | T123: =IF(AND(Programme_Grunddaten!#REF!="Geprüft",Programme_Grunddaten!#REF!<>""),IF(Programme_Grunddaten!#REF!="Ja",1,0),"") -> #REF! | U123: =IF(AND(Programme_Grunddaten!#REF!="Geprüft",Programme_Grunddaten!#REF!<>""),IF(Programme_Grunddaten!#REF!="Ja",1,0),"") -> #REF! | V123: =IF(AND(Programme_Grunddaten!#REF!="Geprüft",Programme_Grunddaten!#REF!<>""),IF(Programme_Grunddaten!#REF!="Ja",1,0),"") -> #REF! | W123: =IF(AND(Programme_Grunddaten!#REF!="Geprüft",Programme_Grunddaten!#REF!<>""),IF(Programme_Grunddaten!#REF!="Ja",1,0),"") -> #REF! | X123: =IF(AND(Programme_Grunddaten!#REF!="Geprüft",Programme_Grunddaten!#REF!<>""),IF(Programme_Grunddaten!#REF!="Ja",1,0),"") -> #REF! | Y123: =IF(AND(Programme_Grunddaten!#REF!="Geprüft",Programme_Grunddaten!#REF!<>""),IF(Programme_Grunddaten!#REF!="Ja",1,0),"") -> #REF! | Z123: =IF(AND(Programme_Grunddaten!#REF!="Geprüft",Programme_Grunddaten!#REF!<>""),IF(Programme_Grunddaten!#REF!="Ja",1,0),"") -> #REF! | AA123: =IF(AND(Programme_Grunddaten!#REF!="Geprüft",Programme_Grunddaten!#REF!<>""),IF(Programme_Grunddaten!#REF!="Ja",1,0),"") -> #REF! | AB123: =IF(AND(Programme_Grunddaten!#REF!="Geprüft",Programme_Grunddaten!#REF!<>""),IF(Programme_Grunddaten!#REF!="individuell programmierbar",1,0),"") -> #REF! | AC123: =IF(AND(Programme_Grunddaten!#REF!="Geprüft",Programme_Grunddaten!#REF!<>""),IF(Programme_Grunddaten!#REF!="Deutsch",0,IF(Programme_Grunddaten!#REF!="Deutsch und Englisch",1,2)),"") -> #REF! | AD123: =IF(AND(Programme_Grunddaten!#REF!="Geprüft",Programme_Grunddaten!#REF!<>""),IF(Programme_Grunddaten!#REF!="Ja",1,0),"") -> #REF! | AE123: =IF(AND(Programme_Grunddaten!#REF!="Geprüft",Programme_Grunddaten!#REF!<>""),IF(Programme_Grunddaten!#REF!="Ja",1,0),"") -> #REF! | AF123: =IF(AND(Programme_Grunddaten!#REF!="Geprüft",Programme_Grunddaten!#REF!<>""),IF(Programme_Grunddaten!#REF!="Ja",1,0),"") -> #REF! | AG123: =IF(AND(Programme_Grunddaten!#REF!="Geprüft",Programme_Grunddaten!#REF!<>""),IF(Programme_Grunddaten!#REF!="Ja",1,0),"") -> #REF! | AH123: =IF(AND(Programme_Grunddaten!#REF!="Geprüft",Programme_Grunddaten!#REF!<>""),IF(Programme_Grunddaten!#REF!="Ja",1,0),"") -> #REF! | AI123: =IF(AND(Programme_Grunddaten!#REF!="Geprüft",Programme_Grunddaten!#REF!<>""),IF(Programme_Grunddaten!#REF!="Ja",1,0),"") -> #REF! | AJ123: =IF(AND(Programme_Grunddaten!#REF!="Geprüft",Programme_Grunddaten!#REF!<>""),IF(Programme_Grunddaten!#REF!="Ja",1,0),"") -> #REF! | AK123: =IF(AND(Programme_Grunddaten!#REF!="Geprüft",Programme_Grunddaten!#REF!<>""),IF(Programme_Grunddaten!#REF!="Ja",1,0),"") -> #REF! | ... AN123: =IF(AND(Programme_Grunddaten!#REF!="Geprüft",Programme_Grunddaten!#REF!<>""),IF(Programme_Grunddaten!#REF!="Ja",1,0),"") -> #REF!
A124: =IF(AND(Programme_Grunddaten!#REF!="Geprüft",Programme_Grunddaten!#REF!<>""),Programme_Grunddaten!#REF!,"") -> #REF! | B124: =IF(AND(Programme_Grunddaten!#REF!="Geprüft",Programme_Grunddaten!#REF!<>""),IF(Programme_Grunddaten!#REF!="Ja",1,0),"") -> #REF! | C124: =IF(AND(Programme_Grunddaten!#REF!="Geprüft",Programme_Grunddaten!#REF!<>""),IF(Programme_Grunddaten!#REF!="Ja",1,0),"") -> #REF! | D124: =IF(AND(Programme_Grunddaten!#REF!="Geprüft",Programme_Grunddaten!#REF!<>""),IF(Programme_Grunddaten!#REF!="Ja",1,0),"") -> #REF! | E124: =IF(AND(Programme_Grunddaten!#REF!="Geprüft",Programme_Grunddaten!#REF!<>""),IF(Programme_Grunddaten!#REF!="Abo / befristete Lizenz",1,0),"") -> #REF! | F124: =IF(AND(Programme_Grunddaten!#REF!="Geprüft",Programme_Grunddaten!#REF!<>""),IF(Programme_Grunddaten!#REF!="Ja",1,0),"") -> #REF! | G124: =IF(AND(Programme_Grunddaten!#REF!="Geprüft",Programme_Grunddaten!#REF!<>""),IF(Programme_Grunddaten!#REF!="Ja",1,0),"") -> #REF! | H124: =IF(AND(Programme_Grunddaten!#REF!="Geprüft",Programme_Grunddaten!#REF!<>""),IF(Programme_Grunddaten!#REF!="Deutschland",0,IF(Programme_Grunddaten!#REF!="EU",1,2)),"") -> #REF! | I124: =IF(AND(Programme_Grunddaten!#REF!="Geprüft",Programme_Grunddaten!#REF!<>""),IF(Programme_Grunddaten!#REF!="Ja",1,0),"") -> #REF! | J124: =IF(AND(Programme_Grunddaten!#REF!="Geprüft",Programme_Grunddaten!#REF!<>""),IF(Programme_Grunddaten!#REF!="geschlossenes System",1,0),"") -> #REF! | K124: =IF(AND(Programme_Grunddaten!#REF!="Geprüft",Programme_Grunddaten!#REF!<>""),IF(Programme_Grunddaten!#REF!="Ja",1,0),"") -> #REF! | L124: =IF(AND(Programme_Grunddaten!#REF!="Geprüft",Programme_Grunddaten!#REF!<>""),IF(Programme_Grunddaten!#REF!="Ja",1,0),"") -> #REF! | M124: =IF(AND(Programme_Grunddaten!#REF!="Geprüft",Programme_Grunddaten!#REF!<>""),IF(Programme_Grunddaten!#REF!="Ja",1,0),"") -> #REF! | N124: =IF(AND(Programme_Grunddaten!#REF!="Geprüft",Programme_Grunddaten!#REF!<>""),IF(Programme_Grunddaten!#REF!="Ja",1,0),"") -> #REF! | O124: =IF(AND(Programme_Grunddaten!#REF!="Geprüft",Programme_Grunddaten!#REF!<>""),IF(Programme_Grunddaten!#REF!="Ja",1,0),"") -> #REF! | P124: =IF(AND(Programme_Grunddaten!#REF!="Geprüft",Programme_Grunddaten!#REF!<>""),IF(Programme_Grunddaten!#REF!="Ja",1,0),"") -> #REF! | Q124: =IF(AND(Programme_Grunddaten!#REF!="Geprüft",Programme_Grunddaten!#REF!<>""),IF(Programme_Grunddaten!#REF!="Ja",1,0),"") -> #REF! | R124: =IF(AND(Programme_Grunddaten!#REF!="Geprüft",Programme_Grunddaten!#REF!<>""),IF(Programme_Grunddaten!#REF!="Ja",1,0),"") -> #REF! | S124: =IF(AND(Programme_Grunddaten!#REF!="Geprüft",Programme_Grunddaten!#REF!<>""),IF(Programme_Grunddaten!#REF!="monolithisch",1,0),"") -> #REF! | T124: =IF(AND(Programme_Grunddaten!#REF!="Geprüft",Programme_Grunddaten!#REF!<>""),IF(Programme_Grunddaten!#REF!="Ja",1,0),"") -> #REF! | U124: =IF(AND(Programme_Grunddaten!#REF!="Geprüft",Programme_Grunddaten!#REF!<>""),IF(Programme_Grunddaten!#REF!="Ja",1,0),"") -> #REF! | V124: =IF(AND(Programme_Grunddaten!#REF!="Geprüft",Programme_Grunddaten!#REF!<>""),IF(Programme_Grunddaten!#REF!="Ja",1,0),"") -> #REF! | W124: =IF(AND(Programme_Grunddaten!#REF!="Geprüft",Programme_Grunddaten!#REF!<>""),IF(Programme_Grunddaten!#REF!="Ja",1,0),"") -> #REF! | X124: =IF(AND(Programme_Grunddaten!#REF!="Geprüft",Programme_Grunddaten!#REF!<>""),IF(Programme_Grunddaten!#REF!="Ja",1,0),"") -> #REF! | Y124: =IF(AND(Programme_Grunddaten!#REF!="Geprüft",Programme_Grunddaten!#REF!<>""),IF(Programme_Grunddaten!#REF!="Ja",1,0),"") -> #REF! | Z124: =IF(AND(Programme_Grunddaten!#REF!="Geprüft",Programme_Grunddaten!#REF!<>""),IF(Programme_Grunddaten!#REF!="Ja",1,0),"") -> #REF! | AA124: =IF(AND(Programme_Grunddaten!#REF!="Geprüft",Programme_Grunddaten!#REF!<>""),IF(Programme_Grunddaten!#REF!="Ja",1,0),"") -> #REF! | AB124: =IF(AND(Programme_Grunddaten!#REF!="Geprüft",Programme_Grunddaten!#REF!<>""),IF(Programme_Grunddaten!#REF!="individuell programmierbar",1,0),"") -> #REF! | AC124: =IF(AND(Programme_Grunddaten!#REF!="Geprüft",Programme_Grunddaten!#REF!<>""),IF(Programme_Grunddaten!#REF!="Deutsch",0,IF(Programme_Grunddaten!#REF!="Deutsch und Englisch",1,2)),"") -> #REF! | AD124: =IF(AND(Programme_Grunddaten!#REF!="Geprüft",Programme_Grunddaten!#REF!<>""),IF(Programme_Grunddaten!#REF!="Ja",1,0),"") -> #REF! | AE124: =IF(AND(Programme_Grunddaten!#REF!="Geprüft",Programme_Grunddaten!#REF!<>""),IF(Programme_Grunddaten!#REF!="Ja",1,0),"") -> #REF! | AF124: =IF(AND(Programme_Grunddaten!#REF!="Geprüft",Programme_Grunddaten!#REF!<>""),IF(Programme_Grunddaten!#REF!="Ja",1,0),"") -> #REF! | AG124: =IF(AND(Programme_Grunddaten!#REF!="Geprüft",Programme_Grunddaten!#REF!<>""),IF(Programme_Grunddaten!#REF!="Ja",1,0),"") -> #REF! | AH124: =IF(AND(Programme_Grunddaten!#REF!="Geprüft",Programme_Grunddaten!#REF!<>""),IF(Programme_Grunddaten!#REF!="Ja",1,0),"") -> #REF! | AI124: =IF(AND(Programme_Grunddaten!#REF!="Geprüft",Programme_Grunddaten!#REF!<>""),IF(Programme_Grunddaten!#REF!="Ja",1,0),"") -> #REF! | AJ124: =IF(AND(Programme_Grunddaten!#REF!="Geprüft",Programme_Grunddaten!#REF!<>""),IF(Programme_Grunddaten!#REF!="Ja",1,0),"") -> #REF! | AK124: =IF(AND(Programme_Grunddaten!#REF!="Geprüft",Programme_Grunddaten!#REF!<>""),IF(Programme_Grunddaten!#REF!="Ja",1,0),"") -> #REF! | ... AN124: =IF(AND(Programme_Grunddaten!#REF!="Geprüft",Programme_Grunddaten!#REF!<>""),IF(Programme_Grunddaten!#REF!="Ja",1,0),"") -> #REF!
A125: =IF(AND(Programme_Grunddaten!#REF!="Geprüft",Programme_Grunddaten!#REF!<>""),Programme_Grunddaten!#REF!,"") -> #REF! | B125: =IF(AND(Programme_Grunddaten!#REF!="Geprüft",Programme_Grunddaten!#REF!<>""),IF(Programme_Grunddaten!#REF!="Ja",1,0),"") -> #REF! | C125: =IF(AND(Programme_Grunddaten!#REF!="Geprüft",Programme_Grunddaten!#REF!<>""),IF(Programme_Grunddaten!#REF!="Ja",1,0),"") -> #REF! | D125: =IF(AND(Programme_Grunddaten!#REF!="Geprüft",Programme_Grunddaten!#REF!<>""),IF(Programme_Grunddaten!#REF!="Ja",1,0),"") -> #REF! | E125: =IF(AND(Programme_Grunddaten!#REF!="Geprüft",Programme_Grunddaten!#REF!<>""),IF(Programme_Grunddaten!#REF!="Abo / befristete Lizenz",1,0),"") -> #REF! | F125: =IF(AND(Programme_Grunddaten!#REF!="Geprüft",Programme_Grunddaten!#REF!<>""),IF(Programme_Grunddaten!#REF!="Ja",1,0),"") -> #REF! | G125: =IF(AND(Programme_Grunddaten!#REF!="Geprüft",Programme_Grunddaten!#REF!<>""),IF(Programme_Grunddaten!#REF!="Ja",1,0),"") -> #REF! | H125: =IF(AND(Programme_Grunddaten!#REF!="Geprüft",Programme_Grunddaten!#REF!<>""),IF(Programme_Grunddaten!#REF!="Deutschland",0,IF(Programme_Grunddaten!#REF!="EU",1,2)),"") -> #REF! | I125: =IF(AND(Programme_Grunddaten!#REF!="Geprüft",Programme_Grunddaten!#REF!<>""),IF(Programme_Grunddaten!#REF!="Ja",1,0),"") -> #REF! | J125: =IF(AND(Programme_Grunddaten!#REF!="Geprüft",Programme_Grunddaten!#REF!<>""),IF(Programme_Grunddaten!#REF!="geschlossenes System",1,0),"") -> #REF! | K125: =IF(AND(Programme_Grunddaten!#REF!="Geprüft",Programme_Grunddaten!#REF!<>""),IF(Programme_Grunddaten!#REF!="Ja",1,0),"") -> #REF! | L125: =IF(AND(Programme_Grunddaten!#REF!="Geprüft",Programme_Grunddaten!#REF!<>""),IF(Programme_Grunddaten!#REF!="Ja",1,0),"") -> #REF! | M125: =IF(AND(Programme_Grunddaten!#REF!="Geprüft",Programme_Grunddaten!#REF!<>""),IF(Programme_Grunddaten!#REF!="Ja",1,0),"") -> #REF! | N125: =IF(AND(Programme_Grunddaten!#REF!="Geprüft",Programme_Grunddaten!#REF!<>""),IF(Programme_Grunddaten!#REF!="Ja",1,0),"") -> #REF! | O125: =IF(AND(Programme_Grunddaten!#REF!="Geprüft",Programme_Grunddaten!#REF!<>""),IF(Programme_Grunddaten!#REF!="Ja",1,0),"") -> #REF! | P125: =IF(AND(Programme_Grunddaten!#REF!="Geprüft",Programme_Grunddaten!#REF!<>""),IF(Programme_Grunddaten!#REF!="Ja",1,0),"") -> #REF! | Q125: =IF(AND(Programme_Grunddaten!#REF!="Geprüft",Programme_Grunddaten!#REF!<>""),IF(Programme_Grunddaten!#REF!="Ja",1,0),"") -> #REF! | R125: =IF(AND(Programme_Grunddaten!#REF!="Geprüft",Programme_Grunddaten!#REF!<>""),IF(Programme_Grunddaten!#REF!="Ja",1,0),"") -> #REF! | S125: =IF(AND(Programme_Grunddaten!#REF!="Geprüft",Programme_Grunddaten!#REF!<>""),IF(Programme_Grunddaten!#REF!="monolithisch",1,0),"") -> #REF! | T125: =IF(AND(Programme_Grunddaten!#REF!="Geprüft",Programme_Grunddaten!#REF!<>""),IF(Programme_Grunddaten!#REF!="Ja",1,0),"") -> #REF! | U125: =IF(AND(Programme_Grunddaten!#REF!="Geprüft",Programme_Grunddaten!#REF!<>""),IF(Programme_Grunddaten!#REF!="Ja",1,0),"") -> #REF! | V125: =IF(AND(Programme_Grunddaten!#REF!="Geprüft",Programme_Grunddaten!#REF!<>""),IF(Programme_Grunddaten!#REF!="Ja",1,0),"") -> #REF! | W125: =IF(AND(Programme_Grunddaten!#REF!="Geprüft",Programme_Grunddaten!#REF!<>""),IF(Programme_Grunddaten!#REF!="Ja",1,0),"") -> #REF! | X125: =IF(AND(Programme_Grunddaten!#REF!="Geprüft",Programme_Grunddaten!#REF!<>""),IF(Programme_Grunddaten!#REF!="Ja",1,0),"") -> #REF! | Y125: =IF(AND(Programme_Grunddaten!#REF!="Geprüft",Programme_Grunddaten!#REF!<>""),IF(Programme_Grunddaten!#REF!="Ja",1,0),"") -> #REF! | Z125: =IF(AND(Programme_Grunddaten!#REF!="Geprüft",Programme_Grunddaten!#REF!<>""),IF(Programme_Grunddaten!#REF!="Ja",1,0),"") -> #REF! | AA125: =IF(AND(Programme_Grunddaten!#REF!="Geprüft",Programme_Grunddaten!#REF!<>""),IF(Programme_Grunddaten!#REF!="Ja",1,0),"") -> #REF! | AB125: =IF(AND(Programme_Grunddaten!#REF!="Geprüft",Programme_Grunddaten!#REF!<>""),IF(Programme_Grunddaten!#REF!="individuell programmierbar",1,0),"") -> #REF! | AC125: =IF(AND(Programme_Grunddaten!#REF!="Geprüft",Programme_Grunddaten!#REF!<>""),IF(Programme_Grunddaten!#REF!="Deutsch",0,IF(Programme_Grunddaten!#REF!="Deutsch und Englisch",1,2)),"") -> #REF! | AD125: =IF(AND(Programme_Grunddaten!#REF!="Geprüft",Programme_Grunddaten!#REF!<>""),IF(Programme_Grunddaten!#REF!="Ja",1,0),"") -> #REF! | AE125: =IF(AND(Programme_Grunddaten!#REF!="Geprüft",Programme_Grunddaten!#REF!<>""),IF(Programme_Grunddaten!#REF!="Ja",1,0),"") -> #REF! | AF125: =IF(AND(Programme_Grunddaten!#REF!="Geprüft",Programme_Grunddaten!#REF!<>""),IF(Programme_Grunddaten!#REF!="Ja",1,0),"") -> #REF! | AG125: =IF(AND(Programme_Grunddaten!#REF!="Geprüft",Programme_Grunddaten!#REF!<>""),IF(Programme_Grunddaten!#REF!="Ja",1,0),"") -> #REF! | AH125: =IF(AND(Programme_Grunddaten!#REF!="Geprüft",Programme_Grunddaten!#REF!<>""),IF(Programme_Grunddaten!#REF!="Ja",1,0),"") -> #REF! | AI125: =IF(AND(Programme_Grunddaten!#REF!="Geprüft",Programme_Grunddaten!#REF!<>""),IF(Programme_Grunddaten!#REF!="Ja",1,0),"") -> #REF! | AJ125: =IF(AND(Programme_Grunddaten!#REF!="Geprüft",Programme_Grunddaten!#REF!<>""),IF(Programme_Grunddaten!#REF!="Ja",1,0),"") -> #REF! | AK125: =IF(AND(Programme_Grunddaten!#REF!="Geprüft",Programme_Grunddaten!#REF!<>""),IF(Programme_Grunddaten!#REF!="Ja",1,0),"") -> #REF! | ... AN125: =IF(AND(Programme_Grunddaten!#REF!="Geprüft",Programme_Grunddaten!#REF!<>""),IF(Programme_Grunddaten!#REF!="Ja",1,0),"") -> #REF!
A126: =IF(AND(Programme_Grunddaten!A131="Geprüft",Programme_Grunddaten!B131<>""),Programme_Grunddaten!B131,"") | B126: =IF(AND(Programme_Grunddaten!$A131="Geprüft",Programme_Grunddaten!I131<>""),IF(Programme_Grunddaten!I131="Ja",1,0),"") | C126: =IF(AND(Programme_Grunddaten!$A131="Geprüft",Programme_Grunddaten!J131<>""),IF(Programme_Grunddaten!J131="Ja",1,0),"") | D126: =IF(AND(Programme_Grunddaten!$A131="Geprüft",Programme_Grunddaten!K131<>""),IF(Programme_Grunddaten!K131="Ja",1,0),"") | E126: =IF(AND(Programme_Grunddaten!$A131="Geprüft",Programme_Grunddaten!L131<>""),IF(Programme_Grunddaten!L131="Abo / befristete Lizenz",1,0),"") | F126: =IF(AND(Programme_Grunddaten!$A131="Geprüft",Programme_Grunddaten!M131<>""),IF(Programme_Grunddaten!M131="Ja",1,0),"") | G126: =IF(AND(Programme_Grunddaten!$A131="Geprüft",Programme_Grunddaten!N131<>""),IF(Programme_Grunddaten!N131="Ja",1,0),"") | H126: =IF(AND(Programme_Grunddaten!$A131="Geprüft",Programme_Grunddaten!O131<>""),IF(Programme_Grunddaten!O131="Deutschland",0,IF(Programme_Grunddaten!O131="EU",1,2)),"") | I126: =IF(AND(Programme_Grunddaten!$A131="Geprüft",Programme_Grunddaten!P131<>""),IF(Programme_Grunddaten!P131="Ja",1,0),"") | J126: =IF(AND(Programme_Grunddaten!$A131="Geprüft",Programme_Grunddaten!Q131<>""),IF(Programme_Grunddaten!Q131="geschlossenes System",1,0),"") | K126: =IF(AND(Programme_Grunddaten!$A131="Geprüft",Programme_Grunddaten!R131<>""),IF(Programme_Grunddaten!R131="Ja",1,0),"") | L126: =IF(AND(Programme_Grunddaten!$A131="Geprüft",Programme_Grunddaten!T131<>""),IF(Programme_Grunddaten!T131="Ja",1,0),"") | M126: =IF(AND(Programme_Grunddaten!$A131="Geprüft",Programme_Grunddaten!U131<>""),IF(Programme_Grunddaten!U131="Ja",1,0),"") | N126: =IF(AND(Programme_Grunddaten!$A131="Geprüft",Programme_Grunddaten!V131<>""),IF(Programme_Grunddaten!V131="Ja",1,0),"") | O126: =IF(AND(Programme_Grunddaten!$A131="Geprüft",Programme_Grunddaten!W131<>""),IF(Programme_Grunddaten!W131="Ja",1,0),"") | P126: =IF(AND(Programme_Grunddaten!$A131="Geprüft",Programme_Grunddaten!X131<>""),IF(Programme_Grunddaten!X131="Ja",1,0),"") | Q126: =IF(AND(Programme_Grunddaten!$A131="Geprüft",Programme_Grunddaten!Y131<>""),IF(Programme_Grunddaten!Y131="Ja",1,0),"") | R126: =IF(AND(Programme_Grunddaten!$A131="Geprüft",Programme_Grunddaten!Z131<>""),IF(Programme_Grunddaten!Z131="Ja",1,0),"") | S126: =IF(AND(Programme_Grunddaten!$A131="Geprüft",Programme_Grunddaten!AA131<>""),IF(Programme_Grunddaten!AA131="monolithisch",1,0),"") | T126: =IF(AND(Programme_Grunddaten!$A131="Geprüft",Programme_Grunddaten!AB131<>""),IF(Programme_Grunddaten!AB131="Ja",1,0),"") | U126: =IF(AND(Programme_Grunddaten!$A131="Geprüft",Programme_Grunddaten!AC131<>""),IF(Programme_Grunddaten!AC131="Ja",1,0),"") | V126: =IF(AND(Programme_Grunddaten!$A131="Geprüft",Programme_Grunddaten!AD131<>""),IF(Programme_Grunddaten!AD131="Ja",1,0),"") | W126: =IF(AND(Programme_Grunddaten!$A131="Geprüft",Programme_Grunddaten!AE131<>""),IF(Programme_Grunddaten!AE131="Ja",1,0),"") | X126: =IF(AND(Programme_Grunddaten!$A131="Geprüft",Programme_Grunddaten!AF131<>""),IF(Programme_Grunddaten!AF131="Ja",1,0),"") | Y126: =IF(AND(Programme_Grunddaten!$A131="Geprüft",Programme_Grunddaten!AG131<>""),IF(Programme_Grunddaten!AG131="Ja",1,0),"") | Z126: =IF(AND(Programme_Grunddaten!$A131="Geprüft",Programme_Grunddaten!AH131<>""),IF(Programme_Grunddaten!AH131="Ja",1,0),"") | AA126: =IF(AND(Programme_Grunddaten!$A131="Geprüft",Programme_Grunddaten!AI131<>""),IF(Programme_Grunddaten!AI131="Ja",1,0),"") | AB126: =IF(AND(Programme_Grunddaten!$A131="Geprüft",Programme_Grunddaten!AJ131<>""),IF(Programme_Grunddaten!AJ131="individuell programmierbar",1,0),"") | AC126: =IF(AND(Programme_Grunddaten!$A131="Geprüft",Programme_Grunddaten!AK131<>""),IF(Programme_Grunddaten!AK131="Deutsch",0,IF(Programme_Grunddaten!AK131="Deutsch und Englisch",1,2)),"") | AD126: =IF(AND(Programme_Grunddaten!$A131="Geprüft",Programme_Grunddaten!AL131<>""),IF(Programme_Grunddaten!AL131="Ja",1,0),"") | AE126: =IF(AND(Programme_Grunddaten!$A131="Geprüft",Programme_Grunddaten!AM131<>""),IF(Programme_Grunddaten!AM131="Ja",1,0),"") | AF126: =IF(AND(Programme_Grunddaten!$A131="Geprüft",Programme_Grunddaten!AN131<>""),IF(Programme_Grunddaten!AN131="Ja",1,0),"") | AG126: =IF(AND(Programme_Grunddaten!$A131="Geprüft",Programme_Grunddaten!AO131<>""),IF(Programme_Grunddaten!AO131="Ja",1,0),"") | AH126: =IF(AND(Programme_Grunddaten!$A131="Geprüft",Programme_Grunddaten!AP131<>""),IF(Programme_Grunddaten!AP131="Ja",1,0),"") | AI126: =IF(AND(Programme_Grunddaten!$A131="Geprüft",Programme_Grunddaten!AQ131<>""),IF(Programme_Grunddaten!AQ131="Ja",1,0),"") | AJ126: =IF(AND(Programme_Grunddaten!$A131="Geprüft",Programme_Grunddaten!AR131<>""),IF(Programme_Grunddaten!AR131="Ja",1,0),"") | AK126: =IF(AND(Programme_Grunddaten!$A131="Geprüft",Programme_Grunddaten!AS131<>""),IF(Programme_Grunddaten!AS131="Ja",1,0),"") | ... AN126: =IF(AND(Programme_Grunddaten!$A131="Geprüft",Programme_Grunddaten!AV131<>""),IF(Programme_Grunddaten!AV131="Ja",1,0),"")
A127: =IF(AND(Programme_Grunddaten!A132="Geprüft",Programme_Grunddaten!B132<>""),Programme_Grunddaten!B132,"") | B127: =IF(AND(Programme_Grunddaten!$A132="Geprüft",Programme_Grunddaten!I132<>""),IF(Programme_Grunddaten!I132="Ja",1,0),"") | C127: =IF(AND(Programme_Grunddaten!$A132="Geprüft",Programme_Grunddaten!J132<>""),IF(Programme_Grunddaten!J132="Ja",1,0),"") | D127: =IF(AND(Programme_Grunddaten!$A132="Geprüft",Programme_Grunddaten!K132<>""),IF(Programme_Grunddaten!K132="Ja",1,0),"") | E127: =IF(AND(Programme_Grunddaten!$A132="Geprüft",Programme_Grunddaten!L132<>""),IF(Programme_Grunddaten!L132="Abo / befristete Lizenz",1,0),"") | F127: =IF(AND(Programme_Grunddaten!$A132="Geprüft",Programme_Grunddaten!M132<>""),IF(Programme_Grunddaten!M132="Ja",1,0),"") | G127: =IF(AND(Programme_Grunddaten!$A132="Geprüft",Programme_Grunddaten!N132<>""),IF(Programme_Grunddaten!N132="Ja",1,0),"") | H127: =IF(AND(Programme_Grunddaten!$A132="Geprüft",Programme_Grunddaten!O132<>""),IF(Programme_Grunddaten!O132="Deutschland",0,IF(Programme_Grunddaten!O132="EU",1,2)),"") | I127: =IF(AND(Programme_Grunddaten!$A132="Geprüft",Programme_Grunddaten!P132<>""),IF(Programme_Grunddaten!P132="Ja",1,0),"") | J127: =IF(AND(Programme_Grunddaten!$A132="Geprüft",Programme_Grunddaten!Q132<>""),IF(Programme_Grunddaten!Q132="geschlossenes System",1,0),"") | K127: =IF(AND(Programme_Grunddaten!$A132="Geprüft",Programme_Grunddaten!R132<>""),IF(Programme_Grunddaten!R132="Ja",1,0),"") | L127: =IF(AND(Programme_Grunddaten!$A132="Geprüft",Programme_Grunddaten!T132<>""),IF(Programme_Grunddaten!T132="Ja",1,0),"") | M127: =IF(AND(Programme_Grunddaten!$A132="Geprüft",Programme_Grunddaten!U132<>""),IF(Programme_Grunddaten!U132="Ja",1,0),"") | N127: =IF(AND(Programme_Grunddaten!$A132="Geprüft",Programme_Grunddaten!V132<>""),IF(Programme_Grunddaten!V132="Ja",1,0),"") | O127: =IF(AND(Programme_Grunddaten!$A132="Geprüft",Programme_Grunddaten!W132<>""),IF(Programme_Grunddaten!W132="Ja",1,0),"") | P127: =IF(AND(Programme_Grunddaten!$A132="Geprüft",Programme_Grunddaten!X132<>""),IF(Programme_Grunddaten!X132="Ja",1,0),"") | Q127: =IF(AND(Programme_Grunddaten!$A132="Geprüft",Programme_Grunddaten!Y132<>""),IF(Programme_Grunddaten!Y132="Ja",1,0),"") | R127: =IF(AND(Programme_Grunddaten!$A132="Geprüft",Programme_Grunddaten!Z132<>""),IF(Programme_Grunddaten!Z132="Ja",1,0),"") | S127: =IF(AND(Programme_Grunddaten!$A132="Geprüft",Programme_Grunddaten!AA132<>""),IF(Programme_Grunddaten!AA132="monolithisch",1,0),"") | T127: =IF(AND(Programme_Grunddaten!$A132="Geprüft",Programme_Grunddaten!AB132<>""),IF(Programme_Grunddaten!AB132="Ja",1,0),"") | U127: =IF(AND(Programme_Grunddaten!$A132="Geprüft",Programme_Grunddaten!AC132<>""),IF(Programme_Grunddaten!AC132="Ja",1,0),"") | V127: =IF(AND(Programme_Grunddaten!$A132="Geprüft",Programme_Grunddaten!AD132<>""),IF(Programme_Grunddaten!AD132="Ja",1,0),"") | W127: =IF(AND(Programme_Grunddaten!$A132="Geprüft",Programme_Grunddaten!AE132<>""),IF(Programme_Grunddaten!AE132="Ja",1,0),"") | X127: =IF(AND(Programme_Grunddaten!$A132="Geprüft",Programme_Grunddaten!AF132<>""),IF(Programme_Grunddaten!AF132="Ja",1,0),"") | Y127: =IF(AND(Programme_Grunddaten!$A132="Geprüft",Programme_Grunddaten!AG132<>""),IF(Programme_Grunddaten!AG132="Ja",1,0),"") | Z127: =IF(AND(Programme_Grunddaten!$A132="Geprüft",Programme_Grunddaten!AH132<>""),IF(Programme_Grunddaten!AH132="Ja",1,0),"") | AA127: =IF(AND(Programme_Grunddaten!$A132="Geprüft",Programme_Grunddaten!AI132<>""),IF(Programme_Grunddaten!AI132="Ja",1,0),"") | AB127: =IF(AND(Programme_Grunddaten!$A132="Geprüft",Programme_Grunddaten!AJ132<>""),IF(Programme_Grunddaten!AJ132="individuell programmierbar",1,0),"") | AC127: =IF(AND(Programme_Grunddaten!$A132="Geprüft",Programme_Grunddaten!AK132<>""),IF(Programme_Grunddaten!AK132="Deutsch",0,IF(Programme_Grunddaten!AK132="Deutsch und Englisch",1,2)),"") | AD127: =IF(AND(Programme_Grunddaten!$A132="Geprüft",Programme_Grunddaten!AL132<>""),IF(Programme_Grunddaten!AL132="Ja",1,0),"") | AE127: =IF(AND(Programme_Grunddaten!$A132="Geprüft",Programme_Grunddaten!AM132<>""),IF(Programme_Grunddaten!AM132="Ja",1,0),"") | AF127: =IF(AND(Programme_Grunddaten!$A132="Geprüft",Programme_Grunddaten!AN132<>""),IF(Programme_Grunddaten!AN132="Ja",1,0),"") | AG127: =IF(AND(Programme_Grunddaten!$A132="Geprüft",Programme_Grunddaten!AO132<>""),IF(Programme_Grunddaten!AO132="Ja",1,0),"") | AH127: =IF(AND(Programme_Grunddaten!$A132="Geprüft",Programme_Grunddaten!AP132<>""),IF(Programme_Grunddaten!AP132="Ja",1,0),"") | AI127: =IF(AND(Programme_Grunddaten!$A132="Geprüft",Programme_Grunddaten!AQ132<>""),IF(Programme_Grunddaten!AQ132="Ja",1,0),"") | AJ127: =IF(AND(Programme_Grunddaten!$A132="Geprüft",Programme_Grunddaten!AR132<>""),IF(Programme_Grunddaten!AR132="Ja",1,0),"") | AK127: =IF(AND(Programme_Grunddaten!$A132="Geprüft",Programme_Grunddaten!AS132<>""),IF(Programme_Grunddaten!AS132="Ja",1,0),"") | ... AN127: =IF(AND(Programme_Grunddaten!$A132="Geprüft",Programme_Grunddaten!AV132<>""),IF(Programme_Grunddaten!AV132="Ja",1,0),"")
A128: =IF(AND(Programme_Grunddaten!A133="Geprüft",Programme_Grunddaten!B133<>""),Programme_Grunddaten!B133,"") | B128: =IF(AND(Programme_Grunddaten!$A133="Geprüft",Programme_Grunddaten!I133<>""),IF(Programme_Grunddaten!I133="Ja",1,0),"") | C128: =IF(AND(Programme_Grunddaten!$A133="Geprüft",Programme_Grunddaten!J133<>""),IF(Programme_Grunddaten!J133="Ja",1,0),"") | D128: =IF(AND(Programme_Grunddaten!$A133="Geprüft",Programme_Grunddaten!K133<>""),IF(Programme_Grunddaten!K133="Ja",1,0),"") | E128: =IF(AND(Programme_Grunddaten!$A133="Geprüft",Programme_Grunddaten!L133<>""),IF(Programme_Grunddaten!L133="Abo / befristete Lizenz",1,0),"") | F128: =IF(AND(Programme_Grunddaten!$A133="Geprüft",Programme_Grunddaten!M133<>""),IF(Programme_Grunddaten!M133="Ja",1,0),"") | G128: =IF(AND(Programme_Grunddaten!$A133="Geprüft",Programme_Grunddaten!N133<>""),IF(Programme_Grunddaten!N133="Ja",1,0),"") | H128: =IF(AND(Programme_Grunddaten!$A133="Geprüft",Programme_Grunddaten!O133<>""),IF(Programme_Grunddaten!O133="Deutschland",0,IF(Programme_Grunddaten!O133="EU",1,2)),"") | I128: =IF(AND(Programme_Grunddaten!$A133="Geprüft",Programme_Grunddaten!P133<>""),IF(Programme_Grunddaten!P133="Ja",1,0),"") | J128: =IF(AND(Programme_Grunddaten!$A133="Geprüft",Programme_Grunddaten!Q133<>""),IF(Programme_Grunddaten!Q133="geschlossenes System",1,0),"") | K128: =IF(AND(Programme_Grunddaten!$A133="Geprüft",Programme_Grunddaten!R133<>""),IF(Programme_Grunddaten!R133="Ja",1,0),"") | L128: =IF(AND(Programme_Grunddaten!$A133="Geprüft",Programme_Grunddaten!T133<>""),IF(Programme_Grunddaten!T133="Ja",1,0),"") | M128: =IF(AND(Programme_Grunddaten!$A133="Geprüft",Programme_Grunddaten!U133<>""),IF(Programme_Grunddaten!U133="Ja",1,0),"") | N128: =IF(AND(Programme_Grunddaten!$A133="Geprüft",Programme_Grunddaten!V133<>""),IF(Programme_Grunddaten!V133="Ja",1,0),"") | O128: =IF(AND(Programme_Grunddaten!$A133="Geprüft",Programme_Grunddaten!W133<>""),IF(Programme_Grunddaten!W133="Ja",1,0),"") | P128: =IF(AND(Programme_Grunddaten!$A133="Geprüft",Programme_Grunddaten!X133<>""),IF(Programme_Grunddaten!X133="Ja",1,0),"") | Q128: =IF(AND(Programme_Grunddaten!$A133="Geprüft",Programme_Grunddaten!Y133<>""),IF(Programme_Grunddaten!Y133="Ja",1,0),"") | R128: =IF(AND(Programme_Grunddaten!$A133="Geprüft",Programme_Grunddaten!Z133<>""),IF(Programme_Grunddaten!Z133="Ja",1,0),"") | S128: =IF(AND(Programme_Grunddaten!$A133="Geprüft",Programme_Grunddaten!AA133<>""),IF(Programme_Grunddaten!AA133="monolithisch",1,0),"") | T128: =IF(AND(Programme_Grunddaten!$A133="Geprüft",Programme_Grunddaten!AB133<>""),IF(Programme_Grunddaten!AB133="Ja",1,0),"") | U128: =IF(AND(Programme_Grunddaten!$A133="Geprüft",Programme_Grunddaten!AC133<>""),IF(Programme_Grunddaten!AC133="Ja",1,0),"") | V128: =IF(AND(Programme_Grunddaten!$A133="Geprüft",Programme_Grunddaten!AD133<>""),IF(Programme_Grunddaten!AD133="Ja",1,0),"") | W128: =IF(AND(Programme_Grunddaten!$A133="Geprüft",Programme_Grunddaten!AE133<>""),IF(Programme_Grunddaten!AE133="Ja",1,0),"") | X128: =IF(AND(Programme_Grunddaten!$A133="Geprüft",Programme_Grunddaten!AF133<>""),IF(Programme_Grunddaten!AF133="Ja",1,0),"") | Y128: =IF(AND(Programme_Grunddaten!$A133="Geprüft",Programme_Grunddaten!AG133<>""),IF(Programme_Grunddaten!AG133="Ja",1,0),"") | Z128: =IF(AND(Programme_Grunddaten!$A133="Geprüft",Programme_Grunddaten!AH133<>""),IF(Programme_Grunddaten!AH133="Ja",1,0),"") | AA128: =IF(AND(Programme_Grunddaten!$A133="Geprüft",Programme_Grunddaten!AI133<>""),IF(Programme_Grunddaten!AI133="Ja",1,0),"") | AB128: =IF(AND(Programme_Grunddaten!$A133="Geprüft",Programme_Grunddaten!AJ133<>""),IF(Programme_Grunddaten!AJ133="individuell programmierbar",1,0),"") | AC128: =IF(AND(Programme_Grunddaten!$A133="Geprüft",Programme_Grunddaten!AK133<>""),IF(Programme_Grunddaten!AK133="Deutsch",0,IF(Programme_Grunddaten!AK133="Deutsch und Englisch",1,2)),"") | AD128: =IF(AND(Programme_Grunddaten!$A133="Geprüft",Programme_Grunddaten!AL133<>""),IF(Programme_Grunddaten!AL133="Ja",1,0),"") | AE128: =IF(AND(Programme_Grunddaten!$A133="Geprüft",Programme_Grunddaten!AM133<>""),IF(Programme_Grunddaten!AM133="Ja",1,0),"") | AF128: =IF(AND(Programme_Grunddaten!$A133="Geprüft",Programme_Grunddaten!AN133<>""),IF(Programme_Grunddaten!AN133="Ja",1,0),"") | AG128: =IF(AND(Programme_Grunddaten!$A133="Geprüft",Programme_Grunddaten!AO133<>""),IF(Programme_Grunddaten!AO133="Ja",1,0),"") | AH128: =IF(AND(Programme_Grunddaten!$A133="Geprüft",Programme_Grunddaten!AP133<>""),IF(Programme_Grunddaten!AP133="Ja",1,0),"") | AI128: =IF(AND(Programme_Grunddaten!$A133="Geprüft",Programme_Grunddaten!AQ133<>""),IF(Programme_Grunddaten!AQ133="Ja",1,0),"") | AJ128: =IF(AND(Programme_Grunddaten!$A133="Geprüft",Programme_Grunddaten!AR133<>""),IF(Programme_Grunddaten!AR133="Ja",1,0),"") | AK128: =IF(AND(Programme_Grunddaten!$A133="Geprüft",Programme_Grunddaten!AS133<>""),IF(Programme_Grunddaten!AS133="Ja",1,0),"") | ... AN128: =IF(AND(Programme_Grunddaten!$A133="Geprüft",Programme_Grunddaten!AV133<>""),IF(Programme_Grunddaten!AV133="Ja",1,0),"")
A129: =IF(AND(Programme_Grunddaten!A134="Geprüft",Programme_Grunddaten!B134<>""),Programme_Grunddaten!B134,"") | B129: =IF(AND(Programme_Grunddaten!$A134="Geprüft",Programme_Grunddaten!I134<>""),IF(Programme_Grunddaten!I134="Ja",1,0),"") | C129: =IF(AND(Programme_Grunddaten!$A134="Geprüft",Programme_Grunddaten!J134<>""),IF(Programme_Grunddaten!J134="Ja",1,0),"") | D129: =IF(AND(Programme_Grunddaten!$A134="Geprüft",Programme_Grunddaten!K134<>""),IF(Programme_Grunddaten!K134="Ja",1,0),"") | E129: =IF(AND(Programme_Grunddaten!$A134="Geprüft",Programme_Grunddaten!L134<>""),IF(Programme_Grunddaten!L134="Abo / befristete Lizenz",1,0),"") | F129: =IF(AND(Programme_Grunddaten!$A134="Geprüft",Programme_Grunddaten!M134<>""),IF(Programme_Grunddaten!M134="Ja",1,0),"") | G129: =IF(AND(Programme_Grunddaten!$A134="Geprüft",Programme_Grunddaten!N134<>""),IF(Programme_Grunddaten!N134="Ja",1,0),"") | H129: =IF(AND(Programme_Grunddaten!$A134="Geprüft",Programme_Grunddaten!O134<>""),IF(Programme_Grunddaten!O134="Deutschland",0,IF(Programme_Grunddaten!O134="EU",1,2)),"") | I129: =IF(AND(Programme_Grunddaten!$A134="Geprüft",Programme_Grunddaten!P134<>""),IF(Programme_Grunddaten!P134="Ja",1,0),"") | J129: =IF(AND(Programme_Grunddaten!$A134="Geprüft",Programme_Grunddaten!Q134<>""),IF(Programme_Grunddaten!Q134="geschlossenes System",1,0),"") | K129: =IF(AND(Programme_Grunddaten!$A134="Geprüft",Programme_Grunddaten!R134<>""),IF(Programme_Grunddaten!R134="Ja",1,0),"") | L129: =IF(AND(Programme_Grunddaten!$A134="Geprüft",Programme_Grunddaten!T134<>""),IF(Programme_Grunddaten!T134="Ja",1,0),"") | M129: =IF(AND(Programme_Grunddaten!$A134="Geprüft",Programme_Grunddaten!U134<>""),IF(Programme_Grunddaten!U134="Ja",1,0),"") | N129: =IF(AND(Programme_Grunddaten!$A134="Geprüft",Programme_Grunddaten!V134<>""),IF(Programme_Grunddaten!V134="Ja",1,0),"") | O129: =IF(AND(Programme_Grunddaten!$A134="Geprüft",Programme_Grunddaten!W134<>""),IF(Programme_Grunddaten!W134="Ja",1,0),"") | P129: =IF(AND(Programme_Grunddaten!$A134="Geprüft",Programme_Grunddaten!X134<>""),IF(Programme_Grunddaten!X134="Ja",1,0),"") | Q129: =IF(AND(Programme_Grunddaten!$A134="Geprüft",Programme_Grunddaten!Y134<>""),IF(Programme_Grunddaten!Y134="Ja",1,0),"") | R129: =IF(AND(Programme_Grunddaten!$A134="Geprüft",Programme_Grunddaten!Z134<>""),IF(Programme_Grunddaten!Z134="Ja",1,0),"") | S129: =IF(AND(Programme_Grunddaten!$A134="Geprüft",Programme_Grunddaten!AA134<>""),IF(Programme_Grunddaten!AA134="monolithisch",1,0),"") | T129: =IF(AND(Programme_Grunddaten!$A134="Geprüft",Programme_Grunddaten!AB134<>""),IF(Programme_Grunddaten!AB134="Ja",1,0),"") | U129: =IF(AND(Programme_Grunddaten!$A134="Geprüft",Programme_Grunddaten!AC134<>""),IF(Programme_Grunddaten!AC134="Ja",1,0),"") | V129: =IF(AND(Programme_Grunddaten!$A134="Geprüft",Programme_Grunddaten!AD134<>""),IF(Programme_Grunddaten!AD134="Ja",1,0),"") | W129: =IF(AND(Programme_Grunddaten!$A134="Geprüft",Programme_Grunddaten!AE134<>""),IF(Programme_Grunddaten!AE134="Ja",1,0),"") | X129: =IF(AND(Programme_Grunddaten!$A134="Geprüft",Programme_Grunddaten!AF134<>""),IF(Programme_Grunddaten!AF134="Ja",1,0),"") | Y129: =IF(AND(Programme_Grunddaten!$A134="Geprüft",Programme_Grunddaten!AG134<>""),IF(Programme_Grunddaten!AG134="Ja",1,0),"") | Z129: =IF(AND(Programme_Grunddaten!$A134="Geprüft",Programme_Grunddaten!AH134<>""),IF(Programme_Grunddaten!AH134="Ja",1,0),"") | AA129: =IF(AND(Programme_Grunddaten!$A134="Geprüft",Programme_Grunddaten!AI134<>""),IF(Programme_Grunddaten!AI134="Ja",1,0),"") | AB129: =IF(AND(Programme_Grunddaten!$A134="Geprüft",Programme_Grunddaten!AJ134<>""),IF(Programme_Grunddaten!AJ134="individuell programmierbar",1,0),"") | AC129: =IF(AND(Programme_Grunddaten!$A134="Geprüft",Programme_Grunddaten!AK134<>""),IF(Programme_Grunddaten!AK134="Deutsch",0,IF(Programme_Grunddaten!AK134="Deutsch und Englisch",1,2)),"") | AD129: =IF(AND(Programme_Grunddaten!$A134="Geprüft",Programme_Grunddaten!AL134<>""),IF(Programme_Grunddaten!AL134="Ja",1,0),"") | AE129: =IF(AND(Programme_Grunddaten!$A134="Geprüft",Programme_Grunddaten!AM134<>""),IF(Programme_Grunddaten!AM134="Ja",1,0),"") | AF129: =IF(AND(Programme_Grunddaten!$A134="Geprüft",Programme_Grunddaten!AN134<>""),IF(Programme_Grunddaten!AN134="Ja",1,0),"") | AG129: =IF(AND(Programme_Grunddaten!$A134="Geprüft",Programme_Grunddaten!AO134<>""),IF(Programme_Grunddaten!AO134="Ja",1,0),"") | AH129: =IF(AND(Programme_Grunddaten!$A134="Geprüft",Programme_Grunddaten!AP134<>""),IF(Programme_Grunddaten!AP134="Ja",1,0),"") | AI129: =IF(AND(Programme_Grunddaten!$A134="Geprüft",Programme_Grunddaten!AQ134<>""),IF(Programme_Grunddaten!AQ134="Ja",1,0),"") | AJ129: =IF(AND(Programme_Grunddaten!$A134="Geprüft",Programme_Grunddaten!AR134<>""),IF(Programme_Grunddaten!AR134="Ja",1,0),"") | AK129: =IF(AND(Programme_Grunddaten!$A134="Geprüft",Programme_Grunddaten!AS134<>""),IF(Programme_Grunddaten!AS134="Ja",1,0),"") | ... AN129: =IF(AND(Programme_Grunddaten!$A134="Geprüft",Programme_Grunddaten!AV134<>""),IF(Programme_Grunddaten!AV134="Ja",1,0),"")
A130: =IF(AND(Programme_Grunddaten!A135="Geprüft",Programme_Grunddaten!B135<>""),Programme_Grunddaten!B135,"") | B130: =IF(AND(Programme_Grunddaten!$A135="Geprüft",Programme_Grunddaten!I135<>""),IF(Programme_Grunddaten!I135="Ja",1,0),"") | C130: =IF(AND(Programme_Grunddaten!$A135="Geprüft",Programme_Grunddaten!J135<>""),IF(Programme_Grunddaten!J135="Ja",1,0),"") | D130: =IF(AND(Programme_Grunddaten!$A135="Geprüft",Programme_Grunddaten!K135<>""),IF(Programme_Grunddaten!K135="Ja",1,0),"") | E130: =IF(AND(Programme_Grunddaten!$A135="Geprüft",Programme_Grunddaten!L135<>""),IF(Programme_Grunddaten!L135="Abo / befristete Lizenz",1,0),"") | F130: =IF(AND(Programme_Grunddaten!$A135="Geprüft",Programme_Grunddaten!M135<>""),IF(Programme_Grunddaten!M135="Ja",1,0),"") | G130: =IF(AND(Programme_Grunddaten!$A135="Geprüft",Programme_Grunddaten!N135<>""),IF(Programme_Grunddaten!N135="Ja",1,0),"") | H130: =IF(AND(Programme_Grunddaten!$A135="Geprüft",Programme_Grunddaten!O135<>""),IF(Programme_Grunddaten!O135="Deutschland",0,IF(Programme_Grunddaten!O135="EU",1,2)),"") | I130: =IF(AND(Programme_Grunddaten!$A135="Geprüft",Programme_Grunddaten!P135<>""),IF(Programme_Grunddaten!P135="Ja",1,0),"") | J130: =IF(AND(Programme_Grunddaten!$A135="Geprüft",Programme_Grunddaten!Q135<>""),IF(Programme_Grunddaten!Q135="geschlossenes System",1,0),"") | K130: =IF(AND(Programme_Grunddaten!$A135="Geprüft",Programme_Grunddaten!R135<>""),IF(Programme_Grunddaten!R135="Ja",1,0),"") | L130: =IF(AND(Programme_Grunddaten!$A135="Geprüft",Programme_Grunddaten!T135<>""),IF(Programme_Grunddaten!T135="Ja",1,0),"") | M130: =IF(AND(Programme_Grunddaten!$A135="Geprüft",Programme_Grunddaten!U135<>""),IF(Programme_Grunddaten!U135="Ja",1,0),"") | N130: =IF(AND(Programme_Grunddaten!$A135="Geprüft",Programme_Grunddaten!V135<>""),IF(Programme_Grunddaten!V135="Ja",1,0),"") | O130: =IF(AND(Programme_Grunddaten!$A135="Geprüft",Programme_Grunddaten!W135<>""),IF(Programme_Grunddaten!W135="Ja",1,0),"") | P130: =IF(AND(Programme_Grunddaten!$A135="Geprüft",Programme_Grunddaten!X135<>""),IF(Programme_Grunddaten!X135="Ja",1,0),"") | Q130: =IF(AND(Programme_Grunddaten!$A135="Geprüft",Programme_Grunddaten!Y135<>""),IF(Programme_Grunddaten!Y135="Ja",1,0),"") | R130: =IF(AND(Programme_Grunddaten!$A135="Geprüft",Programme_Grunddaten!Z135<>""),IF(Programme_Grunddaten!Z135="Ja",1,0),"") | S130: =IF(AND(Programme_Grunddaten!$A135="Geprüft",Programme_Grunddaten!AA135<>""),IF(Programme_Grunddaten!AA135="monolithisch",1,0),"") | T130: =IF(AND(Programme_Grunddaten!$A135="Geprüft",Programme_Grunddaten!AB135<>""),IF(Programme_Grunddaten!AB135="Ja",1,0),"") | U130: =IF(AND(Programme_Grunddaten!$A135="Geprüft",Programme_Grunddaten!AC135<>""),IF(Programme_Grunddaten!AC135="Ja",1,0),"") | V130: =IF(AND(Programme_Grunddaten!$A135="Geprüft",Programme_Grunddaten!AD135<>""),IF(Programme_Grunddaten!AD135="Ja",1,0),"") | W130: =IF(AND(Programme_Grunddaten!$A135="Geprüft",Programme_Grunddaten!AE135<>""),IF(Programme_Grunddaten!AE135="Ja",1,0),"") | X130: =IF(AND(Programme_Grunddaten!$A135="Geprüft",Programme_Grunddaten!AF135<>""),IF(Programme_Grunddaten!AF135="Ja",1,0),"") | Y130: =IF(AND(Programme_Grunddaten!$A135="Geprüft",Programme_Grunddaten!AG135<>""),IF(Programme_Grunddaten!AG135="Ja",1,0),"") | Z130: =IF(AND(Programme_Grunddaten!$A135="Geprüft",Programme_Grunddaten!AH135<>""),IF(Programme_Grunddaten!AH135="Ja",1,0),"") | AA130: =IF(AND(Programme_Grunddaten!$A135="Geprüft",Programme_Grunddaten!AI135<>""),IF(Programme_Grunddaten!AI135="Ja",1,0),"") | AB130: =IF(AND(Programme_Grunddaten!$A135="Geprüft",Programme_Grunddaten!AJ135<>""),IF(Programme_Grunddaten!AJ135="individuell programmierbar",1,0),"") | AC130: =IF(AND(Programme_Grunddaten!$A135="Geprüft",Programme_Grunddaten!AK135<>""),IF(Programme_Grunddaten!AK135="Deutsch",0,IF(Programme_Grunddaten!AK135="Deutsch und Englisch",1,2)),"") | AD130: =IF(AND(Programme_Grunddaten!$A135="Geprüft",Programme_Grunddaten!AL135<>""),IF(Programme_Grunddaten!AL135="Ja",1,0),"") | AE130: =IF(AND(Programme_Grunddaten!$A135="Geprüft",Programme_Grunddaten!AM135<>""),IF(Programme_Grunddaten!AM135="Ja",1,0),"") | AF130: =IF(AND(Programme_Grunddaten!$A135="Geprüft",Programme_Grunddaten!AN135<>""),IF(Programme_Grunddaten!AN135="Ja",1,0),"") | AG130: =IF(AND(Programme_Grunddaten!$A135="Geprüft",Programme_Grunddaten!AO135<>""),IF(Programme_Grunddaten!AO135="Ja",1,0),"") | AH130: =IF(AND(Programme_Grunddaten!$A135="Geprüft",Programme_Grunddaten!AP135<>""),IF(Programme_Grunddaten!AP135="Ja",1,0),"") | AI130: =IF(AND(Programme_Grunddaten!$A135="Geprüft",Programme_Grunddaten!AQ135<>""),IF(Programme_Grunddaten!AQ135="Ja",1,0),"") | AJ130: =IF(AND(Programme_Grunddaten!$A135="Geprüft",Programme_Grunddaten!AR135<>""),IF(Programme_Grunddaten!AR135="Ja",1,0),"") | AK130: =IF(AND(Programme_Grunddaten!$A135="Geprüft",Programme_Grunddaten!AS135<>""),IF(Programme_Grunddaten!AS135="Ja",1,0),"") | ... AN130: =IF(AND(Programme_Grunddaten!$A135="Geprüft",Programme_Grunddaten!AV135<>""),IF(Programme_Grunddaten!AV135="Ja",1,0),"")
A131: =IF(AND(Programme_Grunddaten!A136="Geprüft",Programme_Grunddaten!B136<>""),Programme_Grunddaten!B136,"") | B131: =IF(AND(Programme_Grunddaten!$A136="Geprüft",Programme_Grunddaten!I136<>""),IF(Programme_Grunddaten!I136="Ja",1,0),"") | C131: =IF(AND(Programme_Grunddaten!$A136="Geprüft",Programme_Grunddaten!J136<>""),IF(Programme_Grunddaten!J136="Ja",1,0),"") | D131: =IF(AND(Programme_Grunddaten!$A136="Geprüft",Programme_Grunddaten!K136<>""),IF(Programme_Grunddaten!K136="Ja",1,0),"") | E131: =IF(AND(Programme_Grunddaten!$A136="Geprüft",Programme_Grunddaten!L136<>""),IF(Programme_Grunddaten!L136="Abo / befristete Lizenz",1,0),"") | F131: =IF(AND(Programme_Grunddaten!$A136="Geprüft",Programme_Grunddaten!M136<>""),IF(Programme_Grunddaten!M136="Ja",1,0),"") | G131: =IF(AND(Programme_Grunddaten!$A136="Geprüft",Programme_Grunddaten!N136<>""),IF(Programme_Grunddaten!N136="Ja",1,0),"") | H131: =IF(AND(Programme_Grunddaten!$A136="Geprüft",Programme_Grunddaten!O136<>""),IF(Programme_Grunddaten!O136="Deutschland",0,IF(Programme_Grunddaten!O136="EU",1,2)),"") | I131: =IF(AND(Programme_Grunddaten!$A136="Geprüft",Programme_Grunddaten!P136<>""),IF(Programme_Grunddaten!P136="Ja",1,0),"") | J131: =IF(AND(Programme_Grunddaten!$A136="Geprüft",Programme_Grunddaten!Q136<>""),IF(Programme_Grunddaten!Q136="geschlossenes System",1,0),"") | K131: =IF(AND(Programme_Grunddaten!$A136="Geprüft",Programme_Grunddaten!R136<>""),IF(Programme_Grunddaten!R136="Ja",1,0),"") | L131: =IF(AND(Programme_Grunddaten!$A136="Geprüft",Programme_Grunddaten!T136<>""),IF(Programme_Grunddaten!T136="Ja",1,0),"") | M131: =IF(AND(Programme_Grunddaten!$A136="Geprüft",Programme_Grunddaten!U136<>""),IF(Programme_Grunddaten!U136="Ja",1,0),"") | N131: =IF(AND(Programme_Grunddaten!$A136="Geprüft",Programme_Grunddaten!V136<>""),IF(Programme_Grunddaten!V136="Ja",1,0),"") | O131: =IF(AND(Programme_Grunddaten!$A136="Geprüft",Programme_Grunddaten!W136<>""),IF(Programme_Grunddaten!W136="Ja",1,0),"") | P131: =IF(AND(Programme_Grunddaten!$A136="Geprüft",Programme_Grunddaten!X136<>""),IF(Programme_Grunddaten!X136="Ja",1,0),"") | Q131: =IF(AND(Programme_Grunddaten!$A136="Geprüft",Programme_Grunddaten!Y136<>""),IF(Programme_Grunddaten!Y136="Ja",1,0),"") | R131: =IF(AND(Programme_Grunddaten!$A136="Geprüft",Programme_Grunddaten!Z136<>""),IF(Programme_Grunddaten!Z136="Ja",1,0),"") | S131: =IF(AND(Programme_Grunddaten!$A136="Geprüft",Programme_Grunddaten!AA136<>""),IF(Programme_Grunddaten!AA136="monolithisch",1,0),"") | T131: =IF(AND(Programme_Grunddaten!$A136="Geprüft",Programme_Grunddaten!AB136<>""),IF(Programme_Grunddaten!AB136="Ja",1,0),"") | U131: =IF(AND(Programme_Grunddaten!$A136="Geprüft",Programme_Grunddaten!AC136<>""),IF(Programme_Grunddaten!AC136="Ja",1,0),"") | V131: =IF(AND(Programme_Grunddaten!$A136="Geprüft",Programme_Grunddaten!AD136<>""),IF(Programme_Grunddaten!AD136="Ja",1,0),"") | W131: =IF(AND(Programme_Grunddaten!$A136="Geprüft",Programme_Grunddaten!AE136<>""),IF(Programme_Grunddaten!AE136="Ja",1,0),"") | X131: =IF(AND(Programme_Grunddaten!$A136="Geprüft",Programme_Grunddaten!AF136<>""),IF(Programme_Grunddaten!AF136="Ja",1,0),"") | Y131: =IF(AND(Programme_Grunddaten!$A136="Geprüft",Programme_Grunddaten!AG136<>""),IF(Programme_Grunddaten!AG136="Ja",1,0),"") | Z131: =IF(AND(Programme_Grunddaten!$A136="Geprüft",Programme_Grunddaten!AH136<>""),IF(Programme_Grunddaten!AH136="Ja",1,0),"") | AA131: =IF(AND(Programme_Grunddaten!$A136="Geprüft",Programme_Grunddaten!AI136<>""),IF(Programme_Grunddaten!AI136="Ja",1,0),"") | AB131: =IF(AND(Programme_Grunddaten!$A136="Geprüft",Programme_Grunddaten!AJ136<>""),IF(Programme_Grunddaten!AJ136="individuell programmierbar",1,0),"") | AC131: =IF(AND(Programme_Grunddaten!$A136="Geprüft",Programme_Grunddaten!AK136<>""),IF(Programme_Grunddaten!AK136="Deutsch",0,IF(Programme_Grunddaten!AK136="Deutsch und Englisch",1,2)),"") | AD131: =IF(AND(Programme_Grunddaten!$A136="Geprüft",Programme_Grunddaten!AL136<>""),IF(Programme_Grunddaten!AL136="Ja",1,0),"") | AE131: =IF(AND(Programme_Grunddaten!$A136="Geprüft",Programme_Grunddaten!AM136<>""),IF(Programme_Grunddaten!AM136="Ja",1,0),"") | AF131: =IF(AND(Programme_Grunddaten!$A136="Geprüft",Programme_Grunddaten!AN136<>""),IF(Programme_Grunddaten!AN136="Ja",1,0),"") | AG131: =IF(AND(Programme_Grunddaten!$A136="Geprüft",Programme_Grunddaten!AO136<>""),IF(Programme_Grunddaten!AO136="Ja",1,0),"") | AH131: =IF(AND(Programme_Grunddaten!$A136="Geprüft",Programme_Grunddaten!AP136<>""),IF(Programme_Grunddaten!AP136="Ja",1,0),"") | AI131: =IF(AND(Programme_Grunddaten!$A136="Geprüft",Programme_Grunddaten!AQ136<>""),IF(Programme_Grunddaten!AQ136="Ja",1,0),"") | AJ131: =IF(AND(Programme_Grunddaten!$A136="Geprüft",Programme_Grunddaten!AR136<>""),IF(Programme_Grunddaten!AR136="Ja",1,0),"") | AK131: =IF(AND(Programme_Grunddaten!$A136="Geprüft",Programme_Grunddaten!AS136<>""),IF(Programme_Grunddaten!AS136="Ja",1,0),"") | ... AN131: =IF(AND(Programme_Grunddaten!$A136="Geprüft",Programme_Grunddaten!AV136<>""),IF(Programme_Grunddaten!AV136="Ja",1,0),"")
A132: =IF(AND(Programme_Grunddaten!A137="Geprüft",Programme_Grunddaten!B137<>""),Programme_Grunddaten!B137,"") | B132: =IF(AND(Programme_Grunddaten!$A137="Geprüft",Programme_Grunddaten!I137<>""),IF(Programme_Grunddaten!I137="Ja",1,0),"") | C132: =IF(AND(Programme_Grunddaten!$A137="Geprüft",Programme_Grunddaten!J137<>""),IF(Programme_Grunddaten!J137="Ja",1,0),"") | D132: =IF(AND(Programme_Grunddaten!$A137="Geprüft",Programme_Grunddaten!K137<>""),IF(Programme_Grunddaten!K137="Ja",1,0),"") | E132: =IF(AND(Programme_Grunddaten!$A137="Geprüft",Programme_Grunddaten!L137<>""),IF(Programme_Grunddaten!L137="Abo / befristete Lizenz",1,0),"") | F132: =IF(AND(Programme_Grunddaten!$A137="Geprüft",Programme_Grunddaten!M137<>""),IF(Programme_Grunddaten!M137="Ja",1,0),"") | G132: =IF(AND(Programme_Grunddaten!$A137="Geprüft",Programme_Grunddaten!N137<>""),IF(Programme_Grunddaten!N137="Ja",1,0),"") | H132: =IF(AND(Programme_Grunddaten!$A137="Geprüft",Programme_Grunddaten!O137<>""),IF(Programme_Grunddaten!O137="Deutschland",0,IF(Programme_Grunddaten!O137="EU",1,2)),"") | I132: =IF(AND(Programme_Grunddaten!$A137="Geprüft",Programme_Grunddaten!P137<>""),IF(Programme_Grunddaten!P137="Ja",1,0),"") | J132: =IF(AND(Programme_Grunddaten!$A137="Geprüft",Programme_Grunddaten!Q137<>""),IF(Programme_Grunddaten!Q137="geschlossenes System",1,0),"") | K132: =IF(AND(Programme_Grunddaten!$A137="Geprüft",Programme_Grunddaten!R137<>""),IF(Programme_Grunddaten!R137="Ja",1,0),"") | L132: =IF(AND(Programme_Grunddaten!$A137="Geprüft",Programme_Grunddaten!T137<>""),IF(Programme_Grunddaten!T137="Ja",1,0),"") | M132: =IF(AND(Programme_Grunddaten!$A137="Geprüft",Programme_Grunddaten!U137<>""),IF(Programme_Grunddaten!U137="Ja",1,0),"") | N132: =IF(AND(Programme_Grunddaten!$A137="Geprüft",Programme_Grunddaten!V137<>""),IF(Programme_Grunddaten!V137="Ja",1,0),"") | O132: =IF(AND(Programme_Grunddaten!$A137="Geprüft",Programme_Grunddaten!W137<>""),IF(Programme_Grunddaten!W137="Ja",1,0),"") | P132: =IF(AND(Programme_Grunddaten!$A137="Geprüft",Programme_Grunddaten!X137<>""),IF(Programme_Grunddaten!X137="Ja",1,0),"") | Q132: =IF(AND(Programme_Grunddaten!$A137="Geprüft",Programme_Grunddaten!Y137<>""),IF(Programme_Grunddaten!Y137="Ja",1,0),"") | R132: =IF(AND(Programme_Grunddaten!$A137="Geprüft",Programme_Grunddaten!Z137<>""),IF(Programme_Grunddaten!Z137="Ja",1,0),"") | S132: =IF(AND(Programme_Grunddaten!$A137="Geprüft",Programme_Grunddaten!AA137<>""),IF(Programme_Grunddaten!AA137="monolithisch",1,0),"") | T132: =IF(AND(Programme_Grunddaten!$A137="Geprüft",Programme_Grunddaten!AB137<>""),IF(Programme_Grunddaten!AB137="Ja",1,0),"") | U132: =IF(AND(Programme_Grunddaten!$A137="Geprüft",Programme_Grunddaten!AC137<>""),IF(Programme_Grunddaten!AC137="Ja",1,0),"") | V132: =IF(AND(Programme_Grunddaten!$A137="Geprüft",Programme_Grunddaten!AD137<>""),IF(Programme_Grunddaten!AD137="Ja",1,0),"") | W132: =IF(AND(Programme_Grunddaten!$A137="Geprüft",Programme_Grunddaten!AE137<>""),IF(Programme_Grunddaten!AE137="Ja",1,0),"") | X132: =IF(AND(Programme_Grunddaten!$A137="Geprüft",Programme_Grunddaten!AF137<>""),IF(Programme_Grunddaten!AF137="Ja",1,0),"") | Y132: =IF(AND(Programme_Grunddaten!$A137="Geprüft",Programme_Grunddaten!AG137<>""),IF(Programme_Grunddaten!AG137="Ja",1,0),"") | Z132: =IF(AND(Programme_Grunddaten!$A137="Geprüft",Programme_Grunddaten!AH137<>""),IF(Programme_Grunddaten!AH137="Ja",1,0),"") | AA132: =IF(AND(Programme_Grunddaten!$A137="Geprüft",Programme_Grunddaten!AI137<>""),IF(Programme_Grunddaten!AI137="Ja",1,0),"") | AB132: =IF(AND(Programme_Grunddaten!$A137="Geprüft",Programme_Grunddaten!AJ137<>""),IF(Programme_Grunddaten!AJ137="individuell programmierbar",1,0),"") | AC132: =IF(AND(Programme_Grunddaten!$A137="Geprüft",Programme_Grunddaten!AK137<>""),IF(Programme_Grunddaten!AK137="Deutsch",0,IF(Programme_Grunddaten!AK137="Deutsch und Englisch",1,2)),"") | AD132: =IF(AND(Programme_Grunddaten!$A137="Geprüft",Programme_Grunddaten!AL137<>""),IF(Programme_Grunddaten!AL137="Ja",1,0),"") | AE132: =IF(AND(Programme_Grunddaten!$A137="Geprüft",Programme_Grunddaten!AM137<>""),IF(Programme_Grunddaten!AM137="Ja",1,0),"") | AF132: =IF(AND(Programme_Grunddaten!$A137="Geprüft",Programme_Grunddaten!AN137<>""),IF(Programme_Grunddaten!AN137="Ja",1,0),"") | AG132: =IF(AND(Programme_Grunddaten!$A137="Geprüft",Programme_Grunddaten!AO137<>""),IF(Programme_Grunddaten!AO137="Ja",1,0),"") | AH132: =IF(AND(Programme_Grunddaten!$A137="Geprüft",Programme_Grunddaten!AP137<>""),IF(Programme_Grunddaten!AP137="Ja",1,0),"") | AI132: =IF(AND(Programme_Grunddaten!$A137="Geprüft",Programme_Grunddaten!AQ137<>""),IF(Programme_Grunddaten!AQ137="Ja",1,0),"") | AJ132: =IF(AND(Programme_Grunddaten!$A137="Geprüft",Programme_Grunddaten!AR137<>""),IF(Programme_Grunddaten!AR137="Ja",1,0),"") | AK132: =IF(AND(Programme_Grunddaten!$A137="Geprüft",Programme_Grunddaten!AS137<>""),IF(Programme_Grunddaten!AS137="Ja",1,0),"") | ... AN132: =IF(AND(Programme_Grunddaten!$A137="Geprüft",Programme_Grunddaten!AV137<>""),IF(Programme_Grunddaten!AV137="Ja",1,0),"")
